Workbook

Sheet 経営比較
A1: Guard・Send・セット 経営比較
A2: 選択条件は4行に表示。共通率は前提と出典E4〜E6。価格・配分は正式決定ではない。
A4: 選択Guard案 | B4: =INDEX('前提と出典'!A41:A43,'前提と出典'!$B$15+1) -> G2二段階 | D4: 選択Send案 | E4: =INDEX('前提と出典'!A46:A48,'前提と出典'!$B$16+1) -> D | G4: 割引 | H4: ='前提と出典'!$B$17 -> 500
A6: 共通配分率 | B6: 初回黒字企業数 | C6: 継続黒字企業数 | D6: 両サービス継続黒字 | E6: 100社差引 | F6: 100社Guard差引 | G6: 100社Send差引
A7: ='前提と出典'!E4 -> 0.3 | B7: =IF(MIN('利益曲線'!AA5:AA1004)>1000,"範囲内なし",MIN('利益曲線'!AA5:AA1004)) -> 23 | C7: =IF(MAX('利益曲線'!AB5:AB1004)>=1000,"範囲内なし",MAX(1,MAX('利益曲線'!AB5:AB1004)+1)) -> 23 | D7: =IF(MAX('利益曲線'!AC5:AC1004)>=1000,"範囲内なし",MAX(1,MAX('利益曲線'!AC5:AC1004)+1)) -> 48 | E7: =INDEX('利益曲線'!T5:T1004,100) -> 193091.39 | F7: =INDEX('利益曲線'!R5:R1004,100) -> 154716.56 | G7: =INDEX('利益曲線'!S5:S1004,100) -> 38374.824
A8: ='前提と出典'!E5 -> 0.4 | B8: =IF(MIN('利益曲線'!AD5:AD1004)>1000,"範囲内なし",MIN('利益曲線'!AD5:AD1004)) -> 25 | C8: =IF(MAX('利益曲線'!AE5:AE1004)>=1000,"範囲内なし",MAX(1,MAX('利益曲線'!AE5:AE1004)+1)) -> 25 | D8: =IF(MAX('利益曲線'!AF5:AF1004)>=1000,"範囲内なし",MAX(1,MAX('利益曲線'!AF5:AF1004)+1)) -> 53 | E8: =INDEX('利益曲線'!W5:W1004,100) -> 166147.99 | F8: =INDEX('利益曲線'!U5:U1004,100) -> 135367.12 | G8: =INDEX('利益曲線'!V5:V1004,100) -> 30780.87
A9: ='前提と出典'!E6 -> 0.5 | B9: =IF(MIN('利益曲線'!AG5:AG1004)>1000,"範囲内なし",MIN('利益曲線'!AG5:AG1004)) -> 29 | C9: =IF(MAX('利益曲線'!AH5:AH1004)>=1000,"範囲内なし",MAX(1,MAX('利益曲線'!AH5:AH1004)+1)) -> 29 | D9: =IF(MAX('利益曲線'!AI5:AI1004)>=1000,"範囲内なし",MAX(1,MAX('利益曲線'!AI5:AI1004)+1)) -> 60 | E9: =INDEX('利益曲線'!Z5:Z1004,100) -> 139204.59 | F9: =INDEX('利益曲線'!X5:X1004,100) -> 116017.67 | G9: =INDEX('利益曲線'!Y5:Y1004,100) -> 23186.915
A12: 企業数 | B12: 総売上 | C12: 基本料金net | D12: 従量売上 | E12: 率2配分 | F12: DNS仕入 | G12: G+S infra運用 | H12: 決済手数料 | I12: 率2後差引
A13: 10 | B13: =INDEX('利益曲線'!E5:E1004,A13)+INDEX('利益曲線'!F5:F1004,A13)+INDEX('利益曲線'!G5:G1004,A13)+INDEX('利益曲線'!H5:H1004,A13) -> 53756.472 | C13: =INDEX('利益曲線'!E5:E1004,A13)+INDEX('利益曲線'!F5:F1004,A13) -> 26943.401 | D13: =INDEX('利益曲線'!G5:G1004,A13)+INDEX('利益曲線'!H5:H1004,A13) -> 26813.071 | E13: =C13*'前提と出典'!E5 -> 10777.361 | F13: =INDEX('利益曲線'!O5:O1004,A13) -> 22500 | G13: =INDEX('利益曲線'!I5:I1004,A13)+INDEX('利益曲線'!J5:J1004,A13)+INDEX('利益曲線'!K5:K1004,A13)+INDEX('利益曲線'!L5:L1004,A13)+INDEX('利益曲線'!M5:M1004,A13)+INDEX('利益曲線'!N5:N1004,A13) -> 49059.089 | H13: =B13*'前提と出典'!$B$7 -> 1935.233 | I13: =INDEX('利益曲線'!W5:W1004,A13) -> -30515.21
A14: 30 | B14: =INDEX('利益曲線'!E5:E1004,A14)+INDEX('利益曲線'!F5:F1004,A14)+INDEX('利益曲線'!G5:G1004,A14)+INDEX('利益曲線'!H5:H1004,A14) -> 161269.42 | C14: =INDEX('利益曲線'!E5:E1004,A14)+INDEX('利益曲線'!F5:F1004,A14) -> 80830.204 | D14: =INDEX('利益曲線'!G5:G1004,A14)+INDEX('利益曲線'!H5:H1004,A14) -> 80439.213 | E14: =C14*'前提と出典'!E5 -> 32332.082 | F14: =INDEX('利益曲線'!O5:O1004,A14) -> 29789.497 | G14: =INDEX('利益曲線'!I5:I1004,A14)+INDEX('利益曲線'!J5:J1004,A14)+INDEX('利益曲線'!K5:K1004,A14)+INDEX('利益曲線'!L5:L1004,A14)+INDEX('利益曲線'!M5:M1004,A14)+INDEX('利益曲線'!N5:N1004,A14) -> 81655.397 | H14: =B14*'前提と出典'!$B$7 -> 5805.699 | I14: =INDEX('利益曲線'!W5:W1004,A14) -> 11686.742
A15: 50 | B15: =INDEX('利益曲線'!E5:E1004,A15)+INDEX('利益曲線'!F5:F1004,A15)+INDEX('利益曲線'!G5:G1004,A15)+INDEX('利益曲線'!H5:H1004,A15) -> 268782.36 | C15: =INDEX('利益曲線'!E5:E1004,A15)+INDEX('利益曲線'!F5:F1004,A15) -> 134717.01 | D15: =INDEX('利益曲線'!G5:G1004,A15)+INDEX('利益曲線'!H5:H1004,A15) -> 134065.35 | E15: =C15*'前提と出典'!E5 -> 53886.803 | F15: =INDEX('利益曲線'!O5:O1004,A15) -> 49649.162 | G15: =INDEX('利益曲線'!I5:I1004,A15)+INDEX('利益曲線'!J5:J1004,A15)+INDEX('利益曲線'!K5:K1004,A15)+INDEX('利益曲線'!L5:L1004,A15)+INDEX('利益曲線'!M5:M1004,A15)+INDEX('利益曲線'!N5:N1004,A15) -> 99751.706 | H15: =B15*'前提と出典'!$B$7 -> 9676.165 | I15: =INDEX('利益曲線'!W5:W1004,A15) -> 55818.526
A16: 100 | B16: =INDEX('利益曲線'!E5:E1004,A16)+INDEX('利益曲線'!F5:F1004,A16)+INDEX('利益曲線'!G5:G1004,A16)+INDEX('利益曲線'!H5:H1004,A16) -> 537564.72 | C16: =INDEX('利益曲線'!E5:E1004,A16)+INDEX('利益曲線'!F5:F1004,A16) -> 269434.01 | D16: =INDEX('利益曲線'!G5:G1004,A16)+INDEX('利益曲線'!H5:H1004,A16) -> 268130.71 | E16: =C16*'前提と出典'!E5 -> 107773.61 | F16: =INDEX('利益曲線'!O5:O1004,A16) -> 99298.324 | G16: =INDEX('利益曲線'!I5:I1004,A16)+INDEX('利益曲線'!J5:J1004,A16)+INDEX('利益曲線'!K5:K1004,A16)+INDEX('利益曲線'!L5:L1004,A16)+INDEX('利益曲線'!M5:M1004,A16)+INDEX('利益曲線'!N5:N1004,A16) -> 144992.48 | H16: =B16*'前提と出典'!$B$7 -> 19352.33 | I16: =INDEX('利益曲線'!W5:W1004,A16) -> 166147.99
A17: 300 | B17: =INDEX('利益曲線'!E5:E1004,A17)+INDEX('利益曲線'!F5:F1004,A17)+INDEX('利益曲線'!G5:G1004,A17)+INDEX('利益曲線'!H5:H1004,A17) -> 1612694.2 | C17: =INDEX('利益曲線'!E5:E1004,A17)+INDEX('利益曲線'!F5:F1004,A17) -> 808302.04 | D17: =INDEX('利益曲線'!G5:G1004,A17)+INDEX('利益曲線'!H5:H1004,A17) -> 804392.13 | E17: =C17*'前提と出典'!E5 -> 323320.82 | F17: =INDEX('利益曲線'!O5:O1004,A17) -> 297894.97 | G17: =INDEX('利益曲線'!I5:I1004,A17)+INDEX('利益曲線'!J5:J1004,A17)+INDEX('利益曲線'!K5:K1004,A17)+INDEX('利益曲線'!L5:L1004,A17)+INDEX('利益曲線'!M5:M1004,A17)+INDEX('利益曲線'!N5:N1004,A17) -> 367955.56 | H17: =B17*'前提と出典'!$B$7 -> 58056.99 | I17: =INDEX('利益曲線'!W5:W1004,A17) -> 565465.83
A18: 1000 | B18: =INDEX('利益曲線'!E5:E1004,A18)+INDEX('利益曲線'!F5:F1004,A18)+INDEX('利益曲線'!G5:G1004,A18)+INDEX('利益曲線'!H5:H1004,A18) -> 5375647.2 | C18: =INDEX('利益曲線'!E5:E1004,A18)+INDEX('利益曲線'!F5:F1004,A18) -> 2694340.1 | D18: =INDEX('利益曲線'!G5:G1004,A18)+INDEX('利益曲線'!H5:H1004,A18) -> 2681307.1 | E18: =C18*'前提と出典'!E5 -> 1077736.1 | F18: =INDEX('利益曲線'!O5:O1004,A18) -> 992983.24 | G18: =INDEX('利益曲線'!I5:I1004,A18)+INDEX('利益曲線'!J5:J1004,A18)+INDEX('利益曲線'!K5:K1004,A18)+INDEX('利益曲線'!L5:L1004,A18)+INDEX('利益曲線'!M5:M1004,A18)+INDEX('利益曲線'!N5:N1004,A18) -> 1071326.4 | H18: =B18*'前提と出典'!$B$7 -> 193523.3 | I18: =INDEX('利益曲線'!W5:W1004,A18) -> 2040078.3
A21: 共通率 | B21: 単月黒字月 | C21: 累積回収月 | D21: 最大累積赤字 | E21: 36月累積差引
A22: ='前提と出典'!E4 -> 0.3 | B22: =IF(MIN('累積回収'!AH5:AH40)>36,"36月内なし",MIN('累積回収'!AH5:AH40)) -> 8 | C22: =IF(MIN('累積回収'!AI5:AI40)>36,"36月内なし",MIN('累積回収'!AI5:AI40)) -> 14 | D22: =MAX('累積回収'!AE5:AE40) -> 185180 | E22: ='累積回収'!AB40 -> 2973111.4
A23: ='前提と出典'!E5 -> 0.4 | B23: =IF(MIN('累積回収'!AJ5:AJ40)>36,"36月内なし",MIN('累積回収'!AJ5:AJ40)) -> 9 | C23: =IF(MIN('累積回収'!AK5:AK40)>36,"36月内なし",MIN('累積回収'!AK5:AK40)) -> 16 | D23: =MAX('累積回収'!AF5:AF40) -> 209365.25 | E23: ='累積回収'!AC40 -> 2434782.2
A24: ='前提と出典'!E6 -> 0.5 | B24: =IF(MIN('累積回収'!AL5:AL40)>36,"36月内なし",MIN('累積回収'!AL5:AL40)) -> 10 | C24: =IF(MIN('累積回収'!AM5:AM40)>36,"36月内なし",MIN('累積回収'!AM5:AM40)) -> 18 | D24: =MAX('累積回収'!AG5:AG40) -> 240671.87 | E24: ='累積回収'!AD40 -> 1896453
A27: 初期費用 | B27: =IF('前提と出典'!$B$32="","未入力・未算入",'前提と出典'!$B$32) -> 未入力・未算入
A28: 導入率からの対象企業数 | B28: ='前提と出典'!$B$28*'前提と出典'!$B$29 -> 100
A29: 参照Guard/Send/Set対象率 | B29: ='契約別単価'!B5 -> 0.895 | C29: ='契約別単価'!B6 -> 0.995 | D29: ='契約別単価'!B7 -> 0.895
A31: 各価格・比率・為替・利用・割引は前提と出典で変更。契約形態だけの評価はB34で1/2/3を選択。
A32: セット合計黒字とGuard/Send独立黒字を分ける。51送信者以上・101PC以上は要見積。
A33: 同一企業の規模仮説はPR14のPC帯を再利用。前回の全国従業者ベンチマークによるSend分布と別の感度。
A35: 共通率 | B35: 導入目標社数時の差引 | C35: 導入目標時DNS原価
A36: ='前提と出典'!E4 -> 0.3 | B36: =IF(OR(B28<1,B28>1000),"評価範囲外",INDEX('利益曲線'!T5:T1004,ROUNDUP(B28,0))) -> 193091.39 | C36: =IF(OR(B28<1,B28>1000),"評価範囲外",INDEX('利益曲線'!O5:O1004,ROUNDUP(B28,0))) -> 99298.324
A37: ='前提と出典'!E5 -> 0.4 | B37: =IF(OR(B28<1,B28>1000),"評価範囲外",INDEX('利益曲線'!W5:W1004,ROUNDUP(B28,0))) -> 166147.99 | C37: =IF(OR(B28<1,B28>1000),"評価範囲外",INDEX('利益曲線'!O5:O1004,ROUNDUP(B28,0))) -> 99298.324
A38: ='前提と出典'!E6 -> 0.5 | B38: =IF(OR(B28<1,B28>1000),"評価範囲外",INDEX('利益曲線'!Z5:Z1004,ROUNDUP(B28,0))) -> 139204.59 | C38: =IF(OR(B28<1,B28>1000),"評価範囲外",INDEX('利益曲線'!O5:O1004,ROUNDUP(B28,0))) -> 99298.324
A40: 導入目標と対象社数の整合 | B40: =IF(AND(B28*('前提と出典'!C36+'前提と出典'!C38)<='前提と出典'!B28*'契約別単価'!B5,B28*('前提と出典'!C37+'前提と出典'!C38)<='前提と出典'!B28*'契約別単価'!B6,B28*'前提と出典'!C38<='前提と出典'!B28*'契約別単価'!B7),"仮定内","構成比を再設定") -> 仮定内

Sheet 前提と出典
A1: Secure Services 共通料金・原価の設定
A2: 青字は仮定・選択。実請求・公表・仮定を区分。料金・配分は正式決定ではない。
A4: 為替 JPY/USD | B4: 150 | D4: シェア率比較 | E4: 0.3
A5: DNS単価 USD/台 | B5: 0.92 | D5: シェア率比較 | E5: 0.4
A6: MSP最低 USD/月 | B6: 150 | D6: シェア率比較 | E6: 0.5
A7: 決済手数料率 | B7: 0.036
A8: 運用時給 | B8: 4000
A9: Guard support分/社 | B9: 8
A10: Guard support分/PC | B10: 0.1 | D10: 低位送信職務倍率 | E10: 0.5
A11: Guard変動JPY/社 | B11: 50 | D11: 基準送信職務倍率 | E11: 1
A12: Guard変動JPY/PC | B12: 1 | D12: 高位送信職務倍率 | E12: 1.5
A13: Send送信者JPY/名 | B13: 200
A14: 同一企業シナリオ0低1基2高 | B14: 1
A15: Guard案0現行1二段2三段 | B15: 1
A16: Send案0A1C2D | B16: 2
A17: セット基本割引 | B17: 500
A18: Send利用0低1標2高3上限 | B18: 1
A19: 割引按分0比例1Guard負担 | B19: 0
A20: MSP原価0最低内包1加算 | B20: 0
A21: 現場中心企業の仮比率 | B21: 0.7
A22: 現場型の従業者倍率 | B22: 1.5
A23: 事務型の従業者倍率 | B23: 0.75
A24: 現場型の送信者職務率 | B24: 0.1
... A31: 月間解約率 | B31: 0
A32: 初期投資JPY・未入力除外
A33: Guard従量0一律1累進 | B33: 1
A34: 契約構成0下記1G2S3セット | B34: 0
A35: 契約構成 | B35: 入力比率 | C35: 正規化・有効比率
A36: Guardのみ | B36: 0.4 | C36: =IF($B$34=0,B36/SUM($B$36:$B$38),IF($B$34=1,1,0)) -> 0.4
A37: Sendのみ | B37: 0.3 | C37: =IF($B$34=0,B37/SUM($B$36:$B$38),IF($B$34=2,1,0)) -> 0.3
A38: セット | B38: 0.3 | C38: =IF($B$34=0,B38/SUM($B$36:$B$38),IF($B$34=3,1,0)) -> 0.3
A40: Guard基本案 | B40: 上限1 | C40: 料金1 | D40: 上限2 | E40: 料金2 | F40: 上限3 | G40: 料金3
A41: G0基本5000比較 | B41: 100 | C41: 5000 | D41: 100 | E41: 5000 | F41: 100 | G41: 5000
A42: G2二段階 | B42: 10 | C42: 2500 | D42: 100 | E42: 4000 | F42: 100 | G42: 4000
A43: G3三段階 | B43: 5 | C43: 2000 | D43: 20 | E43: 3000 | F43: 100 | G43: 4500
A45: Send基本案 | B45: 上限1 | C45: 料金1 | D45: 上限2 | E45: 料金2 | F45: 上限3 | G45: 料金3 | H45: 上限4 | I45: 料金4
A46: A | B46: 10 | C46: 1500 | D46: 50 | E46: 3000 | F46: 50 | G46: 3000 | H46: 50 | I46: 3000
A47: C | B47: 5 | C47: 1000 | D47: 10 | E47: 1500 | F47: 30 | G47: 2500 | H47: 50 | I47: 4000
A48: D | B48: 10 | C48: 1200 | D48: 50 | E48: 2500 | F48: 50 | G48: 2500 | H48: 50 | I48: 2500
A51: Windows PC代表 | B51: 従業者規模アンカー | C51: 低位重み | D51: 基準重み | E51: 高位重み
A52: 0 | B52: 4 | C52: 0.2 | D52: 0.1 | E52: 0.05
A53: 3 | B53: 10 | C53: 0.45 | D53: 0.37 | E53: 0.25
A54: 8 | B54: 25 | C54: 0.24 | D54: 0.28 | E54: 0.25
A55: 18 | B55: 60 | C55: 0.09 | D55: 0.2 | E55: 0.3
A56: 40 | B56: 120 | C56: 0.015 | D56: 0.03 | E56: 0.09
A57: 70 | B57: 200 | C57: 0.004 | D57: 0.015 | E57: 0.04
A58: 130 | B58: 400 | C58: 0.001 | D58: 0.005 | E58: 0.02
A60: PC重みはPR14の仮定。従業者アンカー・業種型比率・職務率は今回の共同分布仮定。実測ではない。
A62: Run CPU 円/秒 | B62: 0.0038862386
A63: Run memory 円/GiB秒 | B63: 0.00039526863
A66: Send利用 | B66: 送信/名 | C66: file/送信 | D66: MiB/file | E66: DL倍率 | F66: OTP/送信 | G66: scan秒/file | H66: support分/社
A67: 低位 | B67: 5 | C67: 1 | D67: 2 | E67: 1 | F67: 1.1 | G67: 1 | H67: 3
A68: 標準 | B68: 20 | C68: 2 | D68: 10 | E68: 1.5 | F68: 1.8 | G68: 2 | H68: 8
A69: 高位 | B69: 80 | C69: 3 | D69: 50 | E69: 2 | F69: 2.5 | G69: 5 | H69: 20
A72: 企業数上限 | B72: Guard固定infra | C72: Guard固定運用 | D72: Send固定infra | E72: Send固定運用
A73: 10 | B73: 2000 | C73: 8000 | D73: 22010.935 | E73: 8000
A74: 100 | B74: 4000 | C74: 16000 | D74: 26510.935 | E74: 8000
A75: 500 | B75: 8000 | C75: 32000 | D75: 48510.935 | E75: 8000
A76: 1000 | B76: 16000 | C76: 64000 | D76: 78510.935 | E76: 8000
A79: Send費用ドライバー | B79: 固定変動JPY/社 | C79: 変動JPY/送信者 | D79: supportJPY/社 | E79: supportJPY/送信者 | F79: 容量取扱比率
A80: 低位 | B80: 50 | C80: =2+F80*((B67*.3+B67*E67*.2)*($B$62+.5*$B$63)+(B67*C67*G67*.3+B67*C67/1000*20)*($B$62+4*$B$63)+B67*(1+F67)*.1+(B67*C67*(.005+(2+E67)*.0004)/1000+B67*(12/1048576*.5+8/1e6*.4)+(B67*C67*D67/1024)*(28/30*.025+E67*.12)+B67*C67*3*.4/1e6)*$B$4) -> 3.2911599 | D80: =H67/60*$B$8 -> 200 | E80: =.1/60*$B$8 -> 6.6666667 | F80: 1
A81: 標準 | B81: 50 | C81: =2+F81*((B68*.3+B68*E68*.2)*($B$62+.5*$B$63)+(B68*C68*G68*.3+B68*C68/1000*20)*($B$62+4*$B$63)+B68*(1+F68)*.1+(B68*C68*(.005+(2+E68)*.0004)/1000+B68*(12/1048576*.5+8/1e6*.4)+(B68*C68*D68/1024)*(28/30*.025+E68*.12)+B68*C68*3*.4/1e6)*$B$4) -> 19.771024 | D81: =H68/60*$B$8 -> 533.33333 | E81: =.1/60*$B$8 -> 6.6666667 | F81: 1
A82: 高位 | B82: 50 | C82: =2+F82*((B69*.3+B69*E69*.2)*($B$62+.5*$B$63)+(B69*C69*G69*.3+B69*C69/1000*20)*($B$62+4*$B$63)+B69*(1+F69)*.1+(B69*C69*(.005+(2+E69)*.0004)/1000+B69*(12/1048576*.5+8/1e6*.4)+(B69*C69*D69/1024)*(28/30*.025+E69*.12)+B69*C69*3*.4/1e6)*$B$4) -> 495.50166 | D82: =H69/60*$B$8 -> 1333.3333 | E82: =.1/60*$B$8 -> 6.6666667 | F82: 1
A83: 高位上限 | B83: 50 | C83: =2+F83*((B69*.3+B69*E69*.2)*($B$62+.5*$B$63)+(B69*C69*G69*.3+B69*C69/1000*20)*($B$62+4*$B$63)+B69*(1+F69)*.1+(B69*C69*(.005+(2+E69)*.0004)/1000+B69*(12/1048576*.5+8/1e6*.4)+(B69*C69*D69/1024)*(28/30*.025+E69*.12)+B69*C69*3*.4/1e6)*$B$4) -> 44.112142 | D83: =H69/60*$B$8 -> 1333.3333 | E83: =.1/60*$B$8 -> 6.6666667 | F83: =MIN(1,$B$26/(B69*C69*D69/1024),$B$27/(B69*C69*D69/1024*E69)) -> 0.085333333
A85: 出典: Corporate PR14 40b7610 / Issue16・17 / PR7 23b887d / PR9 932bf38、Send PR3 74facb2。
A86: DNS .92は表示値・実契約未確認。公式MSP starts150、標準Core月額1.15。最低額との関係は未確認。
A87: Guard固定費/サポートは新規予算仮定。Sendは専用SQL/非同期min0の既存予算。Production構成とは別。
A88: 初期投資が空欄なら未算入。営業・導入・事故・税・入金時差を含まない。赤字許容額は未設定。
A89: 固定条件比較は作成時の2,079ケース。編集後は経営比較・利益曲線・累積回収が再計算。固定表は更新しない。
A90: https://www.dnsfilter.com/pricing 2026-10-18閲覧。詳細根拠は統合レポートとcanonical-sources.json。

Sheet 同一企業モデル
A1: 同一企業の従業者・PC・送信者（相関仮定）
A2: 同じPC帯・企業規模・職務型から送信者を作る。独立平均の掛算はしない。0PCでもSendは利用可能。
A4: シナリオ | B4: PC帯番号 | C4: 企業型 | D4: 重み | E4: 従業者 | F4: Windows PC | G4: 有料送信者 | H4: G料金対象 | I4: S料金対象 | J4: セット対象 | K4: 選択重み | L4: G基本 | M4: G従量 | N4: S基本 | O4: S従量 | P4: セット割引 | Q4: G割引按分 | R4: S割引按分 | S4: G変動infra | T4: Gsupport | U4: S変動infra | V4: Ssupport | W4: セットG基本 | X4: セットS基本
A5: 0 | B5: 0 | C5: 0 | D5: ='前提と出典'!C52*'前提と出典'!$B$21 -> 0.14 | E5: =ROUNDUP('前提と出典'!B52*'前提と出典'!$B$22,0) -> 6 | F5: ='前提と出典'!A52 -> 0 | G5: =MAX(1,ROUNDUP(E5*'前提と出典'!$B$24*'前提と出典'!E10,0)) -> 1 | H5: =IF(AND(F5>=1,F5<=100),1,0) -> 0 | I5: =IF(G5<=50,1,0) -> 1 | J5: =H5*I5 -> 0 | K5: =IF(A5='前提と出典'!$B$14,D5,0) -> 0 | L5: =IF(H5=0,0,IF(F5<=INDEX('前提と出典'!B41:B43,'前提と出典'!$B$15+1),INDEX('前提と出典'!C41:C43,'前提と出典'!$B$15+1),IF(F5<=INDEX('前提と出典'!D41:D43,'前提と出典'!$B$15+1),INDEX('前提と出典'!E41:E43,'前提と出典'!$B$15+1),INDEX('前提と出典'!G41:G43,'前提と出典'!$B$15+1)))) -> 0 | M5: =IF(H5=0,0,IF('前提と出典'!$B$33=1,MIN(F5,10)*300+MIN(MAX(0,F5-10),20)*250+MAX(0,F5-30)*200,F5*300)) -> 0 | N5: =IF(I5=0,0,IF(G5<=INDEX('前提と出典'!B46:B48,'前提と出典'!$B$16+1),INDEX('前提と出典'!C46:C48,'前提と出典'!$B$16+1),IF(G5<=INDEX('前提と出典'!D46:D48,'前提と出典'!$B$16+1),INDEX('前提と出典'!E46:E48,'前提と出典'!$B$16+1),IF(G5<=INDEX('前提と出典'!F46:F48,'前提と出典'!$B$16+1),INDEX('前提と出典'!G46:G48,'前提と出典'!$B$16+1),INDEX('前提と出典'!I46:I48,'前提と出典'!$B$16+1))))) -> 1200 | O5: =IF(I5=1,G5*'前提と出典'!$B$13,0) -> 200 | P5: =IF(J5=1,MIN('前提と出典'!$B$17,L5+N5),0) -> 0 | Q5: =IF(J5=0,0,IF('前提と出典'!$B$19=0,P5*L5/(L5+N5),MIN(P5,L5))) -> 0 | R5: =P5-Q5 -> 0 | S5: =IF(H5=1,'前提と出典'!$B$11+F5*'前提と出典'!$B$12,0) -> 0 | T5: =IF(H5=1,('前提と出典'!$B$9+F5*'前提と出典'!$B$10)/60*'前提と出典'!$B$8,0) -> 0 | U5: =IF(I5=1,INDEX('前提と出典'!B80:B83,'前提と出典'!$B$18+1)+G5*INDEX('前提と出典'!C80:C83,'前提と出典'!$B$18+1),0) -> 69.771024 | V5: =IF(I5=1,INDEX('前提と出典'!D80:D83,'前提と出典'!$B$18+1)+G5*INDEX('前提と出典'!E80:E83,'前提と出典'!$B$18+1),0) -> 540 | W5: =L5-Q5 -> 0 | X5: =N5-R5 -> 1200
A6: 0 | B6: 0 | C6: 1 | D6: ='前提と出典'!C52*(1-'前提と出典'!$B$21) -> 0.06 | E6: =ROUNDUP('前提と出典'!B52*'前提と出典'!$B$23,0) -> 3 | F6: ='前提と出典'!A52 -> 0 | G6: =MAX(1,ROUNDUP(E6*'前提と出典'!$B$25*'前提と出典'!E10,0)) -> 1 | H6: =IF(AND(F6>=1,F6<=100),1,0) -> 0 | I6: =IF(G6<=50,1,0) -> 1 | J6: =H6*I6 -> 0 | K6: =IF(A6='前提と出典'!$B$14,D6,0) -> 0 | L6: =IF(H6=0,0,IF(F6<=INDEX('前提と出典'!B41:B43,'前提と出典'!$B$15+1),INDEX('前提と出典'!C41:C43,'前提と出典'!$B$15+1),IF(F6<=INDEX('前提と出典'!D41:D43,'前提と出典'!$B$15+1),INDEX('前提と出典'!E41:E43,'前提と出典'!$B$15+1),INDEX('前提と出典'!G41:G43,'前提と出典'!$B$15+1)))) -> 0 | M6: =IF(H6=0,0,IF('前提と出典'!$B$33=1,MIN(F6,10)*300+MIN(MAX(0,F6-10),20)*250+MAX(0,F6-30)*200,F6*300)) -> 0 | N6: =IF(I6=0,0,IF(G6<=INDEX('前提と出典'!B46:B48,'前提と出典'!$B$16+1),INDEX('前提と出典'!C46:C48,'前提と出典'!$B$16+1),IF(G6<=INDEX('前提と出典'!D46:D48,'前提と出典'!$B$16+1),INDEX('前提と出典'!E46:E48,'前提と出典'!$B$16+1),IF(G6<=INDEX('前提と出典'!F46:F48,'前提と出典'!$B$16+1),INDEX('前提と出典'!G46:G48,'前提と出典'!$B$16+1),INDEX('前提と出典'!I46:I48,'前提と出典'!$B$16+1))))) -> 1200 | O6: =IF(I6=1,G6*'前提と出典'!$B$13,0) -> 200 | P6: =IF(J6=1,MIN('前提と出典'!$B$17,L6+N6),0) -> 0 | Q6: =IF(J6=0,0,IF('前提と出典'!$B$19=0,P6*L6/(L6+N6),MIN(P6,L6))) -> 0 | R6: =P6-Q6 -> 0 | S6: =IF(H6=1,'前提と出典'!$B$11+F6*'前提と出典'!$B$12,0) -> 0 | T6: =IF(H6=1,('前提と出典'!$B$9+F6*'前提と出典'!$B$10)/60*'前提と出典'!$B$8,0) -> 0 | U6: =IF(I6=1,INDEX('前提と出典'!B80:B83,'前提と出典'!$B$18+1)+G6*INDEX('前提と出典'!C80:C83,'前提と出典'!$B$18+1),0) -> 69.771024 | V6: =IF(I6=1,INDEX('前提と出典'!D80:D83,'前提と出典'!$B$18+1)+G6*INDEX('前提と出典'!E80:E83,'前提と出典'!$B$18+1),0) -> 540 | W6: =L6-Q6 -> 0 | X6: =N6-R6 -> 1200
A7: 0 | B7: 1 | C7: 0 | D7: ='前提と出典'!C53*'前提と出典'!$B$21 -> 0.315 | E7: =ROUNDUP('前提と出典'!B53*'前提と出典'!$B$22,0) -> 15 | F7: ='前提と出典'!A53 -> 3 | G7: =MAX(1,ROUNDUP(E7*'前提と出典'!$B$24*'前提と出典'!E10,0)) -> 1 | H7: =IF(AND(F7>=1,F7<=100),1,0) -> 1 | I7: =IF(G7<=50,1,0) -> 1 | J7: =H7*I7 -> 1 | K7: =IF(A7='前提と出典'!$B$14,D7,0) -> 0 | L7: =IF(H7=0,0,IF(F7<=INDEX('前提と出典'!B41:B43,'前提と出典'!$B$15+1),INDEX('前提と出典'!C41:C43,'前提と出典'!$B$15+1),IF(F7<=INDEX('前提と出典'!D41:D43,'前提と出典'!$B$15+1),INDEX('前提と出典'!E41:E43,'前提と出典'!$B$15+1),INDEX('前提と出典'!G41:G43,'前提と出典'!$B$15+1)))) -> 2500 | M7: =IF(H7=0,0,IF('前提と出典'!$B$33=1,MIN(F7,10)*300+MIN(MAX(0,F7-10),20)*250+MAX(0,F7-30)*200,F7*300)) -> 900 | N7: =IF(I7=0,0,IF(G7<=INDEX('前提と出典'!B46:B48,'前提と出典'!$B$16+1),INDEX('前提と出典'!C46:C48,'前提と出典'!$B$16+1),IF(G7<=INDEX('前提と出典'!D46:D48,'前提と出典'!$B$16+1),INDEX('前提と出典'!E46:E48,'前提と出典'!$B$16+1),IF(G7<=INDEX('前提と出典'!F46:F48,'前提と出典'!$B$16+1),INDEX('前提と出典'!G46:G48,'前提と出典'!$B$16+1),INDEX('前提と出典'!I46:I48,'前提と出典'!$B$16+1))))) -> 1200 | O7: =IF(I7=1,G7*'前提と出典'!$B$13,0) -> 200 | P7: =IF(J7=1,MIN('前提と出典'!$B$17,L7+N7),0) -> 500 | Q7: =IF(J7=0,0,IF('前提と出典'!$B$19=0,P7*L7/(L7+N7),MIN(P7,L7))) -> 337.83784 | R7: =P7-Q7 -> 162.16216 | S7: =IF(H7=1,'前提と出典'!$B$11+F7*'前提と出典'!$B$12,0) -> 53 | T7: =IF(H7=1,('前提と出典'!$B$9+F7*'前提と出典'!$B$10)/60*'前提と出典'!$B$8,0) -> 553.33333 | U7: =IF(I7=1,INDEX('前提と出典'!B80:B83,'前提と出典'!$B$18+1)+G7*INDEX('前提と出典'!C80:C83,'前提と出典'!$B$18+1),0) -> 69.771024 | V7: =IF(I7=1,INDEX('前提と出典'!D80:D83,'前提と出典'!$B$18+1)+G7*INDEX('前提と出典'!E80:E83,'前提と出典'!$B$18+1),0) -> 540 | W7: =L7-Q7 -> 2162.1622 | X7: =N7-R7 -> 1037.8378
A8: 0 | B8: 1 | C8: 1 | D8: ='前提と出典'!C53*(1-'前提と出典'!$B$21) -> 0.135 | E8: =ROUNDUP('前提と出典'!B53*'前提と出典'!$B$23,0) -> 8 | F8: ='前提と出典'!A53 -> 3 | G8: =MAX(1,ROUNDUP(E8*'前提と出典'!$B$25*'前提と出典'!E10,0)) -> 2 | H8: =IF(AND(F8>=1,F8<=100),1,0) -> 1 | I8: =IF(G8<=50,1,0) -> 1 | J8: =H8*I8 -> 1 | K8: =IF(A8='前提と出典'!$B$14,D8,0) -> 0 | L8: =IF(H8=0,0,IF(F8<=INDEX('前提と出典'!B41:B43,'前提と出典'!$B$15+1),INDEX('前提と出典'!C41:C43,'前提と出典'!$B$15+1),IF(F8<=INDEX('前提と出典'!D41:D43,'前提と出典'!$B$15+1),INDEX('前提と出典'!E41:E43,'前提と出典'!$B$15+1),INDEX('前提と出典'!G41:G43,'前提と出典'!$B$15+1)))) -> 2500 | M8: =IF(H8=0,0,IF('前提と出典'!$B$33=1,MIN(F8,10)*300+MIN(MAX(0,F8-10),20)*250+MAX(0,F8-30)*200,F8*300)) -> 900 | N8: =IF(I8=0,0,IF(G8<=INDEX('前提と出典'!B46:B48,'前提と出典'!$B$16+1),INDEX('前提と出典'!C46:C48,'前提と出典'!$B$16+1),IF(G8<=INDEX('前提と出典'!D46:D48,'前提と出典'!$B$16+1),INDEX('前提と出典'!E46:E48,'前提と出典'!$B$16+1),IF(G8<=INDEX('前提と出典'!F46:F48,'前提と出典'!$B$16+1),INDEX('前提と出典'!G46:G48,'前提と出典'!$B$16+1),INDEX('前提と出典'!I46:I48,'前提と出典'!$B$16+1))))) -> 1200 | O8: =IF(I8=1,G8*'前提と出典'!$B$13,0) -> 400 | P8: =IF(J8=1,MIN('前提と出典'!$B$17,L8+N8),0) -> 500 | Q8: =IF(J8=0,0,IF('前提と出典'!$B$19=0,P8*L8/(L8+N8),MIN(P8,L8))) -> 337.83784 | R8: =P8-Q8 -> 162.16216 | S8: =IF(H8=1,'前提と出典'!$B$11+F8*'前提と出典'!$B$12,0) -> 53 | T8: =IF(H8=1,('前提と出典'!$B$9+F8*'前提と出典'!$B$10)/60*'前提と出典'!$B$8,0) -> 553.33333 | U8: =IF(I8=1,INDEX('前提と出典'!B80:B83,'前提と出典'!$B$18+1)+G8*INDEX('前提と出典'!C80:C83,'前提と出典'!$B$18+1),0) -> 89.542049 | V8: =IF(I8=1,INDEX('前提と出典'!D80:D83,'前提と出典'!$B$18+1)+G8*INDEX('前提と出典'!E80:E83,'前提と出典'!$B$18+1),0) -> 546.66667 | W8: =L8-Q8 -> 2162.1622 | X8: =N8-R8 -> 1037.8378
A9: 0 | B9: 2 | C9: 0 | D9: ='前提と出典'!C54*'前提と出典'!$B$21 -> 0.168 | E9: =ROUNDUP('前提と出典'!B54*'前提と出典'!$B$22,0) -> 38 | F9: ='前提と出典'!A54 -> 8 | G9: =MAX(1,ROUNDUP(E9*'前提と出典'!$B$24*'前提と出典'!E10,0)) -> 2 | H9: =IF(AND(F9>=1,F9<=100),1,0) -> 1 | I9: =IF(G9<=50,1,0) -> 1 | J9: =H9*I9 -> 1 | K9: =IF(A9='前提と出典'!$B$14,D9,0) -> 0 | L9: =IF(H9=0,0,IF(F9<=INDEX('前提と出典'!B41:B43,'前提と出典'!$B$15+1),INDEX('前提と出典'!C41:C43,'前提と出典'!$B$15+1),IF(F9<=INDEX('前提と出典'!D41:D43,'前提と出典'!$B$15+1),INDEX('前提と出典'!E41:E43,'前提と出典'!$B$15+1),INDEX('前提と出典'!G41:G43,'前提と出典'!$B$15+1)))) -> 2500 | M9: =IF(H9=0,0,IF('前提と出典'!$B$33=1,MIN(F9,10)*300+MIN(MAX(0,F9-10),20)*250+MAX(0,F9-30)*200,F9*300)) -> 2400 | N9: =IF(I9=0,0,IF(G9<=INDEX('前提と出典'!B46:B48,'前提と出典'!$B$16+1),INDEX('前提と出典'!C46:C48,'前提と出典'!$B$16+1),IF(G9<=INDEX('前提と出典'!D46:D48,'前提と出典'!$B$16+1),INDEX('前提と出典'!E46:E48,'前提と出典'!$B$16+1),IF(G9<=INDEX('前提と出典'!F46:F48,'前提と出典'!$B$16+1),INDEX('前提と出典'!G46:G48,'前提と出典'!$B$16+1),INDEX('前提と出典'!I46:I48,'前提と出典'!$B$16+1))))) -> 1200 | O9: =IF(I9=1,G9*'前提と出典'!$B$13,0) -> 400 | P9: =IF(J9=1,MIN('前提と出典'!$B$17,L9+N9),0) -> 500 | Q9: =IF(J9=0,0,IF('前提と出典'!$B$19=0,P9*L9/(L9+N9),MIN(P9,L9))) -> 337.83784 | R9: =P9-Q9 -> 162.16216 | S9: =IF(H9=1,'前提と出典'!$B$11+F9*'前提と出典'!$B$12,0) -> 58 | T9: =IF(H9=1,('前提と出典'!$B$9+F9*'前提と出典'!$B$10)/60*'前提と出典'!$B$8,0) -> 586.66667 | U9: =IF(I9=1,INDEX('前提と出典'!B80:B83,'前提と出典'!$B$18+1)+G9*INDEX('前提と出典'!C80:C83,'前提と出典'!$B$18+1),0) -> 89.542049 | V9: =IF(I9=1,INDEX('前提と出典'!D80:D83,'前提と出典'!$B$18+1)+G9*INDEX('前提と出典'!E80:E83,'前提と出典'!$B$18+1),0) -> 546.66667 | W9: =L9-Q9 -> 2162.1622 | X9: =N9-R9 -> 1037.8378
A10: 0 | B10: 2 | C10: 1 | D10: ='前提と出典'!C54*(1-'前提と出典'!$B$21) -> 0.072 | E10: =ROUNDUP('前提と出典'!B54*'前提と出典'!$B$23,0) -> 19 | F10: ='前提と出典'!A54 -> 8 | G10: =MAX(1,ROUNDUP(E10*'前提と出典'!$B$25*'前提と出典'!E10,0)) -> 3 | H10: =IF(AND(F10>=1,F10<=100),1,0) -> 1 | I10: =IF(G10<=50,1,0) -> 1 | J10: =H10*I10 -> 1 | K10: =IF(A10='前提と出典'!$B$14,D10,0) -> 0 | L10: =IF(H10=0,0,IF(F10<=INDEX('前提と出典'!B41:B43,'前提と出典'!$B$15+1),INDEX('前提と出典'!C41:C43,'前提と出典'!$B$15+1),IF(F10<=INDEX('前提と出典'!D41:D43,'前提と出典'!$B$15+1),INDEX('前提と出典'!E41:E43,'前提と出典'!$B$15+1),INDEX('前提と出典'!G41:G43,'前提と出典'!$B$15+1)))) -> 2500 | M10: =IF(H10=0,0,IF('前提と出典'!$B$33=1,MIN(F10,10)*300+MIN(MAX(0,F10-10),20)*250+MAX(0,F10-30)*200,F10*300)) -> 2400 | N10: =IF(I10=0,0,IF(G10<=INDEX('前提と出典'!B46:B48,'前提と出典'!$B$16+1),INDEX('前提と出典'!C46:C48,'前提と出典'!$B$16+1),IF(G10<=INDEX('前提と出典'!D46:D48,'前提と出典'!$B$16+1),INDEX('前提と出典'!E46:E48,'前提と出典'!$B$16+1),IF(G10<=INDEX('前提と出典'!F46:F48,'前提と出典'!$B$16+1),INDEX('前提と出典'!G46:G48,'前提と出典'!$B$16+1),INDEX('前提と出典'!I46:I48,'前提と出典'!$B$16+1))))) -> 1200 | O10: =IF(I10=1,G10*'前提と出典'!$B$13,0) -> 600 | P10: =IF(J10=1,MIN('前提と出典'!$B$17,L10+N10),0) -> 500 | Q10: =IF(J10=0,0,IF('前提と出典'!$B$19=0,P10*L10/(L10+N10),MIN(P10,L10))) -> 337.83784 | R10: =P10-Q10 -> 162.16216 | S10: =IF(H10=1,'前提と出典'!$B$11+F10*'前提と出典'!$B$12,0) -> 58 | T10: =IF(H10=1,('前提と出典'!$B$9+F10*'前提と出典'!$B$10)/60*'前提と出典'!$B$8,0) -> 586.66667 | U10: =IF(I10=1,INDEX('前提と出典'!B80:B83,'前提と出典'!$B$18+1)+G10*INDEX('前提と出典'!C80:C83,'前提と出典'!$B$18+1),0) -> 109.31307 | V10: =IF(I10=1,INDEX('前提と出典'!D80:D83,'前提と出典'!$B$18+1)+G10*INDEX('前提と出典'!E80:E83,'前提と出典'!$B$18+1),0) -> 553.33333 | W10: =L10-Q10 -> 2162.1622 | X10: =N10-R10 -> 1037.8378
A11: 0 | B11: 3 | C11: 0 | D11: ='前提と出典'!C55*'前提と出典'!$B$21 -> 0.063 | E11: =ROUNDUP('前提と出典'!B55*'前提と出典'!$B$22,0) -> 90 | F11: ='前提と出典'!A55 -> 18 | G11: =MAX(1,ROUNDUP(E11*'前提と出典'!$B$24*'前提と出典'!E10,0)) -> 5 | H11: =IF(AND(F11>=1,F11<=100),1,0) -> 1 | I11: =IF(G11<=50,1,0) -> 1 | J11: =H11*I11 -> 1 | K11: =IF(A11='前提と出典'!$B$14,D11,0) -> 0 | L11: =IF(H11=0,0,IF(F11<=INDEX('前提と出典'!B41:B43,'前提と出典'!$B$15+1),INDEX('前提と出典'!C41:C43,'前提と出典'!$B$15+1),IF(F11<=INDEX('前提と出典'!D41:D43,'前提と出典'!$B$15+1),INDEX('前提と出典'!E41:E43,'前提と出典'!$B$15+1),INDEX('前提と出典'!G41:G43,'前提と出典'!$B$15+1)))) -> 4000 | M11: =IF(H11=0,0,IF('前提と出典'!$B$33=1,MIN(F11,10)*300+MIN(MAX(0,F11-10),20)*250+MAX(0,F11-30)*200,F11*300)) -> 5000 | N11: =IF(I11=0,0,IF(G11<=INDEX('前提と出典'!B46:B48,'前提と出典'!$B$16+1),INDEX('前提と出典'!C46:C48,'前提と出典'!$B$16+1),IF(G11<=INDEX('前提と出典'!D46:D48,'前提と出典'!$B$16+1),INDEX('前提と出典'!E46:E48,'前提と出典'!$B$16+1),IF(G11<=INDEX('前提と出典'!F46:F48,'前提と出典'!$B$16+1),INDEX('前提と出典'!G46:G48,'前提と出典'!$B$16+1),INDEX('前提と出典'!I46:I48,'前提と出典'!$B$16+1))))) -> 1200 | O11: =IF(I11=1,G11*'前提と出典'!$B$13,0) -> 1000 | P11: =IF(J11=1,MIN('前提と出典'!$B$17,L11+N11),0) -> 500 | Q11: =IF(J11=0,0,IF('前提と出典'!$B$19=0,P11*L11/(L11+N11),MIN(P11,L11))) -> 384.61538 | R11: =P11-Q11 -> 115.38462 | S11: =IF(H11=1,'前提と出典'!$B$11+F11*'前提と出典'!$B$12,0) -> 68 | T11: =IF(H11=1,('前提と出典'!$B$9+F11*'前提と出典'!$B$10)/60*'前提と出典'!$B$8,0) -> 653.33333 | U11: =IF(I11=1,INDEX('前提と出典'!B80:B83,'前提と出典'!$B$18+1)+G11*INDEX('前提と出典'!C80:C83,'前提と出典'!$B$18+1),0) -> 148.85512 | V11: =IF(I11=1,INDEX('前提と出典'!D80:D83,'前提と出典'!$B$18+1)+G11*INDEX('前提と出典'!E80:E83,'前提と出典'!$B$18+1),0) -> 566.66667 | W11: =L11-Q11 -> 3615.3846 | X11: =N11-R11 -> 1084.6154
A12: 0 | B12: 3 | C12: 1 | D12: ='前提と出典'!C55*(1-'前提と出典'!$B$21) -> 0.027 | E12: =ROUNDUP('前提と出典'!B55*'前提と出典'!$B$23,0) -> 45 | F12: ='前提と出典'!A55 -> 18 | G12: =MAX(1,ROUNDUP(E12*'前提と出典'!$B$25*'前提と出典'!E10,0)) -> 7 | H12: =IF(AND(F12>=1,F12<=100),1,0) -> 1 | I12: =IF(G12<=50,1,0) -> 1 | J12: =H12*I12 -> 1 | K12: =IF(A12='前提と出典'!$B$14,D12,0) -> 0 | L12: =IF(H12=0,0,IF(F12<=INDEX('前提と出典'!B41:B43,'前提と出典'!$B$15+1),INDEX('前提と出典'!C41:C43,'前提と出典'!$B$15+1),IF(F12<=INDEX('前提と出典'!D41:D43,'前提と出典'!$B$15+1),INDEX('前提と出典'!E41:E43,'前提と出典'!$B$15+1),INDEX('前提と出典'!G41:G43,'前提と出典'!$B$15+1)))) -> 4000 | M12: =IF(H12=0,0,IF('前提と出典'!$B$33=1,MIN(F12,10)*300+MIN(MAX(0,F12-10),20)*250+MAX(0,F12-30)*200,F12*300)) -> 5000 | N12: =IF(I12=0,0,IF(G12<=INDEX('前提と出典'!B46:B48,'前提と出典'!$B$16+1),INDEX('前提と出典'!C46:C48,'前提と出典'!$B$16+1),IF(G12<=INDEX('前提と出典'!D46:D48,'前提と出典'!$B$16+1),INDEX('前提と出典'!E46:E48,'前提と出典'!$B$16+1),IF(G12<=INDEX('前提と出典'!F46:F48,'前提と出典'!$B$16+1),INDEX('前提と出典'!G46:G48,'前提と出典'!$B$16+1),INDEX('前提と出典'!I46:I48,'前提と出典'!$B$16+1))))) -> 1200 | O12: =IF(I12=1,G12*'前提と出典'!$B$13,0) -> 1400 | P12: =IF(J12=1,MIN('前提と出典'!$B$17,L12+N12),0) -> 500 | Q12: =IF(J12=0,0,IF('前提と出典'!$B$19=0,P12*L12/(L12+N12),MIN(P12,L12))) -> 384.61538 | R12: =P12-Q12 -> 115.38462 | S12: =IF(H12=1,'前提と出典'!$B$11+F12*'前提と出典'!$B$12,0) -> 68 | T12: =IF(H12=1,('前提と出典'!$B$9+F12*'前提と出典'!$B$10)/60*'前提と出典'!$B$8,0) -> 653.33333 | U12: =IF(I12=1,INDEX('前提と出典'!B80:B83,'前提と出典'!$B$18+1)+G12*INDEX('前提と出典'!C80:C83,'前提と出典'!$B$18+1),0) -> 188.39717 | V12: =IF(I12=1,INDEX('前提と出典'!D80:D83,'前提と出典'!$B$18+1)+G12*INDEX('前提と出典'!E80:E83,'前提と出典'!$B$18+1),0) -> 580 | W12: =L12-Q12 -> 3615.3846 | X12: =N12-R12 -> 1084.6154
A13: 0 | B13: 4 | C13: 0 | D13: ='前提と出典'!C56*'前提と出典'!$B$21 -> 0.0105 | E13: =ROUNDUP('前提と出典'!B56*'前提と出典'!$B$22,0) -> 180 | F13: ='前提と出典'!A56 -> 40 | G13: =MAX(1,ROUNDUP(E13*'前提と出典'!$B$24*'前提と出典'!E10,0)) -> 9 | H13: =IF(AND(F13>=1,F13<=100),1,0) -> 1 | I13: =IF(G13<=50,1,0) -> 1 | J13: =H13*I13 -> 1 | K13: =IF(A13='前提と出典'!$B$14,D13,0) -> 0 | L13: =IF(H13=0,0,IF(F13<=INDEX('前提と出典'!B41:B43,'前提と出典'!$B$15+1),INDEX('前提と出典'!C41:C43,'前提と出典'!$B$15+1),IF(F13<=INDEX('前提と出典'!D41:D43,'前提と出典'!$B$15+1),INDEX('前提と出典'!E41:E43,'前提と出典'!$B$15+1),INDEX('前提と出典'!G41:G43,'前提と出典'!$B$15+1)))) -> 4000 | M13: =IF(H13=0,0,IF('前提と出典'!$B$33=1,MIN(F13,10)*300+MIN(MAX(0,F13-10),20)*250+MAX(0,F13-30)*200,F13*300)) -> 10000 | N13: =IF(I13=0,0,IF(G13<=INDEX('前提と出典'!B46:B48,'前提と出典'!$B$16+1),INDEX('前提と出典'!C46:C48,'前提と出典'!$B$16+1),IF(G13<=INDEX('前提と出典'!D46:D48,'前提と出典'!$B$16+1),INDEX('前提と出典'!E46:E48,'前提と出典'!$B$16+1),IF(G13<=INDEX('前提と出典'!F46:F48,'前提と出典'!$B$16+1),INDEX('前提と出典'!G46:G48,'前提と出典'!$B$16+1),INDEX('前提と出典'!I46:I48,'前提と出典'!$B$16+1))))) -> 1200 | O13: =IF(I13=1,G13*'前提と出典'!$B$13,0) -> 1800 | P13: =IF(J13=1,MIN('前提と出典'!$B$17,L13+N13),0) -> 500 | Q13: =IF(J13=0,0,IF('前提と出典'!$B$19=0,P13*L13/(L13+N13),MIN(P13,L13))) -> 384.61538 | R13: =P13-Q13 -> 115.38462 | S13: =IF(H13=1,'前提と出典'!$B$11+F13*'前提と出典'!$B$12,0) -> 90 | T13: =IF(H13=1,('前提と出典'!$B$9+F13*'前提と出典'!$B$10)/60*'前提と出典'!$B$8,0) -> 800 | U13: =IF(I13=1,INDEX('前提と出典'!B80:B83,'前提と出典'!$B$18+1)+G13*INDEX('前提と出典'!C80:C83,'前提と出典'!$B$18+1),0) -> 227.93922 | V13: =IF(I13=1,INDEX('前提と出典'!D80:D83,'前提と出典'!$B$18+1)+G13*INDEX('前提と出典'!E80:E83,'前提と出典'!$B$18+1),0) -> 593.33333 | W13: =L13-Q13 -> 3615.3846 | X13: =N13-R13 -> 1084.6154
A14: 0 | B14: 4 | C14: 1 | D14: ='前提と出典'!C56*(1-'前提と出典'!$B$21) -> 0.0045 | E14: =ROUNDUP('前提と出典'!B56*'前提と出典'!$B$23,0) -> 90 | F14: ='前提と出典'!A56 -> 40 | G14: =MAX(1,ROUNDUP(E14*'前提と出典'!$B$25*'前提と出典'!E10,0)) -> 14 | H14: =IF(AND(F14>=1,F14<=100),1,0) -> 1 | I14: =IF(G14<=50,1,0) -> 1 | J14: =H14*I14 -> 1 | K14: =IF(A14='前提と出典'!$B$14,D14,0) -> 0 | L14: =IF(H14=0,0,IF(F14<=INDEX('前提と出典'!B41:B43,'前提と出典'!$B$15+1),INDEX('前提と出典'!C41:C43,'前提と出典'!$B$15+1),IF(F14<=INDEX('前提と出典'!D41:D43,'前提と出典'!$B$15+1),INDEX('前提と出典'!E41:E43,'前提と出典'!$B$15+1),INDEX('前提と出典'!G41:G43,'前提と出典'!$B$15+1)))) -> 4000 | M14: =IF(H14=0,0,IF('前提と出典'!$B$33=1,MIN(F14,10)*300+MIN(MAX(0,F14-10),20)*250+MAX(0,F14-30)*200,F14*300)) -> 10000 | N14: =IF(I14=0,0,IF(G14<=INDEX('前提と出典'!B46:B48,'前提と出典'!$B$16+1),INDEX('前提と出典'!C46:C48,'前提と出典'!$B$16+1),IF(G14<=INDEX('前提と出典'!D46:D48,'前提と出典'!$B$16+1),INDEX('前提と出典'!E46:E48,'前提と出典'!$B$16+1),IF(G14<=INDEX('前提と出典'!F46:F48,'前提と出典'!$B$16+1),INDEX('前提と出典'!G46:G48,'前提と出典'!$B$16+1),INDEX('前提と出典'!I46:I48,'前提と出典'!$B$16+1))))) -> 2500 | O14: =IF(I14=1,G14*'前提と出典'!$B$13,0) -> 2800 | P14: =IF(J14=1,MIN('前提と出典'!$B$17,L14+N14),0) -> 500 | Q14: =IF(J14=0,0,IF('前提と出典'!$B$19=0,P14*L14/(L14+N14),MIN(P14,L14))) -> 307.69231 | R14: =P14-Q14 -> 192.30769 | S14: =IF(H14=1,'前提と出典'!$B$11+F14*'前提と出典'!$B$12,0) -> 90 | T14: =IF(H14=1,('前提と出典'!$B$9+F14*'前提と出典'!$B$10)/60*'前提と出典'!$B$8,0) -> 800 | U14: =IF(I14=1,INDEX('前提と出典'!B80:B83,'前提と出典'!$B$18+1)+G14*INDEX('前提と出典'!C80:C83,'前提と出典'!$B$18+1),0) -> 326.79434 | V14: =IF(I14=1,INDEX('前提と出典'!D80:D83,'前提と出典'!$B$18+1)+G14*INDEX('前提と出典'!E80:E83,'前提と出典'!$B$18+1),0) -> 626.66667 | W14: =L14-Q14 -> 3692.3077 | X14: =N14-R14 -> 2307.6923
A15: 0 | B15: 5 | C15: 0 | D15: ='前提と出典'!C57*'前提と出典'!$B$21 -> 0.0028 | E15: =ROUNDUP('前提と出典'!B57*'前提と出典'!$B$22,0) -> 300 | F15: ='前提と出典'!A57 -> 70 | G15: =MAX(1,ROUNDUP(E15*'前提と出典'!$B$24*'前提と出典'!E10,0)) -> 15 | H15: =IF(AND(F15>=1,F15<=100),1,0) -> 1 | I15: =IF(G15<=50,1,0) -> 1 | J15: =H15*I15 -> 1 | K15: =IF(A15='前提と出典'!$B$14,D15,0) -> 0 | L15: =IF(H15=0,0,IF(F15<=INDEX('前提と出典'!B41:B43,'前提と出典'!$B$15+1),INDEX('前提と出典'!C41:C43,'前提と出典'!$B$15+1),IF(F15<=INDEX('前提と出典'!D41:D43,'前提と出典'!$B$15+1),INDEX('前提と出典'!E41:E43,'前提と出典'!$B$15+1),INDEX('前提と出典'!G41:G43,'前提と出典'!$B$15+1)))) -> 4000 | M15: =IF(H15=0,0,IF('前提と出典'!$B$33=1,MIN(F15,10)*300+MIN(MAX(0,F15-10),20)*250+MAX(0,F15-30)*200,F15*300)) -> 16000 | N15: =IF(I15=0,0,IF(G15<=INDEX('前提と出典'!B46:B48,'前提と出典'!$B$16+1),INDEX('前提と出典'!C46:C48,'前提と出典'!$B$16+1),IF(G15<=INDEX('前提と出典'!D46:D48,'前提と出典'!$B$16+1),INDEX('前提と出典'!E46:E48,'前提と出典'!$B$16+1),IF(G15<=INDEX('前提と出典'!F46:F48,'前提と出典'!$B$16+1),INDEX('前提と出典'!G46:G48,'前提と出典'!$B$16+1),INDEX('前提と出典'!I46:I48,'前提と出典'!$B$16+1))))) -> 2500 | O15: =IF(I15=1,G15*'前提と出典'!$B$13,0) -> 3000 | P15: =IF(J15=1,MIN('前提と出典'!$B$17,L15+N15),0) -> 500 | Q15: =IF(J15=0,0,IF('前提と出典'!$B$19=0,P15*L15/(L15+N15),MIN(P15,L15))) -> 307.69231 | R15: =P15-Q15 -> 192.30769 | S15: =IF(H15=1,'前提と出典'!$B$11+F15*'前提と出典'!$B$12,0) -> 120 | T15: =IF(H15=1,('前提と出典'!$B$9+F15*'前提と出典'!$B$10)/60*'前提と出典'!$B$8,0) -> 1000 | U15: =IF(I15=1,INDEX('前提と出典'!B80:B83,'前提と出典'!$B$18+1)+G15*INDEX('前提と出典'!C80:C83,'前提と出典'!$B$18+1),0) -> 346.56537 | V15: =IF(I15=1,INDEX('前提と出典'!D80:D83,'前提と出典'!$B$18+1)+G15*INDEX('前提と出典'!E80:E83,'前提と出典'!$B$18+1),0) -> 633.33333 | W15: =L15-Q15 -> 3692.3077 | X15: =N15-R15 -> 2307.6923
A16: 0 | B16: 5 | C16: 1 | D16: ='前提と出典'!C57*(1-'前提と出典'!$B$21) -> 0.0012 | E16: =ROUNDUP('前提と出典'!B57*'前提と出典'!$B$23,0) -> 150 | F16: ='前提と出典'!A57 -> 70 | G16: =MAX(1,ROUNDUP(E16*'前提と出典'!$B$25*'前提と出典'!E10,0)) -> 23 | H16: =IF(AND(F16>=1,F16<=100),1,0) -> 1 | I16: =IF(G16<=50,1,0) -> 1 | J16: =H16*I16 -> 1 | K16: =IF(A16='前提と出典'!$B$14,D16,0) -> 0 | L16: =IF(H16=0,0,IF(F16<=INDEX('前提と出典'!B41:B43,'前提と出典'!$B$15+1),INDEX('前提と出典'!C41:C43,'前提と出典'!$B$15+1),IF(F16<=INDEX('前提と出典'!D41:D43,'前提と出典'!$B$15+1),INDEX('前提と出典'!E41:E43,'前提と出典'!$B$15+1),INDEX('前提と出典'!G41:G43,'前提と出典'!$B$15+1)))) -> 4000 | M16: =IF(H16=0,0,IF('前提と出典'!$B$33=1,MIN(F16,10)*300+MIN(MAX(0,F16-10),20)*250+MAX(0,F16-30)*200,F16*300)) -> 16000 | N16: =IF(I16=0,0,IF(G16<=INDEX('前提と出典'!B46:B48,'前提と出典'!$B$16+1),INDEX('前提と出典'!C46:C48,'前提と出典'!$B$16+1),IF(G16<=INDEX('前提と出典'!D46:D48,'前提と出典'!$B$16+1),INDEX('前提と出典'!E46:E48,'前提と出典'!$B$16+1),IF(G16<=INDEX('前提と出典'!F46:F48,'前提と出典'!$B$16+1),INDEX('前提と出典'!G46:G48,'前提と出典'!$B$16+1),INDEX('前提と出典'!I46:I48,'前提と出典'!$B$16+1))))) -> 2500 | O16: =IF(I16=1,G16*'前提と出典'!$B$13,0) -> 4600 | P16: =IF(J16=1,MIN('前提と出典'!$B$17,L16+N16),0) -> 500 | Q16: =IF(J16=0,0,IF('前提と出典'!$B$19=0,P16*L16/(L16+N16),MIN(P16,L16))) -> 307.69231 | R16: =P16-Q16 -> 192.30769 | S16: =IF(H16=1,'前提と出典'!$B$11+F16*'前提と出典'!$B$12,0) -> 120 | T16: =IF(H16=1,('前提と出典'!$B$9+F16*'前提と出典'!$B$10)/60*'前提と出典'!$B$8,0) -> 1000 | U16: =IF(I16=1,INDEX('前提と出典'!B80:B83,'前提と出典'!$B$18+1)+G16*INDEX('前提と出典'!C80:C83,'前提と出典'!$B$18+1),0) -> 504.73356 | V16: =IF(I16=1,INDEX('前提と出典'!D80:D83,'前提と出典'!$B$18+1)+G16*INDEX('前提と出典'!E80:E83,'前提と出典'!$B$18+1),0) -> 686.66667 | W16: =L16-Q16 -> 3692.3077 | X16: =N16-R16 -> 2307.6923
A17: 0 | B17: 6 | C17: 0 | D17: ='前提と出典'!C58*'前提と出典'!$B$21 -> 0.0007 | E17: =ROUNDUP('前提と出典'!B58*'前提と出典'!$B$22,0) -> 600 | F17: ='前提と出典'!A58 -> 130 | G17: =MAX(1,ROUNDUP(E17*'前提と出典'!$B$24*'前提と出典'!E10,0)) -> 30 | H17: =IF(AND(F17>=1,F17<=100),1,0) -> 0 | I17: =IF(G17<=50,1,0) -> 1 | J17: =H17*I17 -> 0 | K17: =IF(A17='前提と出典'!$B$14,D17,0) -> 0 | L17: =IF(H17=0,0,IF(F17<=INDEX('前提と出典'!B41:B43,'前提と出典'!$B$15+1),INDEX('前提と出典'!C41:C43,'前提と出典'!$B$15+1),IF(F17<=INDEX('前提と出典'!D41:D43,'前提と出典'!$B$15+1),INDEX('前提と出典'!E41:E43,'前提と出典'!$B$15+1),INDEX('前提と出典'!G41:G43,'前提と出典'!$B$15+1)))) -> 0 | M17: =IF(H17=0,0,IF('前提と出典'!$B$33=1,MIN(F17,10)*300+MIN(MAX(0,F17-10),20)*250+MAX(0,F17-30)*200,F17*300)) -> 0 | N17: =IF(I17=0,0,IF(G17<=INDEX('前提と出典'!B46:B48,'前提と出典'!$B$16+1),INDEX('前提と出典'!C46:C48,'前提と出典'!$B$16+1),IF(G17<=INDEX('前提と出典'!D46:D48,'前提と出典'!$B$16+1),INDEX('前提と出典'!E46:E48,'前提と出典'!$B$16+1),IF(G17<=INDEX('前提と出典'!F46:F48,'前提と出典'!$B$16+1),INDEX('前提と出典'!G46:G48,'前提と出典'!$B$16+1),INDEX('前提と出典'!I46:I48,'前提と出典'!$B$16+1))))) -> 2500 | O17: =IF(I17=1,G17*'前提と出典'!$B$13,0) -> 6000 | P17: =IF(J17=1,MIN('前提と出典'!$B$17,L17+N17),0) -> 0 | Q17: =IF(J17=0,0,IF('前提と出典'!$B$19=0,P17*L17/(L17+N17),MIN(P17,L17))) -> 0 | R17: =P17-Q17 -> 0 | S17: =IF(H17=1,'前提と出典'!$B$11+F17*'前提と出典'!$B$12,0) -> 0 | T17: =IF(H17=1,('前提と出典'!$B$9+F17*'前提と出典'!$B$10)/60*'前提と出典'!$B$8,0) -> 0 | U17: =IF(I17=1,INDEX('前提と出典'!B80:B83,'前提と出典'!$B$18+1)+G17*INDEX('前提と出典'!C80:C83,'前提と出典'!$B$18+1),0) -> 643.13073 | V17: =IF(I17=1,INDEX('前提と出典'!D80:D83,'前提と出典'!$B$18+1)+G17*INDEX('前提と出典'!E80:E83,'前提と出典'!$B$18+1),0) -> 733.33333 | W17: =L17-Q17 -> 0 | X17: =N17-R17 -> 2500
A18: 0 | B18: 6 | C18: 1 | D18: ='前提と出典'!C58*(1-'前提と出典'!$B$21) -> 0.0003 | E18: =ROUNDUP('前提と出典'!B58*'前提と出典'!$B$23,0) -> 300 | F18: ='前提と出典'!A58 -> 130 | G18: =MAX(1,ROUNDUP(E18*'前提と出典'!$B$25*'前提と出典'!E10,0)) -> 45 | H18: =IF(AND(F18>=1,F18<=100),1,0) -> 0 | I18: =IF(G18<=50,1,0) -> 1 | J18: =H18*I18 -> 0 | K18: =IF(A18='前提と出典'!$B$14,D18,0) -> 0 | L18: =IF(H18=0,0,IF(F18<=INDEX('前提と出典'!B41:B43,'前提と出典'!$B$15+1),INDEX('前提と出典'!C41:C43,'前提と出典'!$B$15+1),IF(F18<=INDEX('前提と出典'!D41:D43,'前提と出典'!$B$15+1),INDEX('前提と出典'!E41:E43,'前提と出典'!$B$15+1),INDEX('前提と出典'!G41:G43,'前提と出典'!$B$15+1)))) -> 0 | M18: =IF(H18=0,0,IF('前提と出典'!$B$33=1,MIN(F18,10)*300+MIN(MAX(0,F18-10),20)*250+MAX(0,F18-30)*200,F18*300)) -> 0 | N18: =IF(I18=0,0,IF(G18<=INDEX('前提と出典'!B46:B48,'前提と出典'!$B$16+1),INDEX('前提と出典'!C46:C48,'前提と出典'!$B$16+1),IF(G18<=INDEX('前提と出典'!D46:D48,'前提と出典'!$B$16+1),INDEX('前提と出典'!E46:E48,'前提と出典'!$B$16+1),IF(G18<=INDEX('前提と出典'!F46:F48,'前提と出典'!$B$16+1),INDEX('前提と出典'!G46:G48,'前提と出典'!$B$16+1),INDEX('前提と出典'!I46:I48,'前提と出典'!$B$16+1))))) -> 2500 | O18: =IF(I18=1,G18*'前提と出典'!$B$13,0) -> 9000 | P18: =IF(J18=1,MIN('前提と出典'!$B$17,L18+N18),0) -> 0 | Q18: =IF(J18=0,0,IF('前提と出典'!$B$19=0,P18*L18/(L18+N18),MIN(P18,L18))) -> 0 | R18: =P18-Q18 -> 0 | S18: =IF(H18=1,'前提と出典'!$B$11+F18*'前提と出典'!$B$12,0) -> 0 | T18: =IF(H18=1,('前提と出典'!$B$9+F18*'前提と出典'!$B$10)/60*'前提と出典'!$B$8,0) -> 0 | U18: =IF(I18=1,INDEX('前提と出典'!B80:B83,'前提と出典'!$B$18+1)+G18*INDEX('前提と出典'!C80:C83,'前提と出典'!$B$18+1),0) -> 939.6961 | V18: =IF(I18=1,INDEX('前提と出典'!D80:D83,'前提と出典'!$B$18+1)+G18*INDEX('前提と出典'!E80:E83,'前提と出典'!$B$18+1),0) -> 833.33333 | W18: =L18-Q18 -> 0 | X18: =N18-R18 -> 2500
A19: 1 | B19: 0 | C19: 0 | D19: ='前提と出典'!D52*'前提と出典'!$B$21 -> 0.07 | E19: =ROUNDUP('前提と出典'!B52*'前提と出典'!$B$22,0) -> 6 | F19: ='前提と出典'!A52 -> 0 | G19: =MAX(1,ROUNDUP(E19*'前提と出典'!$B$24*'前提と出典'!E11,0)) -> 1 | H19: =IF(AND(F19>=1,F19<=100),1,0) -> 0 | I19: =IF(G19<=50,1,0) -> 1 | J19: =H19*I19 -> 0 | K19: =IF(A19='前提と出典'!$B$14,D19,0) -> 0.07 | L19: =IF(H19=0,0,IF(F19<=INDEX('前提と出典'!B41:B43,'前提と出典'!$B$15+1),INDEX('前提と出典'!C41:C43,'前提と出典'!$B$15+1),IF(F19<=INDEX('前提と出典'!D41:D43,'前提と出典'!$B$15+1),INDEX('前提と出典'!E41:E43,'前提と出典'!$B$15+1),INDEX('前提と出典'!G41:G43,'前提と出典'!$B$15+1)))) -> 0 | M19: =IF(H19=0,0,IF('前提と出典'!$B$33=1,MIN(F19,10)*300+MIN(MAX(0,F19-10),20)*250+MAX(0,F19-30)*200,F19*300)) -> 0 | N19: =IF(I19=0,0,IF(G19<=INDEX('前提と出典'!B46:B48,'前提と出典'!$B$16+1),INDEX('前提と出典'!C46:C48,'前提と出典'!$B$16+1),IF(G19<=INDEX('前提と出典'!D46:D48,'前提と出典'!$B$16+1),INDEX('前提と出典'!E46:E48,'前提と出典'!$B$16+1),IF(G19<=INDEX('前提と出典'!F46:F48,'前提と出典'!$B$16+1),INDEX('前提と出典'!G46:G48,'前提と出典'!$B$16+1),INDEX('前提と出典'!I46:I48,'前提と出典'!$B$16+1))))) -> 1200 | O19: =IF(I19=1,G19*'前提と出典'!$B$13,0) -> 200 | P19: =IF(J19=1,MIN('前提と出典'!$B$17,L19+N19),0) -> 0 | Q19: =IF(J19=0,0,IF('前提と出典'!$B$19=0,P19*L19/(L19+N19),MIN(P19,L19))) -> 0 | R19: =P19-Q19 -> 0 | S19: =IF(H19=1,'前提と出典'!$B$11+F19*'前提と出典'!$B$12,0) -> 0 | T19: =IF(H19=1,('前提と出典'!$B$9+F19*'前提と出典'!$B$10)/60*'前提と出典'!$B$8,0) -> 0 | U19: =IF(I19=1,INDEX('前提と出典'!B80:B83,'前提と出典'!$B$18+1)+G19*INDEX('前提と出典'!C80:C83,'前提と出典'!$B$18+1),0) -> 69.771024 | V19: =IF(I19=1,INDEX('前提と出典'!D80:D83,'前提と出典'!$B$18+1)+G19*INDEX('前提と出典'!E80:E83,'前提と出典'!$B$18+1),0) -> 540 | W19: =L19-Q19 -> 0 | X19: =N19-R19 -> 1200
A20: 1 | B20: 0 | C20: 1 | D20: ='前提と出典'!D52*(1-'前提と出典'!$B$21) -> 0.03 | E20: =ROUNDUP('前提と出典'!B52*'前提と出典'!$B$23,0) -> 3 | F20: ='前提と出典'!A52 -> 0 | G20: =MAX(1,ROUNDUP(E20*'前提と出典'!$B$25*'前提と出典'!E11,0)) -> 1 | H20: =IF(AND(F20>=1,F20<=100),1,0) -> 0 | I20: =IF(G20<=50,1,0) -> 1 | J20: =H20*I20 -> 0 | K20: =IF(A20='前提と出典'!$B$14,D20,0) -> 0.03 | L20: =IF(H20=0,0,IF(F20<=INDEX('前提と出典'!B41:B43,'前提と出典'!$B$15+1),INDEX('前提と出典'!C41:C43,'前提と出典'!$B$15+1),IF(F20<=INDEX('前提と出典'!D41:D43,'前提と出典'!$B$15+1),INDEX('前提と出典'!E41:E43,'前提と出典'!$B$15+1),INDEX('前提と出典'!G41:G43,'前提と出典'!$B$15+1)))) -> 0 | M20: =IF(H20=0,0,IF('前提と出典'!$B$33=1,MIN(F20,10)*300+MIN(MAX(0,F20-10),20)*250+MAX(0,F20-30)*200,F20*300)) -> 0 | N20: =IF(I20=0,0,IF(G20<=INDEX('前提と出典'!B46:B48,'前提と出典'!$B$16+1),INDEX('前提と出典'!C46:C48,'前提と出典'!$B$16+1),IF(G20<=INDEX('前提と出典'!D46:D48,'前提と出典'!$B$16+1),INDEX('前提と出典'!E46:E48,'前提と出典'!$B$16+1),IF(G20<=INDEX('前提と出典'!F46:F48,'前提と出典'!$B$16+1),INDEX('前提と出典'!G46:G48,'前提と出典'!$B$16+1),INDEX('前提と出典'!I46:I48,'前提と出典'!$B$16+1))))) -> 1200 | O20: =IF(I20=1,G20*'前提と出典'!$B$13,0) -> 200 | P20: =IF(J20=1,MIN('前提と出典'!$B$17,L20+N20),0) -> 0 | Q20: =IF(J20=0,0,IF('前提と出典'!$B$19=0,P20*L20/(L20+N20),MIN(P20,L20))) -> 0 | R20: =P20-Q20 -> 0 | S20: =IF(H20=1,'前提と出典'!$B$11+F20*'前提と出典'!$B$12,0) -> 0 | T20: =IF(H20=1,('前提と出典'!$B$9+F20*'前提と出典'!$B$10)/60*'前提と出典'!$B$8,0) -> 0 | U20: =IF(I20=1,INDEX('前提と出典'!B80:B83,'前提と出典'!$B$18+1)+G20*INDEX('前提と出典'!C80:C83,'前提と出典'!$B$18+1),0) -> 69.771024 | V20: =IF(I20=1,INDEX('前提と出典'!D80:D83,'前提と出典'!$B$18+1)+G20*INDEX('前提と出典'!E80:E83,'前提と出典'!$B$18+1),0) -> 540 | W20: =L20-Q20 -> 0 | X20: =N20-R20 -> 1200
A21: 1 | B21: 1 | C21: 0 | D21: ='前提と出典'!D53*'前提と出典'!$B$21 -> 0.259 | E21: =ROUNDUP('前提と出典'!B53*'前提と出典'!$B$22,0) -> 15 | F21: ='前提と出典'!A53 -> 3 | G21: =MAX(1,ROUNDUP(E21*'前提と出典'!$B$24*'前提と出典'!E11,0)) -> 2 | H21: =IF(AND(F21>=1,F21<=100),1,0) -> 1 | I21: =IF(G21<=50,1,0) -> 1 | J21: =H21*I21 -> 1 | K21: =IF(A21='前提と出典'!$B$14,D21,0) -> 0.259 | L21: =IF(H21=0,0,IF(F21<=INDEX('前提と出典'!B41:B43,'前提と出典'!$B$15+1),INDEX('前提と出典'!C41:C43,'前提と出典'!$B$15+1),IF(F21<=INDEX('前提と出典'!D41:D43,'前提と出典'!$B$15+1),INDEX('前提と出典'!E41:E43,'前提と出典'!$B$15+1),INDEX('前提と出典'!G41:G43,'前提と出典'!$B$15+1)))) -> 2500 | M21: =IF(H21=0,0,IF('前提と出典'!$B$33=1,MIN(F21,10)*300+MIN(MAX(0,F21-10),20)*250+MAX(0,F21-30)*200,F21*300)) -> 900 | N21: =IF(I21=0,0,IF(G21<=INDEX('前提と出典'!B46:B48,'前提と出典'!$B$16+1),INDEX('前提と出典'!C46:C48,'前提と出典'!$B$16+1),IF(G21<=INDEX('前提と出典'!D46:D48,'前提と出典'!$B$16+1),INDEX('前提と出典'!E46:E48,'前提と出典'!$B$16+1),IF(G21<=INDEX('前提と出典'!F46:F48,'前提と出典'!$B$16+1),INDEX('前提と出典'!G46:G48,'前提と出典'!$B$16+1),INDEX('前提と出典'!I46:I48,'前提と出典'!$B$16+1))))) -> 1200 | O21: =IF(I21=1,G21*'前提と出典'!$B$13,0) -> 400 | P21: =IF(J21=1,MIN('前提と出典'!$B$17,L21+N21),0) -> 500 | Q21: =IF(J21=0,0,IF('前提と出典'!$B$19=0,P21*L21/(L21+N21),MIN(P21,L21))) -> 337.83784 | R21: =P21-Q21 -> 162.16216 | S21: =IF(H21=1,'前提と出典'!$B$11+F21*'前提と出典'!$B$12,0) -> 53 | T21: =IF(H21=1,('前提と出典'!$B$9+F21*'前提と出典'!$B$10)/60*'前提と出典'!$B$8,0) -> 553.33333 | U21: =IF(I21=1,INDEX('前提と出典'!B80:B83,'前提と出典'!$B$18+1)+G21*INDEX('前提と出典'!C80:C83,'前提と出典'!$B$18+1),0) -> 89.542049 | V21: =IF(I21=1,INDEX('前提と出典'!D80:D83,'前提と出典'!$B$18+1)+G21*INDEX('前提と出典'!E80:E83,'前提と出典'!$B$18+1),0) -> 546.66667 | W21: =L21-Q21 -> 2162.1622 | X21: =N21-R21 -> 1037.8378
A22: 1 | B22: 1 | C22: 1 | D22: ='前提と出典'!D53*(1-'前提と出典'!$B$21) -> 0.111 | E22: =ROUNDUP('前提と出典'!B53*'前提と出典'!$B$23,0) -> 8 | F22: ='前提と出典'!A53 -> 3 | G22: =MAX(1,ROUNDUP(E22*'前提と出典'!$B$25*'前提と出典'!E11,0)) -> 3 | H22: =IF(AND(F22>=1,F22<=100),1,0) -> 1 | I22: =IF(G22<=50,1,0) -> 1 | J22: =H22*I22 -> 1 | K22: =IF(A22='前提と出典'!$B$14,D22,0) -> 0.111 | L22: =IF(H22=0,0,IF(F22<=INDEX('前提と出典'!B41:B43,'前提と出典'!$B$15+1),INDEX('前提と出典'!C41:C43,'前提と出典'!$B$15+1),IF(F22<=INDEX('前提と出典'!D41:D43,'前提と出典'!$B$15+1),INDEX('前提と出典'!E41:E43,'前提と出典'!$B$15+1),INDEX('前提と出典'!G41:G43,'前提と出典'!$B$15+1)))) -> 2500 | M22: =IF(H22=0,0,IF('前提と出典'!$B$33=1,MIN(F22,10)*300+MIN(MAX(0,F22-10),20)*250+MAX(0,F22-30)*200,F22*300)) -> 900 | N22: =IF(I22=0,0,IF(G22<=INDEX('前提と出典'!B46:B48,'前提と出典'!$B$16+1),INDEX('前提と出典'!C46:C48,'前提と出典'!$B$16+1),IF(G22<=INDEX('前提と出典'!D46:D48,'前提と出典'!$B$16+1),INDEX('前提と出典'!E46:E48,'前提と出典'!$B$16+1),IF(G22<=INDEX('前提と出典'!F46:F48,'前提と出典'!$B$16+1),INDEX('前提と出典'!G46:G48,'前提と出典'!$B$16+1),INDEX('前提と出典'!I46:I48,'前提と出典'!$B$16+1))))) -> 1200 | O22: =IF(I22=1,G22*'前提と出典'!$B$13,0) -> 600 | P22: =IF(J22=1,MIN('前提と出典'!$B$17,L22+N22),0) -> 500 | Q22: =IF(J22=0,0,IF('前提と出典'!$B$19=0,P22*L22/(L22+N22),MIN(P22,L22))) -> 337.83784 | R22: =P22-Q22 -> 162.16216 | S22: =IF(H22=1,'前提と出典'!$B$11+F22*'前提と出典'!$B$12,0) -> 53 | T22: =IF(H22=1,('前提と出典'!$B$9+F22*'前提と出典'!$B$10)/60*'前提と出典'!$B$8,0) -> 553.33333 | U22: =IF(I22=1,INDEX('前提と出典'!B80:B83,'前提と出典'!$B$18+1)+G22*INDEX('前提と出典'!C80:C83,'前提と出典'!$B$18+1),0) -> 109.31307 | V22: =IF(I22=1,INDEX('前提と出典'!D80:D83,'前提と出典'!$B$18+1)+G22*INDEX('前提と出典'!E80:E83,'前提と出典'!$B$18+1),0) -> 553.33333 | W22: =L22-Q22 -> 2162.1622 | X22: =N22-R22 -> 1037.8378
A23: 1 | B23: 2 | C23: 0 | D23: ='前提と出典'!D54*'前提と出典'!$B$21 -> 0.196 | E23: =ROUNDUP('前提と出典'!B54*'前提と出典'!$B$22,0) -> 38 | F23: ='前提と出典'!A54 -> 8 | G23: =MAX(1,ROUNDUP(E23*'前提と出典'!$B$24*'前提と出典'!E11,0)) -> 4 | H23: =IF(AND(F23>=1,F23<=100),1,0) -> 1 | I23: =IF(G23<=50,1,0) -> 1 | J23: =H23*I23 -> 1 | K23: =IF(A23='前提と出典'!$B$14,D23,0) -> 0.196 | L23: =IF(H23=0,0,IF(F23<=INDEX('前提と出典'!B41:B43,'前提と出典'!$B$15+1),INDEX('前提と出典'!C41:C43,'前提と出典'!$B$15+1),IF(F23<=INDEX('前提と出典'!D41:D43,'前提と出典'!$B$15+1),INDEX('前提と出典'!E41:E43,'前提と出典'!$B$15+1),INDEX('前提と出典'!G41:G43,'前提と出典'!$B$15+1)))) -> 2500 | M23: =IF(H23=0,0,IF('前提と出典'!$B$33=1,MIN(F23,10)*300+MIN(MAX(0,F23-10),20)*250+MAX(0,F23-30)*200,F23*300)) -> 2400 | N23: =IF(I23=0,0,IF(G23<=INDEX('前提と出典'!B46:B48,'前提と出典'!$B$16+1),INDEX('前提と出典'!C46:C48,'前提と出典'!$B$16+1),IF(G23<=INDEX('前提と出典'!D46:D48,'前提と出典'!$B$16+1),INDEX('前提と出典'!E46:E48,'前提と出典'!$B$16+1),IF(G23<=INDEX('前提と出典'!F46:F48,'前提と出典'!$B$16+1),INDEX('前提と出典'!G46:G48,'前提と出典'!$B$16+1),INDEX('前提と出典'!I46:I48,'前提と出典'!$B$16+1))))) -> 1200 | O23: =IF(I23=1,G23*'前提と出典'!$B$13,0) -> 800 | P23: =IF(J23=1,MIN('前提と出典'!$B$17,L23+N23),0) -> 500 | Q23: =IF(J23=0,0,IF('前提と出典'!$B$19=0,P23*L23/(L23+N23),MIN(P23,L23))) -> 337.83784 | R23: =P23-Q23 -> 162.16216 | S23: =IF(H23=1,'前提と出典'!$B$11+F23*'前提と出典'!$B$12,0) -> 58 | T23: =IF(H23=1,('前提と出典'!$B$9+F23*'前提と出典'!$B$10)/60*'前提と出典'!$B$8,0) -> 586.66667 | U23: =IF(I23=1,INDEX('前提と出典'!B80:B83,'前提と出典'!$B$18+1)+G23*INDEX('前提と出典'!C80:C83,'前提と出典'!$B$18+1),0) -> 129.0841 | V23: =IF(I23=1,INDEX('前提と出典'!D80:D83,'前提と出典'!$B$18+1)+G23*INDEX('前提と出典'!E80:E83,'前提と出典'!$B$18+1),0) -> 560 | W23: =L23-Q23 -> 2162.1622 | X23: =N23-R23 -> 1037.8378
A24: 1 | B24: 2 | C24: 1 | D24: ='前提と出典'!D54*(1-'前提と出典'!$B$21) -> 0.084 | E24: =ROUNDUP('前提と出典'!B54*'前提と出典'!$B$23,0) -> 19 | F24: ='前提と出典'!A54 -> 8 | G24: =MAX(1,ROUNDUP(E24*'前提と出典'!$B$25*'前提と出典'!E11,0)) -> 6 | H24: =IF(AND(F24>=1,F24<=100),1,0) -> 1 | I24: =IF(G24<=50,1,0) -> 1 | J24: =H24*I24 -> 1 | K24: =IF(A24='前提と出典'!$B$14,D24,0) -> 0.084 | L24: =IF(H24=0,0,IF(F24<=INDEX('前提と出典'!B41:B43,'前提と出典'!$B$15+1),INDEX('前提と出典'!C41:C43,'前提と出典'!$B$15+1),IF(F24<=INDEX('前提と出典'!D41:D43,'前提と出典'!$B$15+1),INDEX('前提と出典'!E41:E43,'前提と出典'!$B$15+1),INDEX('前提と出典'!G41:G43,'前提と出典'!$B$15+1)))) -> 2500 | M24: =IF(H24=0,0,IF('前提と出典'!$B$33=1,MIN(F24,10)*300+MIN(MAX(0,F24-10),20)*250+MAX(0,F24-30)*200,F24*300)) -> 2400 | N24: =IF(I24=0,0,IF(G24<=INDEX('前提と出典'!B46:B48,'前提と出典'!$B$16+1),INDEX('前提と出典'!C46:C48,'前提と出典'!$B$16+1),IF(G24<=INDEX('前提と出典'!D46:D48,'前提と出典'!$B$16+1),INDEX('前提と出典'!E46:E48,'前提と出典'!$B$16+1),IF(G24<=INDEX('前提と出典'!F46:F48,'前提と出典'!$B$16+1),INDEX('前提と出典'!G46:G48,'前提と出典'!$B$16+1),INDEX('前提と出典'!I46:I48,'前提と出典'!$B$16+1))))) -> 1200 | O24: =IF(I24=1,G24*'前提と出典'!$B$13,0) -> 1200 | P24: =IF(J24=1,MIN('前提と出典'!$B$17,L24+N24),0) -> 500 | Q24: =IF(J24=0,0,IF('前提と出典'!$B$19=0,P24*L24/(L24+N24),MIN(P24,L24))) -> 337.83784 | R24: =P24-Q24 -> 162.16216 | S24: =IF(H24=1,'前提と出典'!$B$11+F24*'前提と出典'!$B$12,0) -> 58 | T24: =IF(H24=1,('前提と出典'!$B$9+F24*'前提と出典'!$B$10)/60*'前提と出典'!$B$8,0) -> 586.66667 | U24: =IF(I24=1,INDEX('前提と出典'!B80:B83,'前提と出典'!$B$18+1)+G24*INDEX('前提と出典'!C80:C83,'前提と出典'!$B$18+1),0) -> 168.62615 | V24: =IF(I24=1,INDEX('前提と出典'!D80:D83,'前提と出典'!$B$18+1)+G24*INDEX('前提と出典'!E80:E83,'前提と出典'!$B$18+1),0) -> 573.33333 | W24: =L24-Q24 -> 2162.1622 | X24: =N24-R24 -> 1037.8378
A25: 1 | B25: 3 | C25: 0 | D25: ='前提と出典'!D55*'前提と出典'!$B$21 -> 0.14 | E25: =ROUNDUP('前提と出典'!B55*'前提と出典'!$B$22,0) -> 90 | F25: ='前提と出典'!A55 -> 18 | G25: =MAX(1,ROUNDUP(E25*'前提と出典'!$B$24*'前提と出典'!E11,0)) -> 9 | H25: =IF(AND(F25>=1,F25<=100),1,0) -> 1 | I25: =IF(G25<=50,1,0) -> 1 | J25: =H25*I25 -> 1 | K25: =IF(A25='前提と出典'!$B$14,D25,0) -> 0.14 | L25: =IF(H25=0,0,IF(F25<=INDEX('前提と出典'!B41:B43,'前提と出典'!$B$15+1),INDEX('前提と出典'!C41:C43,'前提と出典'!$B$15+1),IF(F25<=INDEX('前提と出典'!D41:D43,'前提と出典'!$B$15+1),INDEX('前提と出典'!E41:E43,'前提と出典'!$B$15+1),INDEX('前提と出典'!G41:G43,'前提と出典'!$B$15+1)))) -> 4000 | M25: =IF(H25=0,0,IF('前提と出典'!$B$33=1,MIN(F25,10)*300+MIN(MAX(0,F25-10),20)*250+MAX(0,F25-30)*200,F25*300)) -> 5000 | N25: =IF(I25=0,0,IF(G25<=INDEX('前提と出典'!B46:B48,'前提と出典'!$B$16+1),INDEX('前提と出典'!C46:C48,'前提と出典'!$B$16+1),IF(G25<=INDEX('前提と出典'!D46:D48,'前提と出典'!$B$16+1),INDEX('前提と出典'!E46:E48,'前提と出典'!$B$16+1),IF(G25<=INDEX('前提と出典'!F46:F48,'前提と出典'!$B$16+1),INDEX('前提と出典'!G46:G48,'前提と出典'!$B$16+1),INDEX('前提と出典'!I46:I48,'前提と出典'!$B$16+1))))) -> 1200 | O25: =IF(I25=1,G25*'前提と出典'!$B$13,0) -> 1800 | P25: =IF(J25=1,MIN('前提と出典'!$B$17,L25+N25),0) -> 500 | Q25: =IF(J25=0,0,IF('前提と出典'!$B$19=0,P25*L25/(L25+N25),MIN(P25,L25))) -> 384.61538 | R25: =P25-Q25 -> 115.38462 | S25: =IF(H25=1,'前提と出典'!$B$11+F25*'前提と出典'!$B$12,0) -> 68 | T25: =IF(H25=1,('前提と出典'!$B$9+F25*'前提と出典'!$B$10)/60*'前提と出典'!$B$8,0) -> 653.33333 | U25: =IF(I25=1,INDEX('前提と出典'!B80:B83,'前提と出典'!$B$18+1)+G25*INDEX('前提と出典'!C80:C83,'前提と出典'!$B$18+1),0) -> 227.93922 | V25: =IF(I25=1,INDEX('前提と出典'!D80:D83,'前提と出典'!$B$18+1)+G25*INDEX('前提と出典'!E80:E83,'前提と出典'!$B$18+1),0) -> 593.33333 | W25: =L25-Q25 -> 3615.3846 | X25: =N25-R25 -> 1084.6154
A26: 1 | B26: 3 | C26: 1 | D26: ='前提と出典'!D55*(1-'前提と出典'!$B$21) -> 0.06 | E26: =ROUNDUP('前提と出典'!B55*'前提と出典'!$B$23,0) -> 45 | F26: ='前提と出典'!A55 -> 18 | G26: =MAX(1,ROUNDUP(E26*'前提と出典'!$B$25*'前提と出典'!E11,0)) -> 14 | H26: =IF(AND(F26>=1,F26<=100),1,0) -> 1 | I26: =IF(G26<=50,1,0) -> 1 | J26: =H26*I26 -> 1 | K26: =IF(A26='前提と出典'!$B$14,D26,0) -> 0.06 | L26: =IF(H26=0,0,IF(F26<=INDEX('前提と出典'!B41:B43,'前提と出典'!$B$15+1),INDEX('前提と出典'!C41:C43,'前提と出典'!$B$15+1),IF(F26<=INDEX('前提と出典'!D41:D43,'前提と出典'!$B$15+1),INDEX('前提と出典'!E41:E43,'前提と出典'!$B$15+1),INDEX('前提と出典'!G41:G43,'前提と出典'!$B$15+1)))) -> 4000 | M26: =IF(H26=0,0,IF('前提と出典'!$B$33=1,MIN(F26,10)*300+MIN(MAX(0,F26-10),20)*250+MAX(0,F26-30)*200,F26*300)) -> 5000 | N26: =IF(I26=0,0,IF(G26<=INDEX('前提と出典'!B46:B48,'前提と出典'!$B$16+1),INDEX('前提と出典'!C46:C48,'前提と出典'!$B$16+1),IF(G26<=INDEX('前提と出典'!D46:D48,'前提と出典'!$B$16+1),INDEX('前提と出典'!E46:E48,'前提と出典'!$B$16+1),IF(G26<=INDEX('前提と出典'!F46:F48,'前提と出典'!$B$16+1),INDEX('前提と出典'!G46:G48,'前提と出典'!$B$16+1),INDEX('前提と出典'!I46:I48,'前提と出典'!$B$16+1))))) -> 2500 | O26: =IF(I26=1,G26*'前提と出典'!$B$13,0) -> 2800 | P26: =IF(J26=1,MIN('前提と出典'!$B$17,L26+N26),0) -> 500 | Q26: =IF(J26=0,0,IF('前提と出典'!$B$19=0,P26*L26/(L26+N26),MIN(P26,L26))) -> 307.69231 | R26: =P26-Q26 -> 192.30769 | S26: =IF(H26=1,'前提と出典'!$B$11+F26*'前提と出典'!$B$12,0) -> 68 | T26: =IF(H26=1,('前提と出典'!$B$9+F26*'前提と出典'!$B$10)/60*'前提と出典'!$B$8,0) -> 653.33333 | U26: =IF(I26=1,INDEX('前提と出典'!B80:B83,'前提と出典'!$B$18+1)+G26*INDEX('前提と出典'!C80:C83,'前提と出典'!$B$18+1),0) -> 326.79434 | V26: =IF(I26=1,INDEX('前提と出典'!D80:D83,'前提と出典'!$B$18+1)+G26*INDEX('前提と出典'!E80:E83,'前提と出典'!$B$18+1),0) -> 626.66667 | W26: =L26-Q26 -> 3692.3077 | X26: =N26-R26 -> 2307.6923
A27: 1 | B27: 4 | C27: 0 | D27: ='前提と出典'!D56*'前提と出典'!$B$21 -> 0.021 | E27: =ROUNDUP('前提と出典'!B56*'前提と出典'!$B$22,0) -> 180 | F27: ='前提と出典'!A56 -> 40 | G27: =MAX(1,ROUNDUP(E27*'前提と出典'!$B$24*'前提と出典'!E11,0)) -> 18 | H27: =IF(AND(F27>=1,F27<=100),1,0) -> 1 | I27: =IF(G27<=50,1,0) -> 1 | J27: =H27*I27 -> 1 | K27: =IF(A27='前提と出典'!$B$14,D27,0) -> 0.021 | L27: =IF(H27=0,0,IF(F27<=INDEX('前提と出典'!B41:B43,'前提と出典'!$B$15+1),INDEX('前提と出典'!C41:C43,'前提と出典'!$B$15+1),IF(F27<=INDEX('前提と出典'!D41:D43,'前提と出典'!$B$15+1),INDEX('前提と出典'!E41:E43,'前提と出典'!$B$15+1),INDEX('前提と出典'!G41:G43,'前提と出典'!$B$15+1)))) -> 4000 | M27: =IF(H27=0,0,IF('前提と出典'!$B$33=1,MIN(F27,10)*300+MIN(MAX(0,F27-10),20)*250+MAX(0,F27-30)*200,F27*300)) -> 10000 | N27: =IF(I27=0,0,IF(G27<=INDEX('前提と出典'!B46:B48,'前提と出典'!$B$16+1),INDEX('前提と出典'!C46:C48,'前提と出典'!$B$16+1),IF(G27<=INDEX('前提と出典'!D46:D48,'前提と出典'!$B$16+1),INDEX('前提と出典'!E46:E48,'前提と出典'!$B$16+1),IF(G27<=INDEX('前提と出典'!F46:F48,'前提と出典'!$B$16+1),INDEX('前提と出典'!G46:G48,'前提と出典'!$B$16+1),INDEX('前提と出典'!I46:I48,'前提と出典'!$B$16+1))))) -> 2500 | O27: =IF(I27=1,G27*'前提と出典'!$B$13,0) -> 3600 | P27: =IF(J27=1,MIN('前提と出典'!$B$17,L27+N27),0) -> 500 | Q27: =IF(J27=0,0,IF('前提と出典'!$B$19=0,P27*L27/(L27+N27),MIN(P27,L27))) -> 307.69231 | R27: =P27-Q27 -> 192.30769 | S27: =IF(H27=1,'前提と出典'!$B$11+F27*'前提と出典'!$B$12,0) -> 90 | T27: =IF(H27=1,('前提と出典'!$B$9+F27*'前提と出典'!$B$10)/60*'前提と出典'!$B$8,0) -> 800 | U27: =IF(I27=1,INDEX('前提と出典'!B80:B83,'前提と出典'!$B$18+1)+G27*INDEX('前提と出典'!C80:C83,'前提と出典'!$B$18+1),0) -> 405.87844 | V27: =IF(I27=1,INDEX('前提と出典'!D80:D83,'前提と出典'!$B$18+1)+G27*INDEX('前提と出典'!E80:E83,'前提と出典'!$B$18+1),0) -> 653.33333 | W27: =L27-Q27 -> 3692.3077 | X27: =N27-R27 -> 2307.6923
A28: 1 | B28: 4 | C28: 1 | D28: ='前提と出典'!D56*(1-'前提と出典'!$B$21) -> 0.009 | E28: =ROUNDUP('前提と出典'!B56*'前提と出典'!$B$23,0) -> 90 | F28: ='前提と出典'!A56 -> 40 | G28: =MAX(1,ROUNDUP(E28*'前提と出典'!$B$25*'前提と出典'!E11,0)) -> 27 | H28: =IF(AND(F28>=1,F28<=100),1,0) -> 1 | I28: =IF(G28<=50,1,0) -> 1 | J28: =H28*I28 -> 1 | K28: =IF(A28='前提と出典'!$B$14,D28,0) -> 0.009 | L28: =IF(H28=0,0,IF(F28<=INDEX('前提と出典'!B41:B43,'前提と出典'!$B$15+1),INDEX('前提と出典'!C41:C43,'前提と出典'!$B$15+1),IF(F28<=INDEX('前提と出典'!D41:D43,'前提と出典'!$B$15+1),INDEX('前提と出典'!E41:E43,'前提と出典'!$B$15+1),INDEX('前提と出典'!G41:G43,'前提と出典'!$B$15+1)))) -> 4000 | M28: =IF(H28=0,0,IF('前提と出典'!$B$33=1,MIN(F28,10)*300+MIN(MAX(0,F28-10),20)*250+MAX(0,F28-30)*200,F28*300)) -> 10000 | N28: =IF(I28=0,0,IF(G28<=INDEX('前提と出典'!B46:B48,'前提と出典'!$B$16+1),INDEX('前提と出典'!C46:C48,'前提と出典'!$B$16+1),IF(G28<=INDEX('前提と出典'!D46:D48,'前提と出典'!$B$16+1),INDEX('前提と出典'!E46:E48,'前提と出典'!$B$16+1),IF(G28<=INDEX('前提と出典'!F46:F48,'前提と出典'!$B$16+1),INDEX('前提と出典'!G46:G48,'前提と出典'!$B$16+1),INDEX('前提と出典'!I46:I48,'前提と出典'!$B$16+1))))) -> 2500 | O28: =IF(I28=1,G28*'前提と出典'!$B$13,0) -> 5400 | P28: =IF(J28=1,MIN('前提と出典'!$B$17,L28+N28),0) -> 500 | Q28: =IF(J28=0,0,IF('前提と出典'!$B$19=0,P28*L28/(L28+N28),MIN(P28,L28))) -> 307.69231 | R28: =P28-Q28 -> 192.30769 | S28: =IF(H28=1,'前提と出典'!$B$11+F28*'前提と出典'!$B$12,0) -> 90 | T28: =IF(H28=1,('前提と出典'!$B$9+F28*'前提と出典'!$B$10)/60*'前提と出典'!$B$8,0) -> 800 | U28: =IF(I28=1,INDEX('前提と出典'!B80:B83,'前提と出典'!$B$18+1)+G28*INDEX('前提と出典'!C80:C83,'前提と出典'!$B$18+1),0) -> 583.81766 | V28: =IF(I28=1,INDEX('前提と出典'!D80:D83,'前提と出典'!$B$18+1)+G28*INDEX('前提と出典'!E80:E83,'前提と出典'!$B$18+1),0) -> 713.33333 | W28: =L28-Q28 -> 3692.3077 | X28: =N28-R28 -> 2307.6923
A29: 1 | B29: 5 | C29: 0 | D29: ='前提と出典'!D57*'前提と出典'!$B$21 -> 0.0105 | E29: =ROUNDUP('前提と出典'!B57*'前提と出典'!$B$22,0) -> 300 | F29: ='前提と出典'!A57 -> 70 | G29: =MAX(1,ROUNDUP(E29*'前提と出典'!$B$24*'前提と出典'!E11,0)) -> 30 | H29: =IF(AND(F29>=1,F29<=100),1,0) -> 1 | I29: =IF(G29<=50,1,0) -> 1 | J29: =H29*I29 -> 1 | K29: =IF(A29='前提と出典'!$B$14,D29,0) -> 0.0105 | L29: =IF(H29=0,0,IF(F29<=INDEX('前提と出典'!B41:B43,'前提と出典'!$B$15+1),INDEX('前提と出典'!C41:C43,'前提と出典'!$B$15+1),IF(F29<=INDEX('前提と出典'!D41:D43,'前提と出典'!$B$15+1),INDEX('前提と出典'!E41:E43,'前提と出典'!$B$15+1),INDEX('前提と出典'!G41:G43,'前提と出典'!$B$15+1)))) -> 4000 | M29: =IF(H29=0,0,IF('前提と出典'!$B$33=1,MIN(F29,10)*300+MIN(MAX(0,F29-10),20)*250+MAX(0,F29-30)*200,F29*300)) -> 16000 | N29: =IF(I29=0,0,IF(G29<=INDEX('前提と出典'!B46:B48,'前提と出典'!$B$16+1),INDEX('前提と出典'!C46:C48,'前提と出典'!$B$16+1),IF(G29<=INDEX('前提と出典'!D46:D48,'前提と出典'!$B$16+1),INDEX('前提と出典'!E46:E48,'前提と出典'!$B$16+1),IF(G29<=INDEX('前提と出典'!F46:F48,'前提と出典'!$B$16+1),INDEX('前提と出典'!G46:G48,'前提と出典'!$B$16+1),INDEX('前提と出典'!I46:I48,'前提と出典'!$B$16+1))))) -> 2500 | O29: =IF(I29=1,G29*'前提と出典'!$B$13,0) -> 6000 | P29: =IF(J29=1,MIN('前提と出典'!$B$17,L29+N29),0) -> 500 | Q29: =IF(J29=0,0,IF('前提と出典'!$B$19=0,P29*L29/(L29+N29),MIN(P29,L29))) -> 307.69231 | R29: =P29-Q29 -> 192.30769 | S29: =IF(H29=1,'前提と出典'!$B$11+F29*'前提と出典'!$B$12,0) -> 120 | T29: =IF(H29=1,('前提と出典'!$B$9+F29*'前提と出典'!$B$10)/60*'前提と出典'!$B$8,0) -> 1000 | U29: =IF(I29=1,INDEX('前提と出典'!B80:B83,'前提と出典'!$B$18+1)+G29*INDEX('前提と出典'!C80:C83,'前提と出典'!$B$18+1),0) -> 643.13073 | V29: =IF(I29=1,INDEX('前提と出典'!D80:D83,'前提と出典'!$B$18+1)+G29*INDEX('前提と出典'!E80:E83,'前提と出典'!$B$18+1),0) -> 733.33333 | W29: =L29-Q29 -> 3692.3077 | X29: =N29-R29 -> 2307.6923
A30: 1 | B30: 5 | C30: 1 | D30: ='前提と出典'!D57*(1-'前提と出典'!$B$21) -> 0.0045 | E30: =ROUNDUP('前提と出典'!B57*'前提と出典'!$B$23,0) -> 150 | F30: ='前提と出典'!A57 -> 70 | G30: =MAX(1,ROUNDUP(E30*'前提と出典'!$B$25*'前提と出典'!E11,0)) -> 45 | H30: =IF(AND(F30>=1,F30<=100),1,0) -> 1 | I30: =IF(G30<=50,1,0) -> 1 | J30: =H30*I30 -> 1 | K30: =IF(A30='前提と出典'!$B$14,D30,0) -> 0.0045 | L30: =IF(H30=0,0,IF(F30<=INDEX('前提と出典'!B41:B43,'前提と出典'!$B$15+1),INDEX('前提と出典'!C41:C43,'前提と出典'!$B$15+1),IF(F30<=INDEX('前提と出典'!D41:D43,'前提と出典'!$B$15+1),INDEX('前提と出典'!E41:E43,'前提と出典'!$B$15+1),INDEX('前提と出典'!G41:G43,'前提と出典'!$B$15+1)))) -> 4000 | M30: =IF(H30=0,0,IF('前提と出典'!$B$33=1,MIN(F30,10)*300+MIN(MAX(0,F30-10),20)*250+MAX(0,F30-30)*200,F30*300)) -> 16000 | N30: =IF(I30=0,0,IF(G30<=INDEX('前提と出典'!B46:B48,'前提と出典'!$B$16+1),INDEX('前提と出典'!C46:C48,'前提と出典'!$B$16+1),IF(G30<=INDEX('前提と出典'!D46:D48,'前提と出典'!$B$16+1),INDEX('前提と出典'!E46:E48,'前提と出典'!$B$16+1),IF(G30<=INDEX('前提と出典'!F46:F48,'前提と出典'!$B$16+1),INDEX('前提と出典'!G46:G48,'前提と出典'!$B$16+1),INDEX('前提と出典'!I46:I48,'前提と出典'!$B$16+1))))) -> 2500 | O30: =IF(I30=1,G30*'前提と出典'!$B$13,0) -> 9000 | P30: =IF(J30=1,MIN('前提と出典'!$B$17,L30+N30),0) -> 500 | Q30: =IF(J30=0,0,IF('前提と出典'!$B$19=0,P30*L30/(L30+N30),MIN(P30,L30))) -> 307.69231 | R30: =P30-Q30 -> 192.30769 | S30: =IF(H30=1,'前提と出典'!$B$11+F30*'前提と出典'!$B$12,0) -> 120 | T30: =IF(H30=1,('前提と出典'!$B$9+F30*'前提と出典'!$B$10)/60*'前提と出典'!$B$8,0) -> 1000 | U30: =IF(I30=1,INDEX('前提と出典'!B80:B83,'前提と出典'!$B$18+1)+G30*INDEX('前提と出典'!C80:C83,'前提と出典'!$B$18+1),0) -> 939.6961 | V30: =IF(I30=1,INDEX('前提と出典'!D80:D83,'前提と出典'!$B$18+1)+G30*INDEX('前提と出典'!E80:E83,'前提と出典'!$B$18+1),0) -> 833.33333 | W30: =L30-Q30 -> 3692.3077 | X30: =N30-R30 -> 2307.6923
A31: 1 | B31: 6 | C31: 0 | D31: ='前提と出典'!D58*'前提と出典'!$B$21 -> 0.0035 | E31: =ROUNDUP('前提と出典'!B58*'前提と出典'!$B$22,0) -> 600 | F31: ='前提と出典'!A58 -> 130 | G31: =MAX(1,ROUNDUP(E31*'前提と出典'!$B$24*'前提と出典'!E11,0)) -> 60 | H31: =IF(AND(F31>=1,F31<=100),1,0) -> 0 | I31: =IF(G31<=50,1,0) -> 0 | J31: =H31*I31 -> 0 | K31: =IF(A31='前提と出典'!$B$14,D31,0) -> 0.0035 | L31: =IF(H31=0,0,IF(F31<=INDEX('前提と出典'!B41:B43,'前提と出典'!$B$15+1),INDEX('前提と出典'!C41:C43,'前提と出典'!$B$15+1),IF(F31<=INDEX('前提と出典'!D41:D43,'前提と出典'!$B$15+1),INDEX('前提と出典'!E41:E43,'前提と出典'!$B$15+1),INDEX('前提と出典'!G41:G43,'前提と出典'!$B$15+1)))) -> 0 | M31: =IF(H31=0,0,IF('前提と出典'!$B$33=1,MIN(F31,10)*300+MIN(MAX(0,F31-10),20)*250+MAX(0,F31-30)*200,F31*300)) -> 0 | N31: =IF(I31=0,0,IF(G31<=INDEX('前提と出典'!B46:B48,'前提と出典'!$B$16+1),INDEX('前提と出典'!C46:C48,'前提と出典'!$B$16+1),IF(G31<=INDEX('前提と出典'!D46:D48,'前提と出典'!$B$16+1),INDEX('前提と出典'!E46:E48,'前提と出典'!$B$16+1),IF(G31<=INDEX('前提と出典'!F46:F48,'前提と出典'!$B$16+1),INDEX('前提と出典'!G46:G48,'前提と出典'!$B$16+1),INDEX('前提と出典'!I46:I48,'前提と出典'!$B$16+1))))) -> 0 | O31: =IF(I31=1,G31*'前提と出典'!$B$13,0) -> 0 | P31: =IF(J31=1,MIN('前提と出典'!$B$17,L31+N31),0) -> 0 | Q31: =IF(J31=0,0,IF('前提と出典'!$B$19=0,P31*L31/(L31+N31),MIN(P31,L31))) -> 0 | R31: =P31-Q31 -> 0 | S31: =IF(H31=1,'前提と出典'!$B$11+F31*'前提と出典'!$B$12,0) -> 0 | T31: =IF(H31=1,('前提と出典'!$B$9+F31*'前提と出典'!$B$10)/60*'前提と出典'!$B$8,0) -> 0 | U31: =IF(I31=1,INDEX('前提と出典'!B80:B83,'前提と出典'!$B$18+1)+G31*INDEX('前提と出典'!C80:C83,'前提と出典'!$B$18+1),0) -> 0 | V31: =IF(I31=1,INDEX('前提と出典'!D80:D83,'前提と出典'!$B$18+1)+G31*INDEX('前提と出典'!E80:E83,'前提と出典'!$B$18+1),0) -> 0 | W31: =L31-Q31 -> 0 | X31: =N31-R31 -> 0
A32: 1 | B32: 6 | C32: 1 | D32: ='前提と出典'!D58*(1-'前提と出典'!$B$21) -> 0.0015 | E32: =ROUNDUP('前提と出典'!B58*'前提と出典'!$B$23,0) -> 300 | F32: ='前提と出典'!A58 -> 130 | G32: =MAX(1,ROUNDUP(E32*'前提と出典'!$B$25*'前提と出典'!E11,0)) -> 90 | H32: =IF(AND(F32>=1,F32<=100),1,0) -> 0 | I32: =IF(G32<=50,1,0) -> 0 | J32: =H32*I32 -> 0 | K32: =IF(A32='前提と出典'!$B$14,D32,0) -> 0.0015 | L32: =IF(H32=0,0,IF(F32<=INDEX('前提と出典'!B41:B43,'前提と出典'!$B$15+1),INDEX('前提と出典'!C41:C43,'前提と出典'!$B$15+1),IF(F32<=INDEX('前提と出典'!D41:D43,'前提と出典'!$B$15+1),INDEX('前提と出典'!E41:E43,'前提と出典'!$B$15+1),INDEX('前提と出典'!G41:G43,'前提と出典'!$B$15+1)))) -> 0 | M32: =IF(H32=0,0,IF('前提と出典'!$B$33=1,MIN(F32,10)*300+MIN(MAX(0,F32-10),20)*250+MAX(0,F32-30)*200,F32*300)) -> 0 | N32: =IF(I32=0,0,IF(G32<=INDEX('前提と出典'!B46:B48,'前提と出典'!$B$16+1),INDEX('前提と出典'!C46:C48,'前提と出典'!$B$16+1),IF(G32<=INDEX('前提と出典'!D46:D48,'前提と出典'!$B$16+1),INDEX('前提と出典'!E46:E48,'前提と出典'!$B$16+1),IF(G32<=INDEX('前提と出典'!F46:F48,'前提と出典'!$B$16+1),INDEX('前提と出典'!G46:G48,'前提と出典'!$B$16+1),INDEX('前提と出典'!I46:I48,'前提と出典'!$B$16+1))))) -> 0 | O32: =IF(I32=1,G32*'前提と出典'!$B$13,0) -> 0 | P32: =IF(J32=1,MIN('前提と出典'!$B$17,L32+N32),0) -> 0 | Q32: =IF(J32=0,0,IF('前提と出典'!$B$19=0,P32*L32/(L32+N32),MIN(P32,L32))) -> 0 | R32: =P32-Q32 -> 0 | S32: =IF(H32=1,'前提と出典'!$B$11+F32*'前提と出典'!$B$12,0) -> 0 | T32: =IF(H32=1,('前提と出典'!$B$9+F32*'前提と出典'!$B$10)/60*'前提と出典'!$B$8,0) -> 0 | U32: =IF(I32=1,INDEX('前提と出典'!B80:B83,'前提と出典'!$B$18+1)+G32*INDEX('前提と出典'!C80:C83,'前提と出典'!$B$18+1),0) -> 0 | V32: =IF(I32=1,INDEX('前提と出典'!D80:D83,'前提と出典'!$B$18+1)+G32*INDEX('前提と出典'!E80:E83,'前提と出典'!$B$18+1),0) -> 0 | W32: =L32-Q32 -> 0 | X32: =N32-R32 -> 0
A33: 2 | B33: 0 | C33: 0 | D33: ='前提と出典'!E52*'前提と出典'!$B$21 -> 0.035 | E33: =ROUNDUP('前提と出典'!B52*'前提と出典'!$B$22,0) -> 6 | F33: ='前提と出典'!A52 -> 0 | G33: =MAX(1,ROUNDUP(E33*'前提と出典'!$B$24*'前提と出典'!E12,0)) -> 1 | H33: =IF(AND(F33>=1,F33<=100),1,0) -> 0 | I33: =IF(G33<=50,1,0) -> 1 | J33: =H33*I33 -> 0 | K33: =IF(A33='前提と出典'!$B$14,D33,0) -> 0 | L33: =IF(H33=0,0,IF(F33<=INDEX('前提と出典'!B41:B43,'前提と出典'!$B$15+1),INDEX('前提と出典'!C41:C43,'前提と出典'!$B$15+1),IF(F33<=INDEX('前提と出典'!D41:D43,'前提と出典'!$B$15+1),INDEX('前提と出典'!E41:E43,'前提と出典'!$B$15+1),INDEX('前提と出典'!G41:G43,'前提と出典'!$B$15+1)))) -> 0 | M33: =IF(H33=0,0,IF('前提と出典'!$B$33=1,MIN(F33,10)*300+MIN(MAX(0,F33-10),20)*250+MAX(0,F33-30)*200,F33*300)) -> 0 | N33: =IF(I33=0,0,IF(G33<=INDEX('前提と出典'!B46:B48,'前提と出典'!$B$16+1),INDEX('前提と出典'!C46:C48,'前提と出典'!$B$16+1),IF(G33<=INDEX('前提と出典'!D46:D48,'前提と出典'!$B$16+1),INDEX('前提と出典'!E46:E48,'前提と出典'!$B$16+1),IF(G33<=INDEX('前提と出典'!F46:F48,'前提と出典'!$B$16+1),INDEX('前提と出典'!G46:G48,'前提と出典'!$B$16+1),INDEX('前提と出典'!I46:I48,'前提と出典'!$B$16+1))))) -> 1200 | O33: =IF(I33=1,G33*'前提と出典'!$B$13,0) -> 200 | P33: =IF(J33=1,MIN('前提と出典'!$B$17,L33+N33),0) -> 0 | Q33: =IF(J33=0,0,IF('前提と出典'!$B$19=0,P33*L33/(L33+N33),MIN(P33,L33))) -> 0 | R33: =P33-Q33 -> 0 | S33: =IF(H33=1,'前提と出典'!$B$11+F33*'前提と出典'!$B$12,0) -> 0 | T33: =IF(H33=1,('前提と出典'!$B$9+F33*'前提と出典'!$B$10)/60*'前提と出典'!$B$8,0) -> 0 | U33: =IF(I33=1,INDEX('前提と出典'!B80:B83,'前提と出典'!$B$18+1)+G33*INDEX('前提と出典'!C80:C83,'前提と出典'!$B$18+1),0) -> 69.771024 | V33: =IF(I33=1,INDEX('前提と出典'!D80:D83,'前提と出典'!$B$18+1)+G33*INDEX('前提と出典'!E80:E83,'前提と出典'!$B$18+1),0) -> 540 | W33: =L33-Q33 -> 0 | X33: =N33-R33 -> 1200
A34: 2 | B34: 0 | C34: 1 | D34: ='前提と出典'!E52*(1-'前提と出典'!$B$21) -> 0.015 | E34: =ROUNDUP('前提と出典'!B52*'前提と出典'!$B$23,0) -> 3 | F34: ='前提と出典'!A52 -> 0 | G34: =MAX(1,ROUNDUP(E34*'前提と出典'!$B$25*'前提と出典'!E12,0)) -> 2 | H34: =IF(AND(F34>=1,F34<=100),1,0) -> 0 | I34: =IF(G34<=50,1,0) -> 1 | J34: =H34*I34 -> 0 | K34: =IF(A34='前提と出典'!$B$14,D34,0) -> 0 | L34: =IF(H34=0,0,IF(F34<=INDEX('前提と出典'!B41:B43,'前提と出典'!$B$15+1),INDEX('前提と出典'!C41:C43,'前提と出典'!$B$15+1),IF(F34<=INDEX('前提と出典'!D41:D43,'前提と出典'!$B$15+1),INDEX('前提と出典'!E41:E43,'前提と出典'!$B$15+1),INDEX('前提と出典'!G41:G43,'前提と出典'!$B$15+1)))) -> 0 | M34: =IF(H34=0,0,IF('前提と出典'!$B$33=1,MIN(F34,10)*300+MIN(MAX(0,F34-10),20)*250+MAX(0,F34-30)*200,F34*300)) -> 0 | N34: =IF(I34=0,0,IF(G34<=INDEX('前提と出典'!B46:B48,'前提と出典'!$B$16+1),INDEX('前提と出典'!C46:C48,'前提と出典'!$B$16+1),IF(G34<=INDEX('前提と出典'!D46:D48,'前提と出典'!$B$16+1),INDEX('前提と出典'!E46:E48,'前提と出典'!$B$16+1),IF(G34<=INDEX('前提と出典'!F46:F48,'前提と出典'!$B$16+1),INDEX('前提と出典'!G46:G48,'前提と出典'!$B$16+1),INDEX('前提と出典'!I46:I48,'前提と出典'!$B$16+1))))) -> 1200 | O34: =IF(I34=1,G34*'前提と出典'!$B$13,0) -> 400 | P34: =IF(J34=1,MIN('前提と出典'!$B$17,L34+N34),0) -> 0 | Q34: =IF(J34=0,0,IF('前提と出典'!$B$19=0,P34*L34/(L34+N34),MIN(P34,L34))) -> 0 | R34: =P34-Q34 -> 0 | S34: =IF(H34=1,'前提と出典'!$B$11+F34*'前提と出典'!$B$12,0) -> 0 | T34: =IF(H34=1,('前提と出典'!$B$9+F34*'前提と出典'!$B$10)/60*'前提と出典'!$B$8,0) -> 0 | U34: =IF(I34=1,INDEX('前提と出典'!B80:B83,'前提と出典'!$B$18+1)+G34*INDEX('前提と出典'!C80:C83,'前提と出典'!$B$18+1),0) -> 89.542049 | V34: =IF(I34=1,INDEX('前提と出典'!D80:D83,'前提と出典'!$B$18+1)+G34*INDEX('前提と出典'!E80:E83,'前提と出典'!$B$18+1),0) -> 546.66667 | W34: =L34-Q34 -> 0 | X34: =N34-R34 -> 1200
A35: 2 | B35: 1 | C35: 0 | D35: ='前提と出典'!E53*'前提と出典'!$B$21 -> 0.175 | E35: =ROUNDUP('前提と出典'!B53*'前提と出典'!$B$22,0) -> 15 | F35: ='前提と出典'!A53 -> 3 | G35: =MAX(1,ROUNDUP(E35*'前提と出典'!$B$24*'前提と出典'!E12,0)) -> 3 | H35: =IF(AND(F35>=1,F35<=100),1,0) -> 1 | I35: =IF(G35<=50,1,0) -> 1 | J35: =H35*I35 -> 1 | K35: =IF(A35='前提と出典'!$B$14,D35,0) -> 0 | L35: =IF(H35=0,0,IF(F35<=INDEX('前提と出典'!B41:B43,'前提と出典'!$B$15+1),INDEX('前提と出典'!C41:C43,'前提と出典'!$B$15+1),IF(F35<=INDEX('前提と出典'!D41:D43,'前提と出典'!$B$15+1),INDEX('前提と出典'!E41:E43,'前提と出典'!$B$15+1),INDEX('前提と出典'!G41:G43,'前提と出典'!$B$15+1)))) -> 2500 | M35: =IF(H35=0,0,IF('前提と出典'!$B$33=1,MIN(F35,10)*300+MIN(MAX(0,F35-10),20)*250+MAX(0,F35-30)*200,F35*300)) -> 900 | N35: =IF(I35=0,0,IF(G35<=INDEX('前提と出典'!B46:B48,'前提と出典'!$B$16+1),INDEX('前提と出典'!C46:C48,'前提と出典'!$B$16+1),IF(G35<=INDEX('前提と出典'!D46:D48,'前提と出典'!$B$16+1),INDEX('前提と出典'!E46:E48,'前提と出典'!$B$16+1),IF(G35<=INDEX('前提と出典'!F46:F48,'前提と出典'!$B$16+1),INDEX('前提と出典'!G46:G48,'前提と出典'!$B$16+1),INDEX('前提と出典'!I46:I48,'前提と出典'!$B$16+1))))) -> 1200 | O35: =IF(I35=1,G35*'前提と出典'!$B$13,0) -> 600 | P35: =IF(J35=1,MIN('前提と出典'!$B$17,L35+N35),0) -> 500 | Q35: =IF(J35=0,0,IF('前提と出典'!$B$19=0,P35*L35/(L35+N35),MIN(P35,L35))) -> 337.83784 | R35: =P35-Q35 -> 162.16216 | S35: =IF(H35=1,'前提と出典'!$B$11+F35*'前提と出典'!$B$12,0) -> 53 | T35: =IF(H35=1,('前提と出典'!$B$9+F35*'前提と出典'!$B$10)/60*'前提と出典'!$B$8,0) -> 553.33333 | U35: =IF(I35=1,INDEX('前提と出典'!B80:B83,'前提と出典'!$B$18+1)+G35*INDEX('前提と出典'!C80:C83,'前提と出典'!$B$18+1),0) -> 109.31307 | V35: =IF(I35=1,INDEX('前提と出典'!D80:D83,'前提と出典'!$B$18+1)+G35*INDEX('前提と出典'!E80:E83,'前提と出典'!$B$18+1),0) -> 553.33333 | W35: =L35-Q35 -> 2162.1622 | X35: =N35-R35 -> 1037.8378
A36: 2 | B36: 1 | C36: 1 | D36: ='前提と出典'!E53*(1-'前提と出典'!$B$21) -> 0.075 | E36: =ROUNDUP('前提と出典'!B53*'前提と出典'!$B$23,0) -> 8 | F36: ='前提と出典'!A53 -> 3 | G36: =MAX(1,ROUNDUP(E36*'前提と出典'!$B$25*'前提と出典'!E12,0)) -> 4 | H36: =IF(AND(F36>=1,F36<=100),1,0) -> 1 | I36: =IF(G36<=50,1,0) -> 1 | J36: =H36*I36 -> 1 | K36: =IF(A36='前提と出典'!$B$14,D36,0) -> 0 | L36: =IF(H36=0,0,IF(F36<=INDEX('前提と出典'!B41:B43,'前提と出典'!$B$15+1),INDEX('前提と出典'!C41:C43,'前提と出典'!$B$15+1),IF(F36<=INDEX('前提と出典'!D41:D43,'前提と出典'!$B$15+1),INDEX('前提と出典'!E41:E43,'前提と出典'!$B$15+1),INDEX('前提と出典'!G41:G43,'前提と出典'!$B$15+1)))) -> 2500 | M36: =IF(H36=0,0,IF('前提と出典'!$B$33=1,MIN(F36,10)*300+MIN(MAX(0,F36-10),20)*250+MAX(0,F36-30)*200,F36*300)) -> 900 | N36: =IF(I36=0,0,IF(G36<=INDEX('前提と出典'!B46:B48,'前提と出典'!$B$16+1),INDEX('前提と出典'!C46:C48,'前提と出典'!$B$16+1),IF(G36<=INDEX('前提と出典'!D46:D48,'前提と出典'!$B$16+1),INDEX('前提と出典'!E46:E48,'前提と出典'!$B$16+1),IF(G36<=INDEX('前提と出典'!F46:F48,'前提と出典'!$B$16+1),INDEX('前提と出典'!G46:G48,'前提と出典'!$B$16+1),INDEX('前提と出典'!I46:I48,'前提と出典'!$B$16+1))))) -> 1200 | O36: =IF(I36=1,G36*'前提と出典'!$B$13,0) -> 800 | P36: =IF(J36=1,MIN('前提と出典'!$B$17,L36+N36),0) -> 500 | Q36: =IF(J36=0,0,IF('前提と出典'!$B$19=0,P36*L36/(L36+N36),MIN(P36,L36))) -> 337.83784 | R36: =P36-Q36 -> 162.16216 | S36: =IF(H36=1,'前提と出典'!$B$11+F36*'前提と出典'!$B$12,0) -> 53 | T36: =IF(H36=1,('前提と出典'!$B$9+F36*'前提と出典'!$B$10)/60*'前提と出典'!$B$8,0) -> 553.33333 | U36: =IF(I36=1,INDEX('前提と出典'!B80:B83,'前提と出典'!$B$18+1)+G36*INDEX('前提と出典'!C80:C83,'前提と出典'!$B$18+1),0) -> 129.0841 | V36: =IF(I36=1,INDEX('前提と出典'!D80:D83,'前提と出典'!$B$18+1)+G36*INDEX('前提と出典'!E80:E83,'前提と出典'!$B$18+1),0) -> 560 | W36: =L36-Q36 -> 2162.1622 | X36: =N36-R36 -> 1037.8378
A37: 2 | B37: 2 | C37: 0 | D37: ='前提と出典'!E54*'前提と出典'!$B$21 -> 0.175 | E37: =ROUNDUP('前提と出典'!B54*'前提と出典'!$B$22,0) -> 38 | F37: ='前提と出典'!A54 -> 8 | G37: =MAX(1,ROUNDUP(E37*'前提と出典'!$B$24*'前提と出典'!E12,0)) -> 6 | H37: =IF(AND(F37>=1,F37<=100),1,0) -> 1 | I37: =IF(G37<=50,1,0) -> 1 | J37: =H37*I37 -> 1 | K37: =IF(A37='前提と出典'!$B$14,D37,0) -> 0 | L37: =IF(H37=0,0,IF(F37<=INDEX('前提と出典'!B41:B43,'前提と出典'!$B$15+1),INDEX('前提と出典'!C41:C43,'前提と出典'!$B$15+1),IF(F37<=INDEX('前提と出典'!D41:D43,'前提と出典'!$B$15+1),INDEX('前提と出典'!E41:E43,'前提と出典'!$B$15+1),INDEX('前提と出典'!G41:G43,'前提と出典'!$B$15+1)))) -> 2500 | M37: =IF(H37=0,0,IF('前提と出典'!$B$33=1,MIN(F37,10)*300+MIN(MAX(0,F37-10),20)*250+MAX(0,F37-30)*200,F37*300)) -> 2400 | N37: =IF(I37=0,0,IF(G37<=INDEX('前提と出典'!B46:B48,'前提と出典'!$B$16+1),INDEX('前提と出典'!C46:C48,'前提と出典'!$B$16+1),IF(G37<=INDEX('前提と出典'!D46:D48,'前提と出典'!$B$16+1),INDEX('前提と出典'!E46:E48,'前提と出典'!$B$16+1),IF(G37<=INDEX('前提と出典'!F46:F48,'前提と出典'!$B$16+1),INDEX('前提と出典'!G46:G48,'前提と出典'!$B$16+1),INDEX('前提と出典'!I46:I48,'前提と出典'!$B$16+1))))) -> 1200 | O37: =IF(I37=1,G37*'前提と出典'!$B$13,0) -> 1200 | P37: =IF(J37=1,MIN('前提と出典'!$B$17,L37+N37),0) -> 500 | Q37: =IF(J37=0,0,IF('前提と出典'!$B$19=0,P37*L37/(L37+N37),MIN(P37,L37))) -> 337.83784 | R37: =P37-Q37 -> 162.16216 | S37: =IF(H37=1,'前提と出典'!$B$11+F37*'前提と出典'!$B$12,0) -> 58 | T37: =IF(H37=1,('前提と出典'!$B$9+F37*'前提と出典'!$B$10)/60*'前提と出典'!$B$8,0) -> 586.66667 | U37: =IF(I37=1,INDEX('前提と出典'!B80:B83,'前提と出典'!$B$18+1)+G37*INDEX('前提と出典'!C80:C83,'前提と出典'!$B$18+1),0) -> 168.62615 | V37: =IF(I37=1,INDEX('前提と出典'!D80:D83,'前提と出典'!$B$18+1)+G37*INDEX('前提と出典'!E80:E83,'前提と出典'!$B$18+1),0) -> 573.33333 | W37: =L37-Q37 -> 2162.1622 | X37: =N37-R37 -> 1037.8378
A38: 2 | B38: 2 | C38: 1 | D38: ='前提と出典'!E54*(1-'前提と出典'!$B$21) -> 0.075 | E38: =ROUNDUP('前提と出典'!B54*'前提と出典'!$B$23,0) -> 19 | F38: ='前提と出典'!A54 -> 8 | G38: =MAX(1,ROUNDUP(E38*'前提と出典'!$B$25*'前提と出典'!E12,0)) -> 9 | H38: =IF(AND(F38>=1,F38<=100),1,0) -> 1 | I38: =IF(G38<=50,1,0) -> 1 | J38: =H38*I38 -> 1 | K38: =IF(A38='前提と出典'!$B$14,D38,0) -> 0 | L38: =IF(H38=0,0,IF(F38<=INDEX('前提と出典'!B41:B43,'前提と出典'!$B$15+1),INDEX('前提と出典'!C41:C43,'前提と出典'!$B$15+1),IF(F38<=INDEX('前提と出典'!D41:D43,'前提と出典'!$B$15+1),INDEX('前提と出典'!E41:E43,'前提と出典'!$B$15+1),INDEX('前提と出典'!G41:G43,'前提と出典'!$B$15+1)))) -> 2500 | M38: =IF(H38=0,0,IF('前提と出典'!$B$33=1,MIN(F38,10)*300+MIN(MAX(0,F38-10),20)*250+MAX(0,F38-30)*200,F38*300)) -> 2400 | N38: =IF(I38=0,0,IF(G38<=INDEX('前提と出典'!B46:B48,'前提と出典'!$B$16+1),INDEX('前提と出典'!C46:C48,'前提と出典'!$B$16+1),IF(G38<=INDEX('前提と出典'!D46:D48,'前提と出典'!$B$16+1),INDEX('前提と出典'!E46:E48,'前提と出典'!$B$16+1),IF(G38<=INDEX('前提と出典'!F46:F48,'前提と出典'!$B$16+1),INDEX('前提と出典'!G46:G48,'前提と出典'!$B$16+1),INDEX('前提と出典'!I46:I48,'前提と出典'!$B$16+1))))) -> 1200 | O38: =IF(I38=1,G38*'前提と出典'!$B$13,0) -> 1800 | P38: =IF(J38=1,MIN('前提と出典'!$B$17,L38+N38),0) -> 500 | Q38: =IF(J38=0,0,IF('前提と出典'!$B$19=0,P38*L38/(L38+N38),MIN(P38,L38))) -> 337.83784 | R38: =P38-Q38 -> 162.16216 | S38: =IF(H38=1,'前提と出典'!$B$11+F38*'前提と出典'!$B$12,0) -> 58 | T38: =IF(H38=1,('前提と出典'!$B$9+F38*'前提と出典'!$B$10)/60*'前提と出典'!$B$8,0) -> 586.66667 | U38: =IF(I38=1,INDEX('前提と出典'!B80:B83,'前提と出典'!$B$18+1)+G38*INDEX('前提と出典'!C80:C83,'前提と出典'!$B$18+1),0) -> 227.93922 | V38: =IF(I38=1,INDEX('前提と出典'!D80:D83,'前提と出典'!$B$18+1)+G38*INDEX('前提と出典'!E80:E83,'前提と出典'!$B$18+1),0) -> 593.33333 | W38: =L38-Q38 -> 2162.1622 | X38: =N38-R38 -> 1037.8378
A39: 2 | B39: 3 | C39: 0 | D39: ='前提と出典'!E55*'前提と出典'!$B$21 -> 0.21 | E39: =ROUNDUP('前提と出典'!B55*'前提と出典'!$B$22,0) -> 90 | F39: ='前提と出典'!A55 -> 18 | G39: =MAX(1,ROUNDUP(E39*'前提と出典'!$B$24*'前提と出典'!E12,0)) -> 14 | H39: =IF(AND(F39>=1,F39<=100),1,0) -> 1 | I39: =IF(G39<=50,1,0) -> 1 | J39: =H39*I39 -> 1 | K39: =IF(A39='前提と出典'!$B$14,D39,0) -> 0 | L39: =IF(H39=0,0,IF(F39<=INDEX('前提と出典'!B41:B43,'前提と出典'!$B$15+1),INDEX('前提と出典'!C41:C43,'前提と出典'!$B$15+1),IF(F39<=INDEX('前提と出典'!D41:D43,'前提と出典'!$B$15+1),INDEX('前提と出典'!E41:E43,'前提と出典'!$B$15+1),INDEX('前提と出典'!G41:G43,'前提と出典'!$B$15+1)))) -> 4000 | M39: =IF(H39=0,0,IF('前提と出典'!$B$33=1,MIN(F39,10)*300+MIN(MAX(0,F39-10),20)*250+MAX(0,F39-30)*200,F39*300)) -> 5000 | N39: =IF(I39=0,0,IF(G39<=INDEX('前提と出典'!B46:B48,'前提と出典'!$B$16+1),INDEX('前提と出典'!C46:C48,'前提と出典'!$B$16+1),IF(G39<=INDEX('前提と出典'!D46:D48,'前提と出典'!$B$16+1),INDEX('前提と出典'!E46:E48,'前提と出典'!$B$16+1),IF(G39<=INDEX('前提と出典'!F46:F48,'前提と出典'!$B$16+1),INDEX('前提と出典'!G46:G48,'前提と出典'!$B$16+1),INDEX('前提と出典'!I46:I48,'前提と出典'!$B$16+1))))) -> 2500 | O39: =IF(I39=1,G39*'前提と出典'!$B$13,0) -> 2800 | P39: =IF(J39=1,MIN('前提と出典'!$B$17,L39+N39),0) -> 500 | Q39: =IF(J39=0,0,IF('前提と出典'!$B$19=0,P39*L39/(L39+N39),MIN(P39,L39))) -> 307.69231 | R39: =P39-Q39 -> 192.30769 | S39: =IF(H39=1,'前提と出典'!$B$11+F39*'前提と出典'!$B$12,0) -> 68 | T39: =IF(H39=1,('前提と出典'!$B$9+F39*'前提と出典'!$B$10)/60*'前提と出典'!$B$8,0) -> 653.33333 | U39: =IF(I39=1,INDEX('前提と出典'!B80:B83,'前提と出典'!$B$18+1)+G39*INDEX('前提と出典'!C80:C83,'前提と出典'!$B$18+1),0) -> 326.79434 | V39: =IF(I39=1,INDEX('前提と出典'!D80:D83,'前提と出典'!$B$18+1)+G39*INDEX('前提と出典'!E80:E83,'前提と出典'!$B$18+1),0) -> 626.66667 | W39: =L39-Q39 -> 3692.3077 | X39: =N39-R39 -> 2307.6923
A40: 2 | B40: 3 | C40: 1 | D40: ='前提と出典'!E55*(1-'前提と出典'!$B$21) -> 0.09 | E40: =ROUNDUP('前提と出典'!B55*'前提と出典'!$B$23,0) -> 45 | F40: ='前提と出典'!A55 -> 18 | G40: =MAX(1,ROUNDUP(E40*'前提と出典'!$B$25*'前提と出典'!E12,0)) -> 21 | H40: =IF(AND(F40>=1,F40<=100),1,0) -> 1 | I40: =IF(G40<=50,1,0) -> 1 | J40: =H40*I40 -> 1 | K40: =IF(A40='前提と出典'!$B$14,D40,0) -> 0 | L40: =IF(H40=0,0,IF(F40<=INDEX('前提と出典'!B41:B43,'前提と出典'!$B$15+1),INDEX('前提と出典'!C41:C43,'前提と出典'!$B$15+1),IF(F40<=INDEX('前提と出典'!D41:D43,'前提と出典'!$B$15+1),INDEX('前提と出典'!E41:E43,'前提と出典'!$B$15+1),INDEX('前提と出典'!G41:G43,'前提と出典'!$B$15+1)))) -> 4000 | M40: =IF(H40=0,0,IF('前提と出典'!$B$33=1,MIN(F40,10)*300+MIN(MAX(0,F40-10),20)*250+MAX(0,F40-30)*200,F40*300)) -> 5000 | N40: =IF(I40=0,0,IF(G40<=INDEX('前提と出典'!B46:B48,'前提と出典'!$B$16+1),INDEX('前提と出典'!C46:C48,'前提と出典'!$B$16+1),IF(G40<=INDEX('前提と出典'!D46:D48,'前提と出典'!$B$16+1),INDEX('前提と出典'!E46:E48,'前提と出典'!$B$16+1),IF(G40<=INDEX('前提と出典'!F46:F48,'前提と出典'!$B$16+1),INDEX('前提と出典'!G46:G48,'前提と出典'!$B$16+1),INDEX('前提と出典'!I46:I48,'前提と出典'!$B$16+1))))) -> 2500 | O40: =IF(I40=1,G40*'前提と出典'!$B$13,0) -> 4200 | P40: =IF(J40=1,MIN('前提と出典'!$B$17,L40+N40),0) -> 500 | Q40: =IF(J40=0,0,IF('前提と出典'!$B$19=0,P40*L40/(L40+N40),MIN(P40,L40))) -> 307.69231 | R40: =P40-Q40 -> 192.30769 | S40: =IF(H40=1,'前提と出典'!$B$11+F40*'前提と出典'!$B$12,0) -> 68 | T40: =IF(H40=1,('前提と出典'!$B$9+F40*'前提と出典'!$B$10)/60*'前提と出典'!$B$8,0) -> 653.33333 | U40: =IF(I40=1,INDEX('前提と出典'!B80:B83,'前提と出典'!$B$18+1)+G40*INDEX('前提と出典'!C80:C83,'前提と出典'!$B$18+1),0) -> 465.19151 | V40: =IF(I40=1,INDEX('前提と出典'!D80:D83,'前提と出典'!$B$18+1)+G40*INDEX('前提と出典'!E80:E83,'前提と出典'!$B$18+1),0) -> 673.33333 | W40: =L40-Q40 -> 3692.3077 | X40: =N40-R40 -> 2307.6923
A41: 2 | B41: 4 | C41: 0 | D41: ='前提と出典'!E56*'前提と出典'!$B$21 -> 0.063 | E41: =ROUNDUP('前提と出典'!B56*'前提と出典'!$B$22,0) -> 180 | F41: ='前提と出典'!A56 -> 40 | G41: =MAX(1,ROUNDUP(E41*'前提と出典'!$B$24*'前提と出典'!E12,0)) -> 27 | H41: =IF(AND(F41>=1,F41<=100),1,0) -> 1 | I41: =IF(G41<=50,1,0) -> 1 | J41: =H41*I41 -> 1 | K41: =IF(A41='前提と出典'!$B$14,D41,0) -> 0 | L41: =IF(H41=0,0,IF(F41<=INDEX('前提と出典'!B41:B43,'前提と出典'!$B$15+1),INDEX('前提と出典'!C41:C43,'前提と出典'!$B$15+1),IF(F41<=INDEX('前提と出典'!D41:D43,'前提と出典'!$B$15+1),INDEX('前提と出典'!E41:E43,'前提と出典'!$B$15+1),INDEX('前提と出典'!G41:G43,'前提と出典'!$B$15+1)))) -> 4000 | M41: =IF(H41=0,0,IF('前提と出典'!$B$33=1,MIN(F41,10)*300+MIN(MAX(0,F41-10),20)*250+MAX(0,F41-30)*200,F41*300)) -> 10000 | N41: =IF(I41=0,0,IF(G41<=INDEX('前提と出典'!B46:B48,'前提と出典'!$B$16+1),INDEX('前提と出典'!C46:C48,'前提と出典'!$B$16+1),IF(G41<=INDEX('前提と出典'!D46:D48,'前提と出典'!$B$16+1),INDEX('前提と出典'!E46:E48,'前提と出典'!$B$16+1),IF(G41<=INDEX('前提と出典'!F46:F48,'前提と出典'!$B$16+1),INDEX('前提と出典'!G46:G48,'前提と出典'!$B$16+1),INDEX('前提と出典'!I46:I48,'前提と出典'!$B$16+1))))) -> 2500 | O41: =IF(I41=1,G41*'前提と出典'!$B$13,0) -> 5400 | P41: =IF(J41=1,MIN('前提と出典'!$B$17,L41+N41),0) -> 500 | Q41: =IF(J41=0,0,IF('前提と出典'!$B$19=0,P41*L41/(L41+N41),MIN(P41,L41))) -> 307.69231 | R41: =P41-Q41 -> 192.30769 | S41: =IF(H41=1,'前提と出典'!$B$11+F41*'前提と出典'!$B$12,0) -> 90 | T41: =IF(H41=1,('前提と出典'!$B$9+F41*'前提と出典'!$B$10)/60*'前提と出典'!$B$8,0) -> 800 | U41: =IF(I41=1,INDEX('前提と出典'!B80:B83,'前提と出典'!$B$18+1)+G41*INDEX('前提と出典'!C80:C83,'前提と出典'!$B$18+1),0) -> 583.81766 | V41: =IF(I41=1,INDEX('前提と出典'!D80:D83,'前提と出典'!$B$18+1)+G41*INDEX('前提と出典'!E80:E83,'前提と出典'!$B$18+1),0) -> 713.33333 | W41: =L41-Q41 -> 3692.3077 | X41: =N41-R41 -> 2307.6923
A42: 2 | B42: 4 | C42: 1 | D42: ='前提と出典'!E56*(1-'前提と出典'!$B$21) -> 0.027 | E42: =ROUNDUP('前提と出典'!B56*'前提と出典'!$B$23,0) -> 90 | F42: ='前提と出典'!A56 -> 40 | G42: =MAX(1,ROUNDUP(E42*'前提と出典'!$B$25*'前提と出典'!E12,0)) -> 41 | H42: =IF(AND(F42>=1,F42<=100),1,0) -> 1 | I42: =IF(G42<=50,1,0) -> 1 | J42: =H42*I42 -> 1 | K42: =IF(A42='前提と出典'!$B$14,D42,0) -> 0 | L42: =IF(H42=0,0,IF(F42<=INDEX('前提と出典'!B41:B43,'前提と出典'!$B$15+1),INDEX('前提と出典'!C41:C43,'前提と出典'!$B$15+1),IF(F42<=INDEX('前提と出典'!D41:D43,'前提と出典'!$B$15+1),INDEX('前提と出典'!E41:E43,'前提と出典'!$B$15+1),INDEX('前提と出典'!G41:G43,'前提と出典'!$B$15+1)))) -> 4000 | M42: =IF(H42=0,0,IF('前提と出典'!$B$33=1,MIN(F42,10)*300+MIN(MAX(0,F42-10),20)*250+MAX(0,F42-30)*200,F42*300)) -> 10000 | N42: =IF(I42=0,0,IF(G42<=INDEX('前提と出典'!B46:B48,'前提と出典'!$B$16+1),INDEX('前提と出典'!C46:C48,'前提と出典'!$B$16+1),IF(G42<=INDEX('前提と出典'!D46:D48,'前提と出典'!$B$16+1),INDEX('前提と出典'!E46:E48,'前提と出典'!$B$16+1),IF(G42<=INDEX('前提と出典'!F46:F48,'前提と出典'!$B$16+1),INDEX('前提と出典'!G46:G48,'前提と出典'!$B$16+1),INDEX('前提と出典'!I46:I48,'前提と出典'!$B$16+1))))) -> 2500 | O42: =IF(I42=1,G42*'前提と出典'!$B$13,0) -> 8200 | P42: =IF(J42=1,MIN('前提と出典'!$B$17,L42+N42),0) -> 500 | Q42: =IF(J42=0,0,IF('前提と出典'!$B$19=0,P42*L42/(L42+N42),MIN(P42,L42))) -> 307.69231 | R42: =P42-Q42 -> 192.30769 | S42: =IF(H42=1,'前提と出典'!$B$11+F42*'前提と出典'!$B$12,0) -> 90 | T42: =IF(H42=1,('前提と出典'!$B$9+F42*'前提と出典'!$B$10)/60*'前提と出典'!$B$8,0) -> 800 | U42: =IF(I42=1,INDEX('前提と出典'!B80:B83,'前提と出典'!$B$18+1)+G42*INDEX('前提と出典'!C80:C83,'前提と出典'!$B$18+1),0) -> 860.612 | V42: =IF(I42=1,INDEX('前提と出典'!D80:D83,'前提と出典'!$B$18+1)+G42*INDEX('前提と出典'!E80:E83,'前提と出典'!$B$18+1),0) -> 806.66667 | W42: =L42-Q42 -> 3692.3077 | X42: =N42-R42 -> 2307.6923
A43: 2 | B43: 5 | C43: 0 | D43: ='前提と出典'!E57*'前提と出典'!$B$21 -> 0.028 | E43: =ROUNDUP('前提と出典'!B57*'前提と出典'!$B$22,0) -> 300 | F43: ='前提と出典'!A57 -> 70 | G43: =MAX(1,ROUNDUP(E43*'前提と出典'!$B$24*'前提と出典'!E12,0)) -> 45 | H43: =IF(AND(F43>=1,F43<=100),1,0) -> 1 | I43: =IF(G43<=50,1,0) -> 1 | J43: =H43*I43 -> 1 | K43: =IF(A43='前提と出典'!$B$14,D43,0) -> 0 | L43: =IF(H43=0,0,IF(F43<=INDEX('前提と出典'!B41:B43,'前提と出典'!$B$15+1),INDEX('前提と出典'!C41:C43,'前提と出典'!$B$15+1),IF(F43<=INDEX('前提と出典'!D41:D43,'前提と出典'!$B$15+1),INDEX('前提と出典'!E41:E43,'前提と出典'!$B$15+1),INDEX('前提と出典'!G41:G43,'前提と出典'!$B$15+1)))) -> 4000 | M43: =IF(H43=0,0,IF('前提と出典'!$B$33=1,MIN(F43,10)*300+MIN(MAX(0,F43-10),20)*250+MAX(0,F43-30)*200,F43*300)) -> 16000 | N43: =IF(I43=0,0,IF(G43<=INDEX('前提と出典'!B46:B48,'前提と出典'!$B$16+1),INDEX('前提と出典'!C46:C48,'前提と出典'!$B$16+1),IF(G43<=INDEX('前提と出典'!D46:D48,'前提と出典'!$B$16+1),INDEX('前提と出典'!E46:E48,'前提と出典'!$B$16+1),IF(G43<=INDEX('前提と出典'!F46:F48,'前提と出典'!$B$16+1),INDEX('前提と出典'!G46:G48,'前提と出典'!$B$16+1),INDEX('前提と出典'!I46:I48,'前提と出典'!$B$16+1))))) -> 2500 | O43: =IF(I43=1,G43*'前提と出典'!$B$13,0) -> 9000 | P43: =IF(J43=1,MIN('前提と出典'!$B$17,L43+N43),0) -> 500 | Q43: =IF(J43=0,0,IF('前提と出典'!$B$19=0,P43*L43/(L43+N43),MIN(P43,L43))) -> 307.69231 | R43: =P43-Q43 -> 192.30769 | S43: =IF(H43=1,'前提と出典'!$B$11+F43*'前提と出典'!$B$12,0) -> 120 | T43: =IF(H43=1,('前提と出典'!$B$9+F43*'前提と出典'!$B$10)/60*'前提と出典'!$B$8,0) -> 1000 | U43: =IF(I43=1,INDEX('前提と出典'!B80:B83,'前提と出典'!$B$18+1)+G43*INDEX('前提と出典'!C80:C83,'前提と出典'!$B$18+1),0) -> 939.6961 | V43: =IF(I43=1,INDEX('前提と出典'!D80:D83,'前提と出典'!$B$18+1)+G43*INDEX('前提と出典'!E80:E83,'前提と出典'!$B$18+1),0) -> 833.33333 | W43: =L43-Q43 -> 3692.3077 | X43: =N43-R43 -> 2307.6923
A44: 2 | B44: 5 | C44: 1 | D44: ='前提と出典'!E57*(1-'前提と出典'!$B$21) -> 0.012 | E44: =ROUNDUP('前提と出典'!B57*'前提と出典'!$B$23,0) -> 150 | F44: ='前提と出典'!A57 -> 70 | G44: =MAX(1,ROUNDUP(E44*'前提と出典'!$B$25*'前提と出典'!E12,0)) -> 68 | H44: =IF(AND(F44>=1,F44<=100),1,0) -> 1 | I44: =IF(G44<=50,1,0) -> 0 | J44: =H44*I44 -> 0 | K44: =IF(A44='前提と出典'!$B$14,D44,0) -> 0 | L44: =IF(H44=0,0,IF(F44<=INDEX('前提と出典'!B41:B43,'前提と出典'!$B$15+1),INDEX('前提と出典'!C41:C43,'前提と出典'!$B$15+1),IF(F44<=INDEX('前提と出典'!D41:D43,'前提と出典'!$B$15+1),INDEX('前提と出典'!E41:E43,'前提と出典'!$B$15+1),INDEX('前提と出典'!G41:G43,'前提と出典'!$B$15+1)))) -> 4000 | M44: =IF(H44=0,0,IF('前提と出典'!$B$33=1,MIN(F44,10)*300+MIN(MAX(0,F44-10),20)*250+MAX(0,F44-30)*200,F44*300)) -> 16000 | N44: =IF(I44=0,0,IF(G44<=INDEX('前提と出典'!B46:B48,'前提と出典'!$B$16+1),INDEX('前提と出典'!C46:C48,'前提と出典'!$B$16+1),IF(G44<=INDEX('前提と出典'!D46:D48,'前提と出典'!$B$16+1),INDEX('前提と出典'!E46:E48,'前提と出典'!$B$16+1),IF(G44<=INDEX('前提と出典'!F46:F48,'前提と出典'!$B$16+1),INDEX('前提と出典'!G46:G48,'前提と出典'!$B$16+1),INDEX('前提と出典'!I46:I48,'前提と出典'!$B$16+1))))) -> 0 | O44: =IF(I44=1,G44*'前提と出典'!$B$13,0) -> 0 | P44: =IF(J44=1,MIN('前提と出典'!$B$17,L44+N44),0) -> 0 | Q44: =IF(J44=0,0,IF('前提と出典'!$B$19=0,P44*L44/(L44+N44),MIN(P44,L44))) -> 0 | R44: =P44-Q44 -> 0 | S44: =IF(H44=1,'前提と出典'!$B$11+F44*'前提と出典'!$B$12,0) -> 120 | T44: =IF(H44=1,('前提と出典'!$B$9+F44*'前提と出典'!$B$10)/60*'前提と出典'!$B$8,0) -> 1000 | U44: =IF(I44=1,INDEX('前提と出典'!B80:B83,'前提と出典'!$B$18+1)+G44*INDEX('前提と出典'!C80:C83,'前提と出典'!$B$18+1),0) -> 0 | V44: =IF(I44=1,INDEX('前提と出典'!D80:D83,'前提と出典'!$B$18+1)+G44*INDEX('前提と出典'!E80:E83,'前提と出典'!$B$18+1),0) -> 0 | W44: =L44-Q44 -> 4000 | X44: =N44-R44 -> 0
A45: 2 | B45: 6 | C45: 0 | D45: ='前提と出典'!E58*'前提と出典'!$B$21 -> 0.014 | E45: =ROUNDUP('前提と出典'!B58*'前提と出典'!$B$22,0) -> 600 | F45: ='前提と出典'!A58 -> 130 | G45: =MAX(1,ROUNDUP(E45*'前提と出典'!$B$24*'前提と出典'!E12,0)) -> 90 | H45: =IF(AND(F45>=1,F45<=100),1,0) -> 0 | I45: =IF(G45<=50,1,0) -> 0 | J45: =H45*I45 -> 0 | K45: =IF(A45='前提と出典'!$B$14,D45,0) -> 0 | L45: =IF(H45=0,0,IF(F45<=INDEX('前提と出典'!B41:B43,'前提と出典'!$B$15+1),INDEX('前提と出典'!C41:C43,'前提と出典'!$B$15+1),IF(F45<=INDEX('前提と出典'!D41:D43,'前提と出典'!$B$15+1),INDEX('前提と出典'!E41:E43,'前提と出典'!$B$15+1),INDEX('前提と出典'!G41:G43,'前提と出典'!$B$15+1)))) -> 0 | M45: =IF(H45=0,0,IF('前提と出典'!$B$33=1,MIN(F45,10)*300+MIN(MAX(0,F45-10),20)*250+MAX(0,F45-30)*200,F45*300)) -> 0 | N45: =IF(I45=0,0,IF(G45<=INDEX('前提と出典'!B46:B48,'前提と出典'!$B$16+1),INDEX('前提と出典'!C46:C48,'前提と出典'!$B$16+1),IF(G45<=INDEX('前提と出典'!D46:D48,'前提と出典'!$B$16+1),INDEX('前提と出典'!E46:E48,'前提と出典'!$B$16+1),IF(G45<=INDEX('前提と出典'!F46:F48,'前提と出典'!$B$16+1),INDEX('前提と出典'!G46:G48,'前提と出典'!$B$16+1),INDEX('前提と出典'!I46:I48,'前提と出典'!$B$16+1))))) -> 0 | O45: =IF(I45=1,G45*'前提と出典'!$B$13,0) -> 0 | P45: =IF(J45=1,MIN('前提と出典'!$B$17,L45+N45),0) -> 0 | Q45: =IF(J45=0,0,IF('前提と出典'!$B$19=0,P45*L45/(L45+N45),MIN(P45,L45))) -> 0 | R45: =P45-Q45 -> 0 | S45: =IF(H45=1,'前提と出典'!$B$11+F45*'前提と出典'!$B$12,0) -> 0 | T45: =IF(H45=1,('前提と出典'!$B$9+F45*'前提と出典'!$B$10)/60*'前提と出典'!$B$8,0) -> 0 | U45: =IF(I45=1,INDEX('前提と出典'!B80:B83,'前提と出典'!$B$18+1)+G45*INDEX('前提と出典'!C80:C83,'前提と出典'!$B$18+1),0) -> 0 | V45: =IF(I45=1,INDEX('前提と出典'!D80:D83,'前提と出典'!$B$18+1)+G45*INDEX('前提と出典'!E80:E83,'前提と出典'!$B$18+1),0) -> 0 | W45: =L45-Q45 -> 0 | X45: =N45-R45 -> 0
A46: 2 | B46: 6 | C46: 1 | D46: ='前提と出典'!E58*(1-'前提と出典'!$B$21) -> 0.006 | E46: =ROUNDUP('前提と出典'!B58*'前提と出典'!$B$23,0) -> 300 | F46: ='前提と出典'!A58 -> 130 | G46: =MAX(1,ROUNDUP(E46*'前提と出典'!$B$25*'前提と出典'!E12,0)) -> 135 | H46: =IF(AND(F46>=1,F46<=100),1,0) -> 0 | I46: =IF(G46<=50,1,0) -> 0 | J46: =H46*I46 -> 0 | K46: =IF(A46='前提と出典'!$B$14,D46,0) -> 0 | L46: =IF(H46=0,0,IF(F46<=INDEX('前提と出典'!B41:B43,'前提と出典'!$B$15+1),INDEX('前提と出典'!C41:C43,'前提と出典'!$B$15+1),IF(F46<=INDEX('前提と出典'!D41:D43,'前提と出典'!$B$15+1),INDEX('前提と出典'!E41:E43,'前提と出典'!$B$15+1),INDEX('前提と出典'!G41:G43,'前提と出典'!$B$15+1)))) -> 0 | M46: =IF(H46=0,0,IF('前提と出典'!$B$33=1,MIN(F46,10)*300+MIN(MAX(0,F46-10),20)*250+MAX(0,F46-30)*200,F46*300)) -> 0 | N46: =IF(I46=0,0,IF(G46<=INDEX('前提と出典'!B46:B48,'前提と出典'!$B$16+1),INDEX('前提と出典'!C46:C48,'前提と出典'!$B$16+1),IF(G46<=INDEX('前提と出典'!D46:D48,'前提と出典'!$B$16+1),INDEX('前提と出典'!E46:E48,'前提と出典'!$B$16+1),IF(G46<=INDEX('前提と出典'!F46:F48,'前提と出典'!$B$16+1),INDEX('前提と出典'!G46:G48,'前提と出典'!$B$16+1),INDEX('前提と出典'!I46:I48,'前提と出典'!$B$16+1))))) -> 0 | O46: =IF(I46=1,G46*'前提と出典'!$B$13,0) -> 0 | P46: =IF(J46=1,MIN('前提と出典'!$B$17,L46+N46),0) -> 0 | Q46: =IF(J46=0,0,IF('前提と出典'!$B$19=0,P46*L46/(L46+N46),MIN(P46,L46))) -> 0 | R46: =P46-Q46 -> 0 | S46: =IF(H46=1,'前提と出典'!$B$11+F46*'前提と出典'!$B$12,0) -> 0 | T46: =IF(H46=1,('前提と出典'!$B$9+F46*'前提と出典'!$B$10)/60*'前提と出典'!$B$8,0) -> 0 | U46: =IF(I46=1,INDEX('前提と出典'!B80:B83,'前提と出典'!$B$18+1)+G46*INDEX('前提と出典'!C80:C83,'前提と出典'!$B$18+1),0) -> 0 | V46: =IF(I46=1,INDEX('前提と出典'!D80:D83,'前提と出典'!$B$18+1)+G46*INDEX('前提と出典'!E80:E83,'前提と出典'!$B$18+1),0) -> 0 | W46: =L46-Q46 -> 0 | X46: =N46-R46 -> 0

Sheet 契約別単価
A1: 契約形態別の加重平均（円/社月）
A2: Guard101台以上・Send51名以上は要見積で除外。価格対象率を分離し、0円契約にしない。
A4: 契約 | B4: 価格対象率 | C4: 平均PC | D4: 平均送信者 | E4: G基本net | F4: S基本net | G4: G従量 | H4: S従量 | I4: G変動infra | J4: S変動infra | K4: Gsupport | L4: Ssupport | M4: G割引 | N4: S割引 | O4: G売上 | P4: S売上 | Q4: 総売上
A5: Guardのみ | B5: =SUMPRODUCT('同一企業モデル'!K5:K46,'同一企業モデル'!H5:H46) -> 0.895 | C5: =SUMPRODUCT('同一企業モデル'!K5:K46,'同一企業モデル'!H5:H46,'同一企業モデル'!F5:F46)/B5 -> 10.27933 | D5: 0 | E5: =SUMPRODUCT('同一企業モデル'!K5:K46,'同一企業モデル'!H5:H46,'同一企業モデル'!L5:L46)/B5 -> 2910.6145 | F5: 0 | G5: =SUMPRODUCT('同一企業モデル'!K5:K46,'同一企業モデル'!H5:H46,'同一企業モデル'!M5:M46)/B5 -> 2843.5754 | H5: 0 | I5: =SUMPRODUCT('同一企業モデル'!K5:K46,'同一企業モデル'!H5:H46,'同一企業モデル'!S5:S46)/B5 -> 60.27933 | J5: 0 | K5: =SUMPRODUCT('同一企業モデル'!K5:K46,'同一企業モデル'!H5:H46,'同一企業モデル'!T5:T46)/B5 -> 601.8622 | L5: 0 | M5: 0 | N5: 0 | O5: =E5+G5 -> 5754.1899 | P5: =F5+H5 -> 0 | Q5: =O5+P5 -> 5754.1899
A6: Sendのみ | B6: =SUMPRODUCT('同一企業モデル'!K5:K46,'同一企業モデル'!I5:I46) -> 0.995 | C6: 0 | D6: =SUMPRODUCT('同一企業モデル'!K5:K46,'同一企業モデル'!I5:I46,'同一企業モデル'!G5:G46)/B6 -> 5.5050251 | E6: 0 | F6: =SUMPRODUCT('同一企業モデル'!K5:K46,'同一企業モデル'!I5:I46,'同一企業モデル'!N5:N46)/B6 -> 1337.1859 | G6: 0 | H6: =SUMPRODUCT('同一企業モデル'!K5:K46,'同一企業モデル'!I5:I46,'同一企業モデル'!O5:O46)/B6 -> 1101.005 | I6: 0 | J6: =SUMPRODUCT('同一企業モデル'!K5:K46,'同一企業モデル'!I5:I46,'同一企業モデル'!U5:U46)/B6 -> 158.83999 | K6: 0 | L6: =SUMPRODUCT('同一企業モデル'!K5:K46,'同一企業モデル'!I5:I46,'同一企業モデル'!V5:V46)/B6 -> 570.0335 | M6: 0 | N6: 0 | O6: =E6+G6 -> 0 | P6: =F6+H6 -> 2438.191 | Q6: =O6+P6 -> 2438.191
A7: セット | B7: =SUMPRODUCT('同一企業モデル'!K5:K46,'同一企業モデル'!J5:J46) -> 0.895 | C7: =SUMPRODUCT('同一企業モデル'!K5:K46,'同一企業モデル'!J5:J46,'同一企業モデル'!F5:F46)/B7 -> 10.27933 | D7: =SUMPRODUCT('同一企業モデル'!K5:K46,'同一企業モデル'!J5:J46,'同一企業モデル'!G5:G46)/B7 -> 6.0083799 | E7: =SUMPRODUCT('同一企業モデル'!K5:K46,'同一企業モデル'!J5:J46,'同一企業モデル'!W5:W46)/B7 -> 2568.9962 | F7: =SUMPRODUCT('同一企業モデル'!K5:K46,'同一企業モデル'!J5:J46,'同一企業モデル'!X5:X46)/B7 -> 1194.1323 | G7: =SUMPRODUCT('同一企業モデル'!K5:K46,'同一企業モデル'!J5:J46,'同一企業モデル'!M5:M46)/B7 -> 2843.5754 | H7: =SUMPRODUCT('同一企業モデル'!K5:K46,'同一企業モデル'!J5:J46,'同一企業モデル'!O5:O46)/B7 -> 1201.676 | I7: =SUMPRODUCT('同一企業モデル'!K5:K46,'同一企業モデル'!J5:J46,'同一企業モデル'!S5:S46)/B7 -> 60.27933 | J7: =SUMPRODUCT('同一企業モデル'!K5:K46,'同一企業モデル'!J5:J46,'同一企業モデル'!U5:U46)/B7 -> 168.79183 | K7: =SUMPRODUCT('同一企業モデル'!K5:K46,'同一企業モデル'!J5:J46,'同一企業モデル'!T5:T46)/B7 -> 601.8622 | L7: =SUMPRODUCT('同一企業モデル'!K5:K46,'同一企業モデル'!J5:J46,'同一企業モデル'!V5:V46)/B7 -> 573.3892 | M7: =SUMPRODUCT('同一企業モデル'!K5:K46,'同一企業モデル'!J5:J46,'同一企業モデル'!Q5:Q46)/B7 -> 341.61837 | N7: =SUMPRODUCT('同一企業モデル'!K5:K46,'同一企業モデル'!J5:J46,'同一企業モデル'!R5:R46)/B7 -> 158.38163 | O7: =E7+G7 -> 5412.5716 | P7: =F7+H7 -> 2395.8083 | Q7: =O7+P7 -> 7808.3799

Sheet 利益曲線
A1: 契約企業数別・サービス別収支
A2: 混在比率は期待値。NG/NSはサービス別契約数、DNS最低額はGuard全体に一回。
A4: 企業数 | B4: Guard社数 | C4: Send社数 | D4: 総PC | E4: G基本net | F4: S基本net | G4: G従量 | H4: S従量 | I4: G変動infra | J4: S変動infra | K4: Gsupport | L4: Ssupport | M4: G固定 | N4: S固定 | O4: DNS原価 | P4: G配分前 | Q4: S配分前 | R4: G・率1後 | S4: S・率1後 | T4: 合計・率1後 | U4: G・率2後 | V4: S・率2後 | W4: 合計・率2後 | X4: G・率3後 | Y4: S・率3後 | Z4: 合計・率3後 | AA4: 初黒・率1 | AB4: 最終赤・率1 | AC4: 両黒・率1 | AD4: 初黒・率2 | AE4: 最終赤・率2 | AF4: 両黒・率2 | AG4: 初黒・率3 | AH4: 最終赤・率3 | AI4: 両黒・率3
A5: 1 | B5: =A5*('前提と出典'!$C$36+'前提と出典'!$C$38) -> 0.7 | C5: =A5*('前提と出典'!$C$37+'前提と出典'!$C$38) -> 0.6 | D5: =A5*('前提と出典'!$C$36*'契約別単価'!C5+'前提と出典'!$C$37*'契約別単価'!C6+'前提と出典'!$C$38*'契約別単価'!C7) -> 7.1955307 | E5: =A5*('前提と出典'!$C$36*'契約別単価'!E5+'前提と出典'!$C$37*'契約別単価'!E6+'前提と出典'!$C$38*'契約別単価'!E7) -> 1934.9447 | F5: =A5*('前提と出典'!$C$36*'契約別単価'!F5+'前提と出典'!$C$37*'契約別単価'!F6+'前提と出典'!$C$38*'契約別単価'!F7) -> 759.39548 | G5: =A5*('前提と出典'!$C$36*'契約別単価'!G5+'前提と出典'!$C$37*'契約別単価'!G6+'前提と出典'!$C$38*'契約別単価'!G7) -> 1990.5028 | H5: =A5*('前提と出典'!$C$36*'契約別単価'!H5+'前提と出典'!$C$37*'契約別単価'!H6+'前提と出典'!$C$38*'契約別単価'!H7) -> 690.8043 | I5: =A5*('前提と出典'!$C$36*'契約別単価'!I5+'前提と出典'!$C$37*'契約別単価'!I6+'前提と出典'!$C$38*'契約別単価'!I7) -> 42.195531 | J5: =A5*('前提と出典'!$C$36*'契約別単価'!J5+'前提と出典'!$C$37*'契約別単価'!J6+'前提と出典'!$C$38*'契約別単価'!J7) -> 98.289544 | K5: =A5*('前提と出典'!$C$36*'契約別単価'!K5+'前提と出典'!$C$37*'契約別単価'!K6+'前提と出典'!$C$38*'契約別単価'!K7) -> 421.30354 | L5: =A5*('前提と出典'!$C$36*'契約別単価'!L5+'前提と出典'!$C$37*'契約別単価'!L6+'前提と出典'!$C$38*'契約別単価'!L7) -> 343.02681 | M5: =IF(('前提と出典'!$C$36+'前提と出典'!$C$38)=0,0,IF(B5<=10,'前提と出典'!B73+'前提と出典'!C73,IF(B5<=100,'前提と出典'!B74+'前提と出典'!C74,IF(B5<=500,'前提と出典'!B75+'前提と出典'!C75,'前提と出典'!B76+'前提と出典'!C76)))) -> 10000 | N5: =IF(('前提と出典'!$C$37+'前提と出典'!$C$38)=0,0,IF(C5<=10,'前提と出典'!D73+'前提と出典'!E73,IF(C5<=100,'前提と出典'!D74+'前提と出典'!E74,IF(C5<=500,'前提と出典'!D75+'前提と出典'!E75,'前提と出典'!D76+'前提と出典'!E76)))) -> 30010.935 | O5: =IF('前提と出典'!$C$36+'前提と出典'!$C$38=0,0,'前提と出典'!$B$4*IF('前提と出典'!$B$20=0,MAX('前提と出典'!$B$6,D5*'前提と出典'!$B$5),'前提と出典'!$B$6+D5*'前提と出典'!$B$5)) -> 22500 | P5: =(E5+G5)*(1-'前提と出典'!$B$7)-I5-K5-M5-O5 -> -29179.368 | Q5: =(F5+H5)*(1-'前提と出典'!$B$7)-J5-L5-N5 -> -29054.258 | R5: =P5-E5*'前提と出典'!$E$4 -> -29759.851 | S5: =Q5-F5*'前提と出典'!$E$4 -> -29282.077 | T5: =R5+S5 -> -59041.928 | U5: =P5-E5*'前提と出典'!$E$5 -> -29953.346 | V5: =Q5-F5*'前提と出典'!$E$5 -> -29358.017 | W5: =U5+V5 -> -59311.362 | X5: =P5-E5*'前提と出典'!$E$6 -> -30146.84 | Y5: =Q5-F5*'前提と出典'!$E$6 -> -29433.956 | Z5: =X5+Y5 -> -59580.796 | AA5: =IF(T5>=0,A5,1001) -> 1001 | AB5: =IF(T5<0,A5,0) -> 1 | AC5: =IF(AND(OR('前提と出典'!$C$36+'前提と出典'!$C$38=0,R5>=0),OR('前提と出典'!$C$37+'前提と出典'!$C$38=0,S5>=0)),0,A5) -> 1 | AD5: =IF(W5>=0,A5,1001) -> 1001 | AE5: =IF(W5<0,A5,0) -> 1 | AF5: =IF(AND(OR('前提と出典'!$C$36+'前提と出典'!$C$38=0,U5>=0),OR('前提と出典'!$C$37+'前提と出典'!$C$38=0,V5>=0)),0,A5) -> 1 | AG5: =IF(Z5>=0,A5,1001) -> 1001 | AH5: =IF(Z5<0,A5,0) -> 1 | AI5: =IF(AND(OR('前提と出典'!$C$36+'前提と出典'!$C$38=0,X5>=0),OR('前提と出典'!$C$37+'前提と出典'!$C$38=0,Y5>=0)),0,A5) -> 1
A6: 2 | B6: =A6*('前提と出典'!$C$36+'前提と出典'!$C$38) -> 1.4 | C6: =A6*('前提と出典'!$C$37+'前提と出典'!$C$38) -> 1.2 | D6: =A6*('前提と出典'!$C$36*'契約別単価'!C5+'前提と出典'!$C$37*'契約別単価'!C6+'前提と出典'!$C$38*'契約別単価'!C7) -> 14.391061 | E6: =A6*('前提と出典'!$C$36*'契約別単価'!E5+'前提と出典'!$C$37*'契約別単価'!E6+'前提と出典'!$C$38*'契約別単価'!E7) -> 3869.8893 | F6: =A6*('前提と出典'!$C$36*'契約別単価'!F5+'前提と出典'!$C$37*'契約別単価'!F6+'前提と出典'!$C$38*'契約別単価'!F7) -> 1518.791 | G6: =A6*('前提と出典'!$C$36*'契約別単価'!G5+'前提と出典'!$C$37*'契約別単価'!G6+'前提と出典'!$C$38*'契約別単価'!G7) -> 3981.0056 | H6: =A6*('前提と出典'!$C$36*'契約別単価'!H5+'前提と出典'!$C$37*'契約別単価'!H6+'前提と出典'!$C$38*'契約別単価'!H7) -> 1381.6086 | I6: =A6*('前提と出典'!$C$36*'契約別単価'!I5+'前提と出典'!$C$37*'契約別単価'!I6+'前提と出典'!$C$38*'契約別単価'!I7) -> 84.391061 | J6: =A6*('前提と出典'!$C$36*'契約別単価'!J5+'前提と出典'!$C$37*'契約別単価'!J6+'前提と出典'!$C$38*'契約別単価'!J7) -> 196.57909 | K6: =A6*('前提と出典'!$C$36*'契約別単価'!K5+'前提と出典'!$C$37*'契約別単価'!K6+'前提と出典'!$C$38*'契約別単価'!K7) -> 842.60708 | L6: =A6*('前提と出典'!$C$36*'契約別単価'!L5+'前提と出典'!$C$37*'契約別単価'!L6+'前提と出典'!$C$38*'契約別単価'!L7) -> 686.05362 | M6: =IF(('前提と出典'!$C$36+'前提と出典'!$C$38)=0,0,IF(B6<=10,'前提と出典'!B73+'前提と出典'!C73,IF(B6<=100,'前提と出典'!B74+'前提と出典'!C74,IF(B6<=500,'前提と出典'!B75+'前提と出典'!C75,'前提と出典'!B76+'前提と出典'!C76)))) -> 10000 | N6: =IF(('前提と出典'!$C$37+'前提と出典'!$C$38)=0,0,IF(C6<=10,'前提と出典'!D73+'前提と出典'!E73,IF(C6<=100,'前提と出典'!D74+'前提と出典'!E74,IF(C6<=500,'前提と出典'!D75+'前提と出典'!E75,'前提と出典'!D76+'前提と出典'!E76)))) -> 30010.935 | O6: =IF('前提と出典'!$C$36+'前提と出典'!$C$38=0,0,'前提と出典'!$B$4*IF('前提と出典'!$B$20=0,MAX('前提と出典'!$B$6,D6*'前提と出典'!$B$5),'前提と出典'!$B$6+D6*'前提と出典'!$B$5)) -> 22500 | P6: =(E6+G6)*(1-'前提と出典'!$B$7)-I6-K6-M6-O6 -> -25858.735 | Q6: =(F6+H6)*(1-'前提と出典'!$B$7)-J6-L6-N6 -> -28097.582 | R6: =P6-E6*'前提と出典'!$E$4 -> -27019.702 | S6: =Q6-F6*'前提と出典'!$E$4 -> -28553.219 | T6: =R6+S6 -> -55572.922 | U6: =P6-E6*'前提と出典'!$E$5 -> -27406.691 | V6: =Q6-F6*'前提と出典'!$E$5 -> -28705.099 | W6: =U6+V6 -> -56111.79 | X6: =P6-E6*'前提と出典'!$E$6 -> -27793.68 | Y6: =Q6-F6*'前提と出典'!$E$6 -> -28856.978 | Z6: =X6+Y6 -> -56650.658 | AA6: =IF(T6>=0,A6,1001) -> 1001 | AB6: =IF(T6<0,A6,0) -> 2 | AC6: =IF(AND(OR('前提と出典'!$C$36+'前提と出典'!$C$38=0,R6>=0),OR('前提と出典'!$C$37+'前提と出典'!$C$38=0,S6>=0)),0,A6) -> 2 | AD6: =IF(W6>=0,A6,1001) -> 1001 | AE6: =IF(W6<0,A6,0) -> 2 | AF6: =IF(AND(OR('前提と出典'!$C$36+'前提と出典'!$C$38=0,U6>=0),OR('前提と出典'!$C$37+'前提と出典'!$C$38=0,V6>=0)),0,A6) -> 2 | AG6: =IF(Z6>=0,A6,1001) -> 1001 | AH6: =IF(Z6<0,A6,0) -> 2 | AI6: =IF(AND(OR('前提と出典'!$C$36+'前提と出典'!$C$38=0,X6>=0),OR('前提と出典'!$C$37+'前提と出典'!$C$38=0,Y6>=0)),0,A6) -> 2
A7: 3 | B7: =A7*('前提と出典'!$C$36+'前提と出典'!$C$38) -> 2.1 | C7: =A7*('前提と出典'!$C$37+'前提と出典'!$C$38) -> 1.8 | D7: =A7*('前提と出典'!$C$36*'契約別単価'!C5+'前提と出典'!$C$37*'契約別単価'!C6+'前提と出典'!$C$38*'契約別単価'!C7) -> 21.586592 | E7: =A7*('前提と出典'!$C$36*'契約別単価'!E5+'前提と出典'!$C$37*'契約別単価'!E6+'前提と出典'!$C$38*'契約別単価'!E7) -> 5804.834 | F7: =A7*('前提と出典'!$C$36*'契約別単価'!F5+'前提と出典'!$C$37*'契約別単価'!F6+'前提と出典'!$C$38*'契約別単価'!F7) -> 2278.1864 | G7: =A7*('前提と出典'!$C$36*'契約別単価'!G5+'前提と出典'!$C$37*'契約別単価'!G6+'前提と出典'!$C$38*'契約別単価'!G7) -> 5971.5084 | H7: =A7*('前提と出典'!$C$36*'契約別単価'!H5+'前提と出典'!$C$37*'契約別単価'!H6+'前提と出典'!$C$38*'契約別単価'!H7) -> 2072.4129 | I7: =A7*('前提と出典'!$C$36*'契約別単価'!I5+'前提と出典'!$C$37*'契約別単価'!I6+'前提と出典'!$C$38*'契約別単価'!I7) -> 126.58659 | J7: =A7*('前提と出典'!$C$36*'契約別単価'!J5+'前提と出典'!$C$37*'契約別単価'!J6+'前提と出典'!$C$38*'契約別単価'!J7) -> 294.86863 | K7: =A7*('前提と出典'!$C$36*'契約別単価'!K5+'前提と出典'!$C$37*'契約別単価'!K6+'前提と出典'!$C$38*'契約別単価'!K7) -> 1263.9106 | L7: =A7*('前提と出典'!$C$36*'契約別単価'!L5+'前提と出典'!$C$37*'契約別単価'!L6+'前提と出典'!$C$38*'契約別単価'!L7) -> 1029.0804 | M7: =IF(('前提と出典'!$C$36+'前提と出典'!$C$38)=0,0,IF(B7<=10,'前提と出典'!B73+'前提と出典'!C73,IF(B7<=100,'前提と出典'!B74+'前提と出典'!C74,IF(B7<=500,'前提と出典'!B75+'前提と出典'!C75,'前提と出典'!B76+'前提と出典'!C76)))) -> 10000 | N7: =IF(('前提と出典'!$C$37+'前提と出典'!$C$38)=0,0,IF(C7<=10,'前提と出典'!D73+'前提と出典'!E73,IF(C7<=100,'前提と出典'!D74+'前提と出典'!E74,IF(C7<=500,'前提と出典'!D75+'前提と出典'!E75,'前提と出典'!D76+'前提と出典'!E76)))) -> 30010.935 | O7: =IF('前提と出典'!$C$36+'前提と出典'!$C$38=0,0,'前提と出典'!$B$4*IF('前提と出典'!$B$20=0,MAX('前提と出典'!$B$6,D7*'前提と出典'!$B$5),'前提と出典'!$B$6+D7*'前提と出典'!$B$5)) -> 22500 | P7: =(E7+G7)*(1-'前提と出典'!$B$7)-I7-K7-M7-O7 -> -22538.103 | Q7: =(F7+H7)*(1-'前提と出典'!$B$7)-J7-L7-N7 -> -27140.906 | R7: =P7-E7*'前提と出典'!$E$4 -> -24279.553 | S7: =Q7-F7*'前提と出典'!$E$4 -> -27824.362 | T7: =R7+S7 -> -52103.915 | U7: =P7-E7*'前提と出典'!$E$5 -> -24860.037 | V7: =Q7-F7*'前提と出典'!$E$5 -> -28052.18 | W7: =U7+V7 -> -52912.217 | X7: =P7-E7*'前提と出典'!$E$6 -> -25440.52 | Y7: =Q7-F7*'前提と出典'!$E$6 -> -28279.999 | Z7: =X7+Y7 -> -53720.519 | AA7: =IF(T7>=0,A7,1001) -> 1001 | AB7: =IF(T7<0,A7,0) -> 3 | AC7: =IF(AND(OR('前提と出典'!$C$36+'前提と出典'!$C$38=0,R7>=0),OR('前提と出典'!$C$37+'前提と出典'!$C$38=0,S7>=0)),0,A7) -> 3 | AD7: =IF(W7>=0,A7,1001) -> 1001 | AE7: =IF(W7<0,A7,0) -> 3 | AF7: =IF(AND(OR('前提と出典'!$C$36+'前提と出典'!$C$38=0,U7>=0),OR('前提と出典'!$C$37+'前提と出典'!$C$38=0,V7>=0)),0,A7) -> 3 | AG7: =IF(Z7>=0,A7,1001) -> 1001 | AH7: =IF(Z7<0,A7,0) -> 3 | AI7: =IF(AND(OR('前提と出典'!$C$36+'前提と出典'!$C$38=0,X7>=0),OR('前提と出典'!$C$37+'前提と出典'!$C$38=0,Y7>=0)),0,A7) -> 3
A8: 4 | B8: =A8*('前提と出典'!$C$36+'前提と出典'!$C$38) -> 2.8 | C8: =A8*('前提と出典'!$C$37+'前提と出典'!$C$38) -> 2.4 | D8: =A8*('前提と出典'!$C$36*'契約別単価'!C5+'前提と出典'!$C$37*'契約別単価'!C6+'前提と出典'!$C$38*'契約別単価'!C7) -> 28.782123 | E8: =A8*('前提と出典'!$C$36*'契約別単価'!E5+'前提と出典'!$C$37*'契約別単価'!E6+'前提と出典'!$C$38*'契約別単価'!E7) -> 7739.7786 | F8: =A8*('前提と出典'!$C$36*'契約別単価'!F5+'前提と出典'!$C$37*'契約別単価'!F6+'前提と出典'!$C$38*'契約別単価'!F7) -> 3037.5819 | G8: =A8*('前提と出典'!$C$36*'契約別単価'!G5+'前提と出典'!$C$37*'契約別単価'!G6+'前提と出典'!$C$38*'契約別単価'!G7) -> 7962.0112 | H8: =A8*('前提と出典'!$C$36*'契約別単価'!H5+'前提と出典'!$C$37*'契約別単価'!H6+'前提と出典'!$C$38*'契約別単価'!H7) -> 2763.2172 | I8: =A8*('前提と出典'!$C$36*'契約別単価'!I5+'前提と出典'!$C$37*'契約別単価'!I6+'前提と出典'!$C$38*'契約別単価'!I7) -> 168.78212 | J8: =A8*('前提と出典'!$C$36*'契約別単価'!J5+'前提と出典'!$C$37*'契約別単価'!J6+'前提と出典'!$C$38*'契約別単価'!J7) -> 393.15817 | K8: =A8*('前提と出典'!$C$36*'契約別単価'!K5+'前提と出典'!$C$37*'契約別単価'!K6+'前提と出典'!$C$38*'契約別単価'!K7) -> 1685.2142 | L8: =A8*('前提と出典'!$C$36*'契約別単価'!L5+'前提と出典'!$C$37*'契約別単価'!L6+'前提と出典'!$C$38*'契約別単価'!L7) -> 1372.1072 | M8: =IF(('前提と出典'!$C$36+'前提と出典'!$C$38)=0,0,IF(B8<=10,'前提と出典'!B73+'前提と出典'!C73,IF(B8<=100,'前提と出典'!B74+'前提と出典'!C74,IF(B8<=500,'前提と出典'!B75+'前提と出典'!C75,'前提と出典'!B76+'前提と出典'!C76)))) -> 10000 | N8: =IF(('前提と出典'!$C$37+'前提と出典'!$C$38)=0,0,IF(C8<=10,'前提と出典'!D73+'前提と出典'!E73,IF(C8<=100,'前提と出典'!D74+'前提と出典'!E74,IF(C8<=500,'前提と出典'!D75+'前提と出典'!E75,'前提と出典'!D76+'前提と出典'!E76)))) -> 30010.935 | O8: =IF('前提と出典'!$C$36+'前提と出典'!$C$38=0,0,'前提と出典'!$B$4*IF('前提と出典'!$B$20=0,MAX('前提と出典'!$B$6,D8*'前提と出典'!$B$5),'前提と出典'!$B$6+D8*'前提と出典'!$B$5)) -> 22500 | P8: =(E8+G8)*(1-'前提と出典'!$B$7)-I8-K8-M8-O8 -> -19217.471 | Q8: =(F8+H8)*(1-'前提と出典'!$B$7)-J8-L8-N8 -> -26184.23 | R8: =P8-E8*'前提と出典'!$E$4 -> -21539.404 | S8: =Q8-F8*'前提と出典'!$E$4 -> -27095.504 | T8: =R8+S8 -> -48634.909 | U8: =P8-E8*'前提と出典'!$E$5 -> -22313.382 | V8: =Q8-F8*'前提と出典'!$E$5 -> -27399.262 | W8: =U8+V8 -> -49712.645 | X8: =P8-E8*'前提と出典'!$E$6 -> -23087.36 | Y8: =Q8-F8*'前提と出典'!$E$6 -> -27703.021 | Z8: =X8+Y8 -> -50790.381 | AA8: =IF(T8>=0,A8,1001) -> 1001 | AB8: =IF(T8<0,A8,0) -> 4 | AC8: =IF(AND(OR('前提と出典'!$C$36+'前提と出典'!$C$38=0,R8>=0),OR('前提と出典'!$C$37+'前提と出典'!$C$38=0,S8>=0)),0,A8) -> 4 | AD8: =IF(W8>=0,A8,1001) -> 1001 | AE8: =IF(W8<0,A8,0) -> 4 | AF8: =IF(AND(OR('前提と出典'!$C$36+'前提と出典'!$C$38=0,U8>=0),OR('前提と出典'!$C$37+'前提と出典'!$C$38=0,V8>=0)),0,A8) -> 4 | AG8: =IF(Z8>=0,A8,1001) -> 1001 | AH8: =IF(Z8<0,A8,0) -> 4 | AI8: =IF(AND(OR('前提と出典'!$C$36+'前提と出典'!$C$38=0,X8>=0),OR('前提と出典'!$C$37+'前提と出典'!$C$38=0,Y8>=0)),0,A8) -> 4
A9: 5 | B9: =A9*('前提と出典'!$C$36+'前提と出典'!$C$38) -> 3.5 | C9: =A9*('前提と出典'!$C$37+'前提と出典'!$C$38) -> 3 | D9: =A9*('前提と出典'!$C$36*'契約別単価'!C5+'前提と出典'!$C$37*'契約別単価'!C6+'前提と出典'!$C$38*'契約別単価'!C7) -> 35.977654 | E9: =A9*('前提と出典'!$C$36*'契約別単価'!E5+'前提と出典'!$C$37*'契約別単価'!E6+'前提と出典'!$C$38*'契約別単価'!E7) -> 9674.7233 | F9: =A9*('前提と出典'!$C$36*'契約別単価'!F5+'前提と出典'!$C$37*'契約別単価'!F6+'前提と出典'!$C$38*'契約別単価'!F7) -> 3796.9774 | G9: =A9*('前提と出典'!$C$36*'契約別単価'!G5+'前提と出典'!$C$37*'契約別単価'!G6+'前提と出典'!$C$38*'契約別単価'!G7) -> 9952.514 | H9: =A9*('前提と出典'!$C$36*'契約別単価'!H5+'前提と出典'!$C$37*'契約別単価'!H6+'前提と出典'!$C$38*'契約別単価'!H7) -> 3454.0215 | I9: =A9*('前提と出典'!$C$36*'契約別単価'!I5+'前提と出典'!$C$37*'契約別単価'!I6+'前提と出典'!$C$38*'契約別単価'!I7) -> 210.97765 | J9: =A9*('前提と出典'!$C$36*'契約別単価'!J5+'前提と出典'!$C$37*'契約別単価'!J6+'前提と出典'!$C$38*'契約別単価'!J7) -> 491.44772 | K9: =A9*('前提と出典'!$C$36*'契約別単価'!K5+'前提と出典'!$C$37*'契約別単価'!K6+'前提と出典'!$C$38*'契約別単価'!K7) -> 2106.5177 | L9: =A9*('前提と出典'!$C$36*'契約別単価'!L5+'前提と出典'!$C$37*'契約別単価'!L6+'前提と出典'!$C$38*'契約別単価'!L7) -> 1715.1341 | M9: =IF(('前提と出典'!$C$36+'前提と出典'!$C$38)=0,0,IF(B9<=10,'前提と出典'!B73+'前提と出典'!C73,IF(B9<=100,'前提と出典'!B74+'前提と出典'!C74,IF(B9<=500,'前提と出典'!B75+'前提と出典'!C75,'前提と出典'!B76+'前提と出典'!C76)))) -> 10000 | N9: =IF(('前提と出典'!$C$37+'前提と出典'!$C$38)=0,0,IF(C9<=10,'前提と出典'!D73+'前提と出典'!E73,IF(C9<=100,'前提と出典'!D74+'前提と出典'!E74,IF(C9<=500,'前提と出典'!D75+'前提と出典'!E75,'前提と出典'!D76+'前提と出典'!E76)))) -> 30010.935 | O9: =IF('前提と出典'!$C$36+'前提と出典'!$C$38=0,0,'前提と出典'!$B$4*IF('前提と出典'!$B$20=0,MAX('前提と出典'!$B$6,D9*'前提と出典'!$B$5),'前提と出典'!$B$6+D9*'前提と出典'!$B$5)) -> 22500 | P9: =(E9+G9)*(1-'前提と出典'!$B$7)-I9-K9-M9-O9 -> -15896.839 | Q9: =(F9+H9)*(1-'前提と出典'!$B$7)-J9-L9-N9 -> -25227.553 | R9: =P9-E9*'前提と出典'!$E$4 -> -18799.256 | S9: =Q9-F9*'前提と出典'!$E$4 -> -26366.647 | T9: =R9+S9 -> -45165.902 | U9: =P9-E9*'前提と出典'!$E$5 -> -19766.728 | V9: =Q9-F9*'前提と出典'!$E$5 -> -26746.344 | W9: =U9+V9 -> -46513.072 | X9: =P9-E9*'前提と出典'!$E$6 -> -20734.2 | Y9: =Q9-F9*'前提と出典'!$E$6 -> -27126.042 | Z9: =X9+Y9 -> -47860.242 | AA9: =IF(T9>=0,A9,1001) -> 1001 | AB9: =IF(T9<0,A9,0) -> 5 | AC9: =IF(AND(OR('前提と出典'!$C$36+'前提と出典'!$C$38=0,R9>=0),OR('前提と出典'!$C$37+'前提と出典'!$C$38=0,S9>=0)),0,A9) -> 5 | AD9: =IF(W9>=0,A9,1001) -> 1001 | AE9: =IF(W9<0,A9,0) -> 5 | AF9: =IF(AND(OR('前提と出典'!$C$36+'前提と出典'!$C$38=0,U9>=0),OR('前提と出典'!$C$37+'前提と出典'!$C$38=0,V9>=0)),0,A9) -> 5 | AG9: =IF(Z9>=0,A9,1001) -> 1001 | AH9: =IF(Z9<0,A9,0) -> 5 | AI9: =IF(AND(OR('前提と出典'!$C$36+'前提と出典'!$C$38=0,X9>=0),OR('前提と出典'!$C$37+'前提と出典'!$C$38=0,Y9>=0)),0,A9) -> 5
A10: 6 | B10: =A10*('前提と出典'!$C$36+'前提と出典'!$C$38) -> 4.2 | C10: =A10*('前提と出典'!$C$37+'前提と出典'!$C$38) -> 3.6 | D10: =A10*('前提と出典'!$C$36*'契約別単価'!C5+'前提と出典'!$C$37*'契約別単価'!C6+'前提と出典'!$C$38*'契約別単価'!C7) -> 43.173184 | E10: =A10*('前提と出典'!$C$36*'契約別単価'!E5+'前提と出典'!$C$37*'契約別単価'!E6+'前提と出典'!$C$38*'契約別単価'!E7) -> 11609.668 | F10: =A10*('前提と出典'!$C$36*'契約別単価'!F5+'前提と出典'!$C$37*'契約別単価'!F6+'前提と出典'!$C$38*'契約別単価'!F7) -> 4556.3729 | G10: =A10*('前提と出典'!$C$36*'契約別単価'!G5+'前提と出典'!$C$37*'契約別単価'!G6+'前提と出典'!$C$38*'契約別単価'!G7) -> 11943.017 | H10: =A10*('前提と出典'!$C$36*'契約別単価'!H5+'前提と出典'!$C$37*'契約別単価'!H6+'前提と出典'!$C$38*'契約別単価'!H7) -> 4144.8258 | I10: =A10*('前提と出典'!$C$36*'契約別単価'!I5+'前提と出典'!$C$37*'契約別単価'!I6+'前提と出典'!$C$38*'契約別単価'!I7) -> 253.17318 | J10: =A10*('前提と出典'!$C$36*'契約別単価'!J5+'前提と出典'!$C$37*'契約別単価'!J6+'前提と出典'!$C$38*'契約別単価'!J7) -> 589.73726 | K10: =A10*('前提と出典'!$C$36*'契約別単価'!K5+'前提と出典'!$C$37*'契約別単価'!K6+'前提と出典'!$C$38*'契約別単価'!K7) -> 2527.8212 | L10: =A10*('前提と出典'!$C$36*'契約別単価'!L5+'前提と出典'!$C$37*'契約別単価'!L6+'前提と出典'!$C$38*'契約別単価'!L7) -> 2058.1609 | M10: =IF(('前提と出典'!$C$36+'前提と出典'!$C$38)=0,0,IF(B10<=10,'前提と出典'!B73+'前提と出典'!C73,IF(B10<=100,'前提と出典'!B74+'前提と出典'!C74,IF(B10<=500,'前提と出典'!B75+'前提と出典'!C75,'前提と出典'!B76+'前提と出典'!C76)))) -> 10000 | N10: =IF(('前提と出典'!$C$37+'前提と出典'!$C$38)=0,0,IF(C10<=10,'前提と出典'!D73+'前提と出典'!E73,IF(C10<=100,'前提と出典'!D74+'前提と出典'!E74,IF(C10<=500,'前提と出典'!D75+'前提と出典'!E75,'前提と出典'!D76+'前提と出典'!E76)))) -> 30010.935 | O10: =IF('前提と出典'!$C$36+'前提と出典'!$C$38=0,0,'前提と出典'!$B$4*IF('前提と出典'!$B$20=0,MAX('前提と出典'!$B$6,D10*'前提と出典'!$B$5),'前提と出典'!$B$6+D10*'前提と出典'!$B$5)) -> 22500 | P10: =(E10+G10)*(1-'前提と出典'!$B$7)-I10-K10-M10-O10 -> -12576.206 | Q10: =(F10+H10)*(1-'前提と出典'!$B$7)-J10-L10-N10 -> -24270.877 | R10: =P10-E10*'前提と出典'!$E$4 -> -16059.107 | S10: =Q10-F10*'前提と出典'!$E$4 -> -25637.789 | T10: =R10+S10 -> -41696.896 | U10: =P10-E10*'前提と出典'!$E$5 -> -17220.074 | V10: =Q10-F10*'前提と出典'!$E$5 -> -26093.426 | W10: =U10+V10 -> -43313.5 | X10: =P10-E10*'前提と出典'!$E$6 -> -18381.04 | Y10: =Q10-F10*'前提と出典'!$E$6 -> -26549.064 | Z10: =X10+Y10 -> -44930.104 | AA10: =IF(T10>=0,A10,1001) -> 1001 | AB10: =IF(T10<0,A10,0) -> 6 | AC10: =IF(AND(OR('前提と出典'!$C$36+'前提と出典'!$C$38=0,R10>=0),OR('前提と出典'!$C$37+'前提と出典'!$C$38=0,S10>=0)),0,A10) -> 6 | AD10: =IF(W10>=0,A10,1001) -> 1001 | AE10: =IF(W10<0,A10,0) -> 6 | AF10: =IF(AND(OR('前提と出典'!$C$36+'前提と出典'!$C$38=0,U10>=0),OR('前提と出典'!$C$37+'前提と出典'!$C$38=0,V10>=0)),0,A10) -> 6 | AG10: =IF(Z10>=0,A10,1001) -> 1001 | AH10: =IF(Z10<0,A10,0) -> 6 | AI10: =IF(AND(OR('前提と出典'!$C$36+'前提と出典'!$C$38=0,X10>=0),OR('前提と出典'!$C$37+'前提と出典'!$C$38=0,Y10>=0)),0,A10) -> 6
A11: 7 | B11: =A11*('前提と出典'!$C$36+'前提と出典'!$C$38) -> 4.9 | C11: =A11*('前提と出典'!$C$37+'前提と出典'!$C$38) -> 4.2 | D11: =A11*('前提と出典'!$C$36*'契約別単価'!C5+'前提と出典'!$C$37*'契約別単価'!C6+'前提と出典'!$C$38*'契約別単価'!C7) -> 50.368715 | E11: =A11*('前提と出典'!$C$36*'契約別単価'!E5+'前提と出典'!$C$37*'契約別単価'!E6+'前提と出典'!$C$38*'契約別単価'!E7) -> 13544.613 | F11: =A11*('前提と出典'!$C$36*'契約別単価'!F5+'前提と出典'!$C$37*'契約別単価'!F6+'前提と出典'!$C$38*'契約別単価'!F7) -> 5315.7684 | G11: =A11*('前提と出典'!$C$36*'契約別単価'!G5+'前提と出典'!$C$37*'契約別単価'!G6+'前提と出典'!$C$38*'契約別単価'!G7) -> 13933.52 | H11: =A11*('前提と出典'!$C$36*'契約別単価'!H5+'前提と出典'!$C$37*'契約別単価'!H6+'前提と出典'!$C$38*'契約別単価'!H7) -> 4835.6301 | I11: =A11*('前提と出典'!$C$36*'契約別単価'!I5+'前提と出典'!$C$37*'契約別単価'!I6+'前提と出典'!$C$38*'契約別単価'!I7) -> 295.36872 | J11: =A11*('前提と出典'!$C$36*'契約別単価'!J5+'前提と出典'!$C$37*'契約別単価'!J6+'前提と出典'!$C$38*'契約別単価'!J7) -> 688.02681 | K11: =A11*('前提と出典'!$C$36*'契約別単価'!K5+'前提と出典'!$C$37*'契約別単価'!K6+'前提と出典'!$C$38*'契約別単価'!K7) -> 2949.1248 | L11: =A11*('前提と出典'!$C$36*'契約別単価'!L5+'前提と出典'!$C$37*'契約別単価'!L6+'前提と出典'!$C$38*'契約別単価'!L7) -> 2401.1877 | M11: =IF(('前提と出典'!$C$36+'前提と出典'!$C$38)=0,0,IF(B11<=10,'前提と出典'!B73+'前提と出典'!C73,IF(B11<=100,'前提と出典'!B74+'前提と出典'!C74,IF(B11<=500,'前提と出典'!B75+'前提と出典'!C75,'前提と出典'!B76+'前提と出典'!C76)))) -> 10000 | N11: =IF(('前提と出典'!$C$37+'前提と出典'!$C$38)=0,0,IF(C11<=10,'前提と出典'!D73+'前提と出典'!E73,IF(C11<=100,'前提と出典'!D74+'前提と出典'!E74,IF(C11<=500,'前提と出典'!D75+'前提と出典'!E75,'前提と出典'!D76+'前提と出典'!E76)))) -> 30010.935 | O11: =IF('前提と出典'!$C$36+'前提と出典'!$C$38=0,0,'前提と出典'!$B$4*IF('前提と出典'!$B$20=0,MAX('前提と出典'!$B$6,D11*'前提と出典'!$B$5),'前提と出典'!$B$6+D11*'前提と出典'!$B$5)) -> 22500 | P11: =(E11+G11)*(1-'前提と出典'!$B$7)-I11-K11-M11-O11 -> -9255.5741 | Q11: =(F11+H11)*(1-'前提と出典'!$B$7)-J11-L11-N11 -> -23314.201 | R11: =P11-E11*'前提と出典'!$E$4 -> -13318.958 | S11: =Q11-F11*'前提と出典'!$E$4 -> -24908.931 | T11: =R11+S11 -> -38227.889 | U11: =P11-E11*'前提と出典'!$E$5 -> -14673.419 | V11: =Q11-F11*'前提と出典'!$E$5 -> -25440.508 | W11: =U11+V11 -> -40113.927 | X11: =P11-E11*'前提と出典'!$E$6 -> -16027.88 | Y11: =Q11-F11*'前提と出典'!$E$6 -> -25972.085 | Z11: =X11+Y11 -> -41999.966 | AA11: =IF(T11>=0,A11,1001) -> 1001 | AB11: =IF(T11<0,A11,0) -> 7 | AC11: =IF(AND(OR('前提と出典'!$C$36+'前提と出典'!$C$38=0,R11>=0),OR('前提と出典'!$C$37+'前提と出典'!$C$38=0,S11>=0)),0,A11) -> 7 | AD11: =IF(W11>=0,A11,1001) -> 1001 | AE11: =IF(W11<0,A11,0) -> 7 | AF11: =IF(AND(OR('前提と出典'!$C$36+'前提と出典'!$C$38=0,U11>=0),OR('前提と出典'!$C$37+'前提と出典'!$C$38=0,V11>=0)),0,A11) -> 7 | AG11: =IF(Z11>=0,A11,1001) -> 1001 | AH11: =IF(Z11<0,A11,0) -> 7 | AI11: =IF(AND(OR('前提と出典'!$C$36+'前提と出典'!$C$38=0,X11>=0),OR('前提と出典'!$C$37+'前提と出典'!$C$38=0,Y11>=0)),0,A11) -> 7
A12: 8 | B12: =A12*('前提と出典'!$C$36+'前提と出典'!$C$38) -> 5.6 | C12: =A12*('前提と出典'!$C$37+'前提と出典'!$C$38) -> 4.8 | D12: =A12*('前提と出典'!$C$36*'契約別単価'!C5+'前提と出典'!$C$37*'契約別単価'!C6+'前提と出典'!$C$38*'契約別単価'!C7) -> 57.564246 | E12: =A12*('前提と出典'!$C$36*'契約別単価'!E5+'前提と出典'!$C$37*'契約別単価'!E6+'前提と出典'!$C$38*'契約別単価'!E7) -> 15479.557 | F12: =A12*('前提と出典'!$C$36*'契約別単価'!F5+'前提と出典'!$C$37*'契約別単価'!F6+'前提と出典'!$C$38*'契約別単価'!F7) -> 6075.1638 | G12: =A12*('前提と出典'!$C$36*'契約別単価'!G5+'前提と出典'!$C$37*'契約別単価'!G6+'前提と出典'!$C$38*'契約別単価'!G7) -> 15924.022 | H12: =A12*('前提と出典'!$C$36*'契約別単価'!H5+'前提と出典'!$C$37*'契約別単価'!H6+'前提と出典'!$C$38*'契約別単価'!H7) -> 5526.4344 | I12: =A12*('前提と出典'!$C$36*'契約別単価'!I5+'前提と出典'!$C$37*'契約別単価'!I6+'前提と出典'!$C$38*'契約別単価'!I7) -> 337.56425 | J12: =A12*('前提と出典'!$C$36*'契約別単価'!J5+'前提と出典'!$C$37*'契約別単価'!J6+'前提と出典'!$C$38*'契約別単価'!J7) -> 786.31635 | K12: =A12*('前提と出典'!$C$36*'契約別単価'!K5+'前提と出典'!$C$37*'契約別単価'!K6+'前提と出典'!$C$38*'契約別単価'!K7) -> 3370.4283 | L12: =A12*('前提と出典'!$C$36*'契約別単価'!L5+'前提と出典'!$C$37*'契約別単価'!L6+'前提と出典'!$C$38*'契約別単価'!L7) -> 2744.2145 | M12: =IF(('前提と出典'!$C$36+'前提と出典'!$C$38)=0,0,IF(B12<=10,'前提と出典'!B73+'前提と出典'!C73,IF(B12<=100,'前提と出典'!B74+'前提と出典'!C74,IF(B12<=500,'前提と出典'!B75+'前提と出典'!C75,'前提と出典'!B76+'前提と出典'!C76)))) -> 10000 | N12: =IF(('前提と出典'!$C$37+'前提と出典'!$C$38)=0,0,IF(C12<=10,'前提と出典'!D73+'前提と出典'!E73,IF(C12<=100,'前提と出典'!D74+'前提と出典'!E74,IF(C12<=500,'前提と出典'!D75+'前提と出典'!E75,'前提と出典'!D76+'前提と出典'!E76)))) -> 30010.935 | O12: =IF('前提と出典'!$C$36+'前提と出典'!$C$38=0,0,'前提と出典'!$B$4*IF('前提と出典'!$B$20=0,MAX('前提と出典'!$B$6,D12*'前提と出典'!$B$5),'前提と出典'!$B$6+D12*'前提と出典'!$B$5)) -> 22500 | P12: =(E12+G12)*(1-'前提と出典'!$B$7)-I12-K12-M12-O12 -> -5934.9418 | Q12: =(F12+H12)*(1-'前提と出典'!$B$7)-J12-L12-N12 -> -22357.525 | R12: =P12-E12*'前提と出典'!$E$4 -> -10578.809 | S12: =Q12-F12*'前提と出典'!$E$4 -> -24180.074 | T12: =R12+S12 -> -34758.883 | U12: =P12-E12*'前提と出典'!$E$5 -> -12126.765 | V12: =Q12-F12*'前提と出典'!$E$5 -> -24787.59 | W12: =U12+V12 -> -36914.355 | X12: =P12-E12*'前提と出典'!$E$6 -> -13674.72 | Y12: =Q12-F12*'前提と出典'!$E$6 -> -25395.107 | Z12: =X12+Y12 -> -39069.827 | AA12: =IF(T12>=0,A12,1001) -> 1001 | AB12: =IF(T12<0,A12,0) -> 8 | AC12: =IF(AND(OR('前提と出典'!$C$36+'前提と出典'!$C$38=0,R12>=0),OR('前提と出典'!$C$37+'前提と出典'!$C$38=0,S12>=0)),0,A12) -> 8 | AD12: =IF(W12>=0,A12,1001) -> 1001 | AE12: =IF(W12<0,A12,0) -> 8 | AF12: =IF(AND(OR('前提と出典'!$C$36+'前提と出典'!$C$38=0,U12>=0),OR('前提と出典'!$C$37+'前提と出典'!$C$38=0,V12>=0)),0,A12) -> 8 | AG12: =IF(Z12>=0,A12,1001) -> 1001 | AH12: =IF(Z12<0,A12,0) -> 8 | AI12: =IF(AND(OR('前提と出典'!$C$36+'前提と出典'!$C$38=0,X12>=0),OR('前提と出典'!$C$37+'前提と出典'!$C$38=0,Y12>=0)),0,A12) -> 8
A13: 9 | B13: =A13*('前提と出典'!$C$36+'前提と出典'!$C$38) -> 6.3 | C13: =A13*('前提と出典'!$C$37+'前提と出典'!$C$38) -> 5.4 | D13: =A13*('前提と出典'!$C$36*'契約別単価'!C5+'前提と出典'!$C$37*'契約別単価'!C6+'前提と出典'!$C$38*'契約別単価'!C7) -> 64.759777 | E13: =A13*('前提と出典'!$C$36*'契約別単価'!E5+'前提と出典'!$C$37*'契約別単価'!E6+'前提と出典'!$C$38*'契約別単価'!E7) -> 17414.502 | F13: =A13*('前提と出典'!$C$36*'契約別単価'!F5+'前提と出典'!$C$37*'契約別単価'!F6+'前提と出典'!$C$38*'契約別単価'!F7) -> 6834.5593 | G13: =A13*('前提と出典'!$C$36*'契約別単価'!G5+'前提と出典'!$C$37*'契約別単価'!G6+'前提と出典'!$C$38*'契約別単価'!G7) -> 17914.525 | H13: =A13*('前提と出典'!$C$36*'契約別単価'!H5+'前提と出典'!$C$37*'契約別単価'!H6+'前提と出典'!$C$38*'契約別単価'!H7) -> 6217.2387 | I13: =A13*('前提と出典'!$C$36*'契約別単価'!I5+'前提と出典'!$C$37*'契約別単価'!I6+'前提と出典'!$C$38*'契約別単価'!I7) -> 379.75978 | J13: =A13*('前提と出典'!$C$36*'契約別単価'!J5+'前提と出典'!$C$37*'契約別単価'!J6+'前提と出典'!$C$38*'契約別単価'!J7) -> 884.60589 | K13: =A13*('前提と出典'!$C$36*'契約別単価'!K5+'前提と出典'!$C$37*'契約別単価'!K6+'前提と出典'!$C$38*'契約別単価'!K7) -> 3791.7318 | L13: =A13*('前提と出典'!$C$36*'契約別単価'!L5+'前提と出典'!$C$37*'契約別単価'!L6+'前提と出典'!$C$38*'契約別単価'!L7) -> 3087.2413 | M13: =IF(('前提と出典'!$C$36+'前提と出典'!$C$38)=0,0,IF(B13<=10,'前提と出典'!B73+'前提と出典'!C73,IF(B13<=100,'前提と出典'!B74+'前提と出典'!C74,IF(B13<=500,'前提と出典'!B75+'前提と出典'!C75,'前提と出典'!B76+'前提と出典'!C76)))) -> 10000 | N13: =IF(('前提と出典'!$C$37+'前提と出典'!$C$38)=0,0,IF(C13<=10,'前提と出典'!D73+'前提と出典'!E73,IF(C13<=100,'前提と出典'!D74+'前提と出典'!E74,IF(C13<=500,'前提と出典'!D75+'前提と出典'!E75,'前提と出典'!D76+'前提と出典'!E76)))) -> 30010.935 | O13: =IF('前提と出典'!$C$36+'前提と出典'!$C$38=0,0,'前提と出典'!$B$4*IF('前提と出典'!$B$20=0,MAX('前提と出典'!$B$6,D13*'前提と出典'!$B$5),'前提と出典'!$B$6+D13*'前提と出典'!$B$5)) -> 22500 | P13: =(E13+G13)*(1-'前提と出典'!$B$7)-I13-K13-M13-O13 -> -2614.3095 | Q13: =(F13+H13)*(1-'前提と出典'!$B$7)-J13-L13-N13 -> -21400.849 | R13: =P13-E13*'前提と出典'!$E$4 -> -7838.6601 | S13: =Q13-F13*'前提と出典'!$E$4 -> -23451.216 | T13: =R13+S13 -> -31289.876 | U13: =P13-E13*'前提と出典'!$E$5 -> -9580.1103 | V13: =Q13-F13*'前提と出典'!$E$5 -> -24134.672 | W13: =U13+V13 -> -33714.783 | X13: =P13-E13*'前提と出典'!$E$6 -> -11321.56 | Y13: =Q13-F13*'前提と出典'!$E$6 -> -24818.128 | Z13: =X13+Y13 -> -36139.689 | AA13: =IF(T13>=0,A13,1001) -> 1001 | AB13: =IF(T13<0,A13,0) -> 9 | AC13: =IF(AND(OR('前提と出典'!$C$36+'前提と出典'!$C$38=0,R13>=0),OR('前提と出典'!$C$37+'前提と出典'!$C$38=0,S13>=0)),0,A13) -> 9 | AD13: =IF(W13>=0,A13,1001) -> 1001 | AE13: =IF(W13<0,A13,0) -> 9 | AF13: =IF(AND(OR('前提と出典'!$C$36+'前提と出典'!$C$38=0,U13>=0),OR('前提と出典'!$C$37+'前提と出典'!$C$38=0,V13>=0)),0,A13) -> 9 | AG13: =IF(Z13>=0,A13,1001) -> 1001 | AH13: =IF(Z13<0,A13,0) -> 9 | AI13: =IF(AND(OR('前提と出典'!$C$36+'前提と出典'!$C$38=0,X13>=0),OR('前提と出典'!$C$37+'前提と出典'!$C$38=0,Y13>=0)),0,A13) -> 9
A14: 10 | B14: =A14*('前提と出典'!$C$36+'前提と出典'!$C$38) -> 7 | C14: =A14*('前提と出典'!$C$37+'前提と出典'!$C$38) -> 6 | D14: =A14*('前提と出典'!$C$36*'契約別単価'!C5+'前提と出典'!$C$37*'契約別単価'!C6+'前提と出典'!$C$38*'契約別単価'!C7) -> 71.955307 | E14: =A14*('前提と出典'!$C$36*'契約別単価'!E5+'前提と出典'!$C$37*'契約別単価'!E6+'前提と出典'!$C$38*'契約別単価'!E7) -> 19349.447 | F14: =A14*('前提と出典'!$C$36*'契約別単価'!F5+'前提と出典'!$C$37*'契約別単価'!F6+'前提と出典'!$C$38*'契約別単価'!F7) -> 7593.9548 | G14: =A14*('前提と出典'!$C$36*'契約別単価'!G5+'前提と出典'!$C$37*'契約別単価'!G6+'前提と出典'!$C$38*'契約別単価'!G7) -> 19905.028 | H14: =A14*('前提と出典'!$C$36*'契約別単価'!H5+'前提と出典'!$C$37*'契約別単価'!H6+'前提と出典'!$C$38*'契約別単価'!H7) -> 6908.043 | I14: =A14*('前提と出典'!$C$36*'契約別単価'!I5+'前提と出典'!$C$37*'契約別単価'!I6+'前提と出典'!$C$38*'契約別単価'!I7) -> 421.95531 | J14: =A14*('前提と出典'!$C$36*'契約別単価'!J5+'前提と出典'!$C$37*'契約別単価'!J6+'前提と出典'!$C$38*'契約別単価'!J7) -> 982.89544 | K14: =A14*('前提と出典'!$C$36*'契約別単価'!K5+'前提と出典'!$C$37*'契約別単価'!K6+'前提と出典'!$C$38*'契約別単価'!K7) -> 4213.0354 | L14: =A14*('前提と出典'!$C$36*'契約別単価'!L5+'前提と出典'!$C$37*'契約別単価'!L6+'前提と出典'!$C$38*'契約別単価'!L7) -> 3430.2681 | M14: =IF(('前提と出典'!$C$36+'前提と出典'!$C$38)=0,0,IF(B14<=10,'前提と出典'!B73+'前提と出典'!C73,IF(B14<=100,'前提と出典'!B74+'前提と出典'!C74,IF(B14<=500,'前提と出典'!B75+'前提と出典'!C75,'前提と出典'!B76+'前提と出典'!C76)))) -> 10000 | N14: =IF(('前提と出典'!$C$37+'前提と出典'!$C$38)=0,0,IF(C14<=10,'前提と出典'!D73+'前提と出典'!E73,IF(C14<=100,'前提と出典'!D74+'前提と出典'!E74,IF(C14<=500,'前提と出典'!D75+'前提と出典'!E75,'前提と出典'!D76+'前提と出典'!E76)))) -> 30010.935 | O14: =IF('前提と出典'!$C$36+'前提と出典'!$C$38=0,0,'前提と出典'!$B$4*IF('前提と出典'!$B$20=0,MAX('前提と出典'!$B$6,D14*'前提と出典'!$B$5),'前提と出典'!$B$6+D14*'前提と出典'!$B$5)) -> 22500 | P14: =(E14+G14)*(1-'前提と出典'!$B$7)-I14-K14-M14-O14 -> 706.32273 | Q14: =(F14+H14)*(1-'前提と出典'!$B$7)-J14-L14-N14 -> -20444.172 | R14: =P14-E14*'前提と出典'!$E$4 -> -5098.5112 | S14: =Q14-F14*'前提と出典'!$E$4 -> -22722.359 | T14: =R14+S14 -> -27820.87 | U14: =P14-E14*'前提と出典'!$E$5 -> -7033.4559 | V14: =Q14-F14*'前提と出典'!$E$5 -> -23481.754 | W14: =U14+V14 -> -30515.21 | X14: =P14-E14*'前提と出典'!$E$6 -> -8968.4006 | Y14: =Q14-F14*'前提と出典'!$E$6 -> -24241.15 | Z14: =X14+Y14 -> -33209.55 | AA14: =IF(T14>=0,A14,1001) -> 1001 | AB14: =IF(T14<0,A14,0) -> 10 | AC14: =IF(AND(OR('前提と出典'!$C$36+'前提と出典'!$C$38=0,R14>=0),OR('前提と出典'!$C$37+'前提と出典'!$C$38=0,S14>=0)),0,A14) -> 10 | AD14: =IF(W14>=0,A14,1001) -> 1001 | AE14: =IF(W14<0,A14,0) -> 10 | AF14: =IF(AND(OR('前提と出典'!$C$36+'前提と出典'!$C$38=0,U14>=0),OR('前提と出典'!$C$37+'前提と出典'!$C$38=0,V14>=0)),0,A14) -> 10 | AG14: =IF(Z14>=0,A14,1001) -> 1001 | AH14: =IF(Z14<0,A14,0) -> 10 | AI14: =IF(AND(OR('前提と出典'!$C$36+'前提と出典'!$C$38=0,X14>=0),OR('前提と出典'!$C$37+'前提と出典'!$C$38=0,Y14>=0)),0,A14) -> 10
A15: 11 | B15: =A15*('前提と出典'!$C$36+'前提と出典'!$C$38) -> 7.7 | C15: =A15*('前提と出典'!$C$37+'前提と出典'!$C$38) -> 6.6 | D15: =A15*('前提と出典'!$C$36*'契約別単価'!C5+'前提と出典'!$C$37*'契約別単価'!C6+'前提と出典'!$C$38*'契約別単価'!C7) -> 79.150838 | E15: =A15*('前提と出典'!$C$36*'契約別単価'!E5+'前提と出典'!$C$37*'契約別単価'!E6+'前提と出典'!$C$38*'契約別単価'!E7) -> 21284.391 | F15: =A15*('前提と出典'!$C$36*'契約別単価'!F5+'前提と出典'!$C$37*'契約別単価'!F6+'前提と出典'!$C$38*'契約別単価'!F7) -> 8353.3503 | G15: =A15*('前提と出典'!$C$36*'契約別単価'!G5+'前提と出典'!$C$37*'契約別単価'!G6+'前提と出典'!$C$38*'契約別単価'!G7) -> 21895.531 | H15: =A15*('前提と出典'!$C$36*'契約別単価'!H5+'前提と出典'!$C$37*'契約別単価'!H6+'前提と出典'!$C$38*'契約別単価'!H7) -> 7598.8473 | I15: =A15*('前提と出典'!$C$36*'契約別単価'!I5+'前提と出典'!$C$37*'契約別単価'!I6+'前提と出典'!$C$38*'契約別単価'!I7) -> 464.15084 | J15: =A15*('前提と出典'!$C$36*'契約別単価'!J5+'前提と出典'!$C$37*'契約別単価'!J6+'前提と出典'!$C$38*'契約別単価'!J7) -> 1081.185 | K15: =A15*('前提と出典'!$C$36*'契約別単価'!K5+'前提と出典'!$C$37*'契約別単価'!K6+'前提と出典'!$C$38*'契約別単価'!K7) -> 4634.3389 | L15: =A15*('前提と出典'!$C$36*'契約別単価'!L5+'前提と出典'!$C$37*'契約別単価'!L6+'前提と出典'!$C$38*'契約別単価'!L7) -> 3773.2949 | M15: =IF(('前提と出典'!$C$36+'前提と出典'!$C$38)=0,0,IF(B15<=10,'前提と出典'!B73+'前提と出典'!C73,IF(B15<=100,'前提と出典'!B74+'前提と出典'!C74,IF(B15<=500,'前提と出典'!B75+'前提と出典'!C75,'前提と出典'!B76+'前提と出典'!C76)))) -> 10000 | N15: =IF(('前提と出典'!$C$37+'前提と出典'!$C$38)=0,0,IF(C15<=10,'前提と出典'!D73+'前提と出典'!E73,IF(C15<=100,'前提と出典'!D74+'前提と出典'!E74,IF(C15<=500,'前提と出典'!D75+'前提と出典'!E75,'前提と出典'!D76+'前提と出典'!E76)))) -> 30010.935 | O15: =IF('前提と出典'!$C$36+'前提と出典'!$C$38=0,0,'前提と出典'!$B$4*IF('前提と出典'!$B$20=0,MAX('前提と出典'!$B$6,D15*'前提と出典'!$B$5),'前提と出典'!$B$6+D15*'前提と出典'!$B$5)) -> 22500 | P15: =(E15+G15)*(1-'前提と出典'!$B$7)-I15-K15-M15-O15 -> 4026.955 | Q15: =(F15+H15)*(1-'前提と出典'!$B$7)-J15-L15-N15 -> -19487.496 | R15: =P15-E15*'前提と出典'!$E$4 -> -2358.3624 | S15: =Q15-F15*'前提と出典'!$E$4 -> -21993.501 | T15: =R15+S15 -> -24351.863 | U15: =P15-E15*'前提と出典'!$E$5 -> -4486.8015 | V15: =Q15-F15*'前提と出典'!$E$5 -> -22828.836 | W15: =U15+V15 -> -27315.638 | X15: =P15-E15*'前提と出典'!$E$6 -> -6615.2406 | Y15: =Q15-F15*'前提と出典'!$E$6 -> -23664.171 | Z15: =X15+Y15 -> -30279.412 | AA15: =IF(T15>=0,A15,1001) -> 1001 | AB15: =IF(T15<0,A15,0) -> 11 | AC15: =IF(AND(OR('前提と出典'!$C$36+'前提と出典'!$C$38=0,R15>=0),OR('前提と出典'!$C$37+'前提と出典'!$C$38=0,S15>=0)),0,A15) -> 11 | AD15: =IF(W15>=0,A15,1001) -> 1001 | AE15: =IF(W15<0,A15,0) -> 11 | AF15: =IF(AND(OR('前提と出典'!$C$36+'前提と出典'!$C$38=0,U15>=0),OR('前提と出典'!$C$37+'前提と出典'!$C$38=0,V15>=0)),0,A15) -> 11 | AG15: =IF(Z15>=0,A15,1001) -> 1001 | AH15: =IF(Z15<0,A15,0) -> 11 | AI15: =IF(AND(OR('前提と出典'!$C$36+'前提と出典'!$C$38=0,X15>=0),OR('前提と出典'!$C$37+'前提と出典'!$C$38=0,Y15>=0)),0,A15) -> 11
A16: 12 | B16: =A16*('前提と出典'!$C$36+'前提と出典'!$C$38) -> 8.4 | C16: =A16*('前提と出典'!$C$37+'前提と出典'!$C$38) -> 7.2 | D16: =A16*('前提と出典'!$C$36*'契約別単価'!C5+'前提と出典'!$C$37*'契約別単価'!C6+'前提と出典'!$C$38*'契約別単価'!C7) -> 86.346369 | E16: =A16*('前提と出典'!$C$36*'契約別単価'!E5+'前提と出典'!$C$37*'契約別単価'!E6+'前提と出典'!$C$38*'契約別単価'!E7) -> 23219.336 | F16: =A16*('前提と出典'!$C$36*'契約別単価'!F5+'前提と出典'!$C$37*'契約別単価'!F6+'前提と出典'!$C$38*'契約別単価'!F7) -> 9112.7458 | G16: =A16*('前提と出典'!$C$36*'契約別単価'!G5+'前提と出典'!$C$37*'契約別単価'!G6+'前提と出典'!$C$38*'契約別単価'!G7) -> 23886.034 | H16: =A16*('前提と出典'!$C$36*'契約別単価'!H5+'前提と出典'!$C$37*'契約別単価'!H6+'前提と出典'!$C$38*'契約別単価'!H7) -> 8289.6516 | I16: =A16*('前提と出典'!$C$36*'契約別単価'!I5+'前提と出典'!$C$37*'契約別単価'!I6+'前提と出典'!$C$38*'契約別単価'!I7) -> 506.34637 | J16: =A16*('前提と出典'!$C$36*'契約別単価'!J5+'前提と出典'!$C$37*'契約別単価'!J6+'前提と出典'!$C$38*'契約別単価'!J7) -> 1179.4745 | K16: =A16*('前提と出典'!$C$36*'契約別単価'!K5+'前提と出典'!$C$37*'契約別単価'!K6+'前提と出典'!$C$38*'契約別単価'!K7) -> 5055.6425 | L16: =A16*('前提と出典'!$C$36*'契約別単価'!L5+'前提と出典'!$C$37*'契約別単価'!L6+'前提と出典'!$C$38*'契約別単価'!L7) -> 4116.3217 | M16: =IF(('前提と出典'!$C$36+'前提と出典'!$C$38)=0,0,IF(B16<=10,'前提と出典'!B73+'前提と出典'!C73,IF(B16<=100,'前提と出典'!B74+'前提と出典'!C74,IF(B16<=500,'前提と出典'!B75+'前提と出典'!C75,'前提と出典'!B76+'前提と出典'!C76)))) -> 10000 | N16: =IF(('前提と出典'!$C$37+'前提と出典'!$C$38)=0,0,IF(C16<=10,'前提と出典'!D73+'前提と出典'!E73,IF(C16<=100,'前提と出典'!D74+'前提と出典'!E74,IF(C16<=500,'前提と出典'!D75+'前提と出典'!E75,'前提と出典'!D76+'前提と出典'!E76)))) -> 30010.935 | O16: =IF('前提と出典'!$C$36+'前提と出典'!$C$38=0,0,'前提と出典'!$B$4*IF('前提と出典'!$B$20=0,MAX('前提と出典'!$B$6,D16*'前提と出典'!$B$5),'前提と出典'!$B$6+D16*'前提と出典'!$B$5)) -> 22500 | P16: =(E16+G16)*(1-'前提と出典'!$B$7)-I16-K16-M16-O16 -> 7347.5873 | Q16: =(F16+H16)*(1-'前提と出典'!$B$7)-J16-L16-N16 -> -18530.82 | R16: =P16-E16*'前提と出典'!$E$4 -> 381.78651 | S16: =Q16-F16*'前提と出典'!$E$4 -> -21264.644 | T16: =R16+S16 -> -20882.857 | U16: =P16-E16*'前提と出典'!$E$5 -> -1940.1471 | V16: =Q16-F16*'前提と出典'!$E$5 -> -22175.918 | W16: =U16+V16 -> -24116.065 | X16: =P16-E16*'前提と出典'!$E$6 -> -4262.0807 | Y16: =Q16-F16*'前提と出典'!$E$6 -> -23087.193 | Z16: =X16+Y16 -> -27349.273 | AA16: =IF(T16>=0,A16,1001) -> 1001 | AB16: =IF(T16<0,A16,0) -> 12 | AC16: =IF(AND(OR('前提と出典'!$C$36+'前提と出典'!$C$38=0,R16>=0),OR('前提と出典'!$C$37+'前提と出典'!$C$38=0,S16>=0)),0,A16) -> 12 | AD16: =IF(W16>=0,A16,1001) -> 1001 | AE16: =IF(W16<0,A16,0) -> 12 | AF16: =IF(AND(OR('前提と出典'!$C$36+'前提と出典'!$C$38=0,U16>=0),OR('前提と出典'!$C$37+'前提と出典'!$C$38=0,V16>=0)),0,A16) -> 12 | AG16: =IF(Z16>=0,A16,1001) -> 1001 | AH16: =IF(Z16<0,A16,0) -> 12 | AI16: =IF(AND(OR('前提と出典'!$C$36+'前提と出典'!$C$38=0,X16>=0),OR('前提と出典'!$C$37+'前提と出典'!$C$38=0,Y16>=0)),0,A16) -> 12
A17: 13 | B17: =A17*('前提と出典'!$C$36+'前提と出典'!$C$38) -> 9.1 | C17: =A17*('前提と出典'!$C$37+'前提と出典'!$C$38) -> 7.8 | D17: =A17*('前提と出典'!$C$36*'契約別単価'!C5+'前提と出典'!$C$37*'契約別単価'!C6+'前提と出典'!$C$38*'契約別単価'!C7) -> 93.541899 | E17: =A17*('前提と出典'!$C$36*'契約別単価'!E5+'前提と出典'!$C$37*'契約別単価'!E6+'前提と出典'!$C$38*'契約別単価'!E7) -> 25154.281 | F17: =A17*('前提と出典'!$C$36*'契約別単価'!F5+'前提と出典'!$C$37*'契約別単価'!F6+'前提と出典'!$C$38*'契約別単価'!F7) -> 9872.1412 | G17: =A17*('前提と出典'!$C$36*'契約別単価'!G5+'前提と出典'!$C$37*'契約別単価'!G6+'前提と出典'!$C$38*'契約別単価'!G7) -> 25876.536 | H17: =A17*('前提と出典'!$C$36*'契約別単価'!H5+'前提と出典'!$C$37*'契約別単価'!H6+'前提と出典'!$C$38*'契約別単価'!H7) -> 8980.4559 | I17: =A17*('前提と出典'!$C$36*'契約別単価'!I5+'前提と出典'!$C$37*'契約別単価'!I6+'前提と出典'!$C$38*'契約別単価'!I7) -> 548.5419 | J17: =A17*('前提と出典'!$C$36*'契約別単価'!J5+'前提と出典'!$C$37*'契約別単価'!J6+'前提と出典'!$C$38*'契約別単価'!J7) -> 1277.7641 | K17: =A17*('前提と出典'!$C$36*'契約別単価'!K5+'前提と出典'!$C$37*'契約別単価'!K6+'前提と出典'!$C$38*'契約別単価'!K7) -> 5476.946 | L17: =A17*('前提と出典'!$C$36*'契約別単価'!L5+'前提と出典'!$C$37*'契約別単価'!L6+'前提と出典'!$C$38*'契約別単価'!L7) -> 4459.3485 | M17: =IF(('前提と出典'!$C$36+'前提と出典'!$C$38)=0,0,IF(B17<=10,'前提と出典'!B73+'前提と出典'!C73,IF(B17<=100,'前提と出典'!B74+'前提と出典'!C74,IF(B17<=500,'前提と出典'!B75+'前提と出典'!C75,'前提と出典'!B76+'前提と出典'!C76)))) -> 10000 | N17: =IF(('前提と出典'!$C$37+'前提と出典'!$C$38)=0,0,IF(C17<=10,'前提と出典'!D73+'前提と出典'!E73,IF(C17<=100,'前提と出典'!D74+'前提と出典'!E74,IF(C17<=500,'前提と出典'!D75+'前提と出典'!E75,'前提と出典'!D76+'前提と出典'!E76)))) -> 30010.935 | O17: =IF('前提と出典'!$C$36+'前提と出典'!$C$38=0,0,'前提と出典'!$B$4*IF('前提と出典'!$B$20=0,MAX('前提と出典'!$B$6,D17*'前提と出典'!$B$5),'前提と出典'!$B$6+D17*'前提と出典'!$B$5)) -> 22500 | P17: =(E17+G17)*(1-'前提と出典'!$B$7)-I17-K17-M17-O17 -> 10668.22 | Q17: =(F17+H17)*(1-'前提と出典'!$B$7)-J17-L17-N17 -> -17574.144 | R17: =P17-E17*'前提と出典'!$E$4 -> 3121.9354 | S17: =Q17-F17*'前提と出典'!$E$4 -> -20535.786 | T17: =R17+S17 -> -17413.851 | U17: =P17-E17*'前提と出典'!$E$5 -> 606.50733 | V17: =Q17-F17*'前提と出典'!$E$5 -> -21523 | W17: =U17+V17 -> -20916.493 | X17: =P17-E17*'前提と出典'!$E$6 -> -1908.9207 | Y17: =Q17-F17*'前提と出典'!$E$6 -> -22510.214 | Z17: =X17+Y17 -> -24419.135 | AA17: =IF(T17>=0,A17,1001) -> 1001 | AB17: =IF(T17<0,A17,0) -> 13 | AC17: =IF(AND(OR('前提と出典'!$C$36+'前提と出典'!$C$38=0,R17>=0),OR('前提と出典'!$C$37+'前提と出典'!$C$38=0,S17>=0)),0,A17) -> 13 | AD17: =IF(W17>=0,A17,1001) -> 1001 | AE17: =IF(W17<0,A17,0) -> 13 | AF17: =IF(AND(OR('前提と出典'!$C$36+'前提と出典'!$C$38=0,U17>=0),OR('前提と出典'!$C$37+'前提と出典'!$C$38=0,V17>=0)),0,A17) -> 13 | AG17: =IF(Z17>=0,A17,1001) -> 1001 | AH17: =IF(Z17<0,A17,0) -> 13 | AI17: =IF(AND(OR('前提と出典'!$C$36+'前提と出典'!$C$38=0,X17>=0),OR('前提と出典'!$C$37+'前提と出典'!$C$38=0,Y17>=0)),0,A17) -> 13
A18: 14 | B18: =A18*('前提と出典'!$C$36+'前提と出典'!$C$38) -> 9.8 | C18: =A18*('前提と出典'!$C$37+'前提と出典'!$C$38) -> 8.4 | D18: =A18*('前提と出典'!$C$36*'契約別単価'!C5+'前提と出典'!$C$37*'契約別単価'!C6+'前提と出典'!$C$38*'契約別単価'!C7) -> 100.73743 | E18: =A18*('前提と出典'!$C$36*'契約別単価'!E5+'前提と出典'!$C$37*'契約別単価'!E6+'前提と出典'!$C$38*'契約別単価'!E7) -> 27089.225 | F18: =A18*('前提と出典'!$C$36*'契約別単価'!F5+'前提と出典'!$C$37*'契約別単価'!F6+'前提と出典'!$C$38*'契約別単価'!F7) -> 10631.537 | G18: =A18*('前提と出典'!$C$36*'契約別単価'!G5+'前提と出典'!$C$37*'契約別単価'!G6+'前提と出典'!$C$38*'契約別単価'!G7) -> 27867.039 | H18: =A18*('前提と出典'!$C$36*'契約別単価'!H5+'前提と出典'!$C$37*'契約別単価'!H6+'前提と出典'!$C$38*'契約別単価'!H7) -> 9671.2602 | I18: =A18*('前提と出典'!$C$36*'契約別単価'!I5+'前提と出典'!$C$37*'契約別単価'!I6+'前提と出典'!$C$38*'契約別単価'!I7) -> 590.73743 | J18: =A18*('前提と出典'!$C$36*'契約別単価'!J5+'前提と出典'!$C$37*'契約別単価'!J6+'前提と出典'!$C$38*'契約別単価'!J7) -> 1376.0536 | K18: =A18*('前提と出典'!$C$36*'契約別単価'!K5+'前提と出典'!$C$37*'契約別単価'!K6+'前提と出典'!$C$38*'契約別単価'!K7) -> 5898.2495 | L18: =A18*('前提と出典'!$C$36*'契約別単価'!L5+'前提と出典'!$C$37*'契約別単価'!L6+'前提と出典'!$C$38*'契約別単価'!L7) -> 4802.3753 | M18: =IF(('前提と出典'!$C$36+'前提と出典'!$C$38)=0,0,IF(B18<=10,'前提と出典'!B73+'前提と出典'!C73,IF(B18<=100,'前提と出典'!B74+'前提と出典'!C74,IF(B18<=500,'前提と出典'!B75+'前提と出典'!C75,'前提と出典'!B76+'前提と出典'!C76)))) -> 10000 | N18: =IF(('前提と出典'!$C$37+'前提と出典'!$C$38)=0,0,IF(C18<=10,'前提と出典'!D73+'前提と出典'!E73,IF(C18<=100,'前提と出典'!D74+'前提と出典'!E74,IF(C18<=500,'前提と出典'!D75+'前提と出典'!E75,'前提と出典'!D76+'前提と出典'!E76)))) -> 30010.935 | O18: =IF('前提と出典'!$C$36+'前提と出典'!$C$38=0,0,'前提と出典'!$B$4*IF('前提と出典'!$B$20=0,MAX('前提と出典'!$B$6,D18*'前提と出典'!$B$5),'前提と出典'!$B$6+D18*'前提と出典'!$B$5)) -> 22500 | P18: =(E18+G18)*(1-'前提と出典'!$B$7)-I18-K18-M18-O18 -> 13988.852 | Q18: =(F18+H18)*(1-'前提と出典'!$B$7)-J18-L18-N18 -> -16617.467 | R18: =P18-E18*'前提と出典'!$E$4 -> 5862.0843 | S18: =Q18-F18*'前提と出典'!$E$4 -> -19806.928 | T18: =R18+S18 -> -13944.844 | U18: =P18-E18*'前提と出典'!$E$5 -> 3153.1617 | V18: =Q18-F18*'前提と出典'!$E$5 -> -20870.082 | W18: =U18+V18 -> -17716.92 | X18: =P18-E18*'前提と出典'!$E$6 -> 444.23922 | Y18: =Q18-F18*'前提と出典'!$E$6 -> -21933.236 | Z18: =X18+Y18 -> -21488.996 | AA18: =IF(T18>=0,A18,1001) -> 1001 | AB18: =IF(T18<0,A18,0) -> 14 | AC18: =IF(AND(OR('前提と出典'!$C$36+'前提と出典'!$C$38=0,R18>=0),OR('前提と出典'!$C$37+'前提と出典'!$C$38=0,S18>=0)),0,A18) -> 14 | AD18: =IF(W18>=0,A18,1001) -> 1001 | AE18: =IF(W18<0,A18,0) -> 14 | AF18: =IF(AND(OR('前提と出典'!$C$36+'前提と出典'!$C$38=0,U18>=0),OR('前提と出典'!$C$37+'前提と出典'!$C$38=0,V18>=0)),0,A18) -> 14 | AG18: =IF(Z18>=0,A18,1001) -> 1001 | AH18: =IF(Z18<0,A18,0) -> 14 | AI18: =IF(AND(OR('前提と出典'!$C$36+'前提と出典'!$C$38=0,X18>=0),OR('前提と出典'!$C$37+'前提と出典'!$C$38=0,Y18>=0)),0,A18) -> 14
A19: 15 | B19: =A19*('前提と出典'!$C$36+'前提と出典'!$C$38) -> 10.5 | C19: =A19*('前提と出典'!$C$37+'前提と出典'!$C$38) -> 9 | D19: =A19*('前提と出典'!$C$36*'契約別単価'!C5+'前提と出典'!$C$37*'契約別単価'!C6+'前提と出典'!$C$38*'契約別単価'!C7) -> 107.93296 | E19: =A19*('前提と出典'!$C$36*'契約別単価'!E5+'前提と出典'!$C$37*'契約別単価'!E6+'前提と出典'!$C$38*'契約別単価'!E7) -> 29024.17 | F19: =A19*('前提と出典'!$C$36*'契約別単価'!F5+'前提と出典'!$C$37*'契約別単価'!F6+'前提と出典'!$C$38*'契約別単価'!F7) -> 11390.932 | G19: =A19*('前提と出典'!$C$36*'契約別単価'!G5+'前提と出典'!$C$37*'契約別単価'!G6+'前提と出典'!$C$38*'契約別単価'!G7) -> 29857.542 | H19: =A19*('前提と出典'!$C$36*'契約別単価'!H5+'前提と出典'!$C$37*'契約別単価'!H6+'前提と出典'!$C$38*'契約別単価'!H7) -> 10362.065 | I19: =A19*('前提と出典'!$C$36*'契約別単価'!I5+'前提と出典'!$C$37*'契約別単価'!I6+'前提と出典'!$C$38*'契約別単価'!I7) -> 632.93296 | J19: =A19*('前提と出典'!$C$36*'契約別単価'!J5+'前提と出典'!$C$37*'契約別単価'!J6+'前提と出典'!$C$38*'契約別単価'!J7) -> 1474.3432 | K19: =A19*('前提と出典'!$C$36*'契約別単価'!K5+'前提と出典'!$C$37*'契約別単価'!K6+'前提と出典'!$C$38*'契約別単価'!K7) -> 6319.5531 | L19: =A19*('前提と出典'!$C$36*'契約別単価'!L5+'前提と出典'!$C$37*'契約別単価'!L6+'前提と出典'!$C$38*'契約別単価'!L7) -> 5145.4022 | M19: =IF(('前提と出典'!$C$36+'前提と出典'!$C$38)=0,0,IF(B19<=10,'前提と出典'!B73+'前提と出典'!C73,IF(B19<=100,'前提と出典'!B74+'前提と出典'!C74,IF(B19<=500,'前提と出典'!B75+'前提と出典'!C75,'前提と出典'!B76+'前提と出典'!C76)))) -> 20000 | N19: =IF(('前提と出典'!$C$37+'前提と出典'!$C$38)=0,0,IF(C19<=10,'前提と出典'!D73+'前提と出典'!E73,IF(C19<=100,'前提と出典'!D74+'前提と出典'!E74,IF(C19<=500,'前提と出典'!D75+'前提と出典'!E75,'前提と出典'!D76+'前提と出典'!E76)))) -> 30010.935 | O19: =IF('前提と出典'!$C$36+'前提と出典'!$C$38=0,0,'前提と出典'!$B$4*IF('前提と出典'!$B$20=0,MAX('前提と出典'!$B$6,D19*'前提と出典'!$B$5),'前提と出典'!$B$6+D19*'前提と出典'!$B$5)) -> 22500 | P19: =(E19+G19)*(1-'前提と出典'!$B$7)-I19-K19-M19-O19 -> 7309.4841 | Q19: =(F19+H19)*(1-'前提と出典'!$B$7)-J19-L19-N19 -> -15660.791 | R19: =P19-E19*'前提と出典'!$E$4 -> -1397.7669 | S19: =Q19-F19*'前提と出典'!$E$4 -> -19078.071 | T19: =R19+S19 -> -20475.838 | U19: =P19-E19*'前提と出典'!$E$5 -> -4300.1838 | V19: =Q19-F19*'前提と出典'!$E$5 -> -20217.164 | W19: =U19+V19 -> -24517.348 | X19: =P19-E19*'前提と出典'!$E$6 -> -7202.6008 | Y19: =Q19-F19*'前提と出典'!$E$6 -> -21356.257 | Z19: =X19+Y19 -> -28558.858 | AA19: =IF(T19>=0,A19,1001) -> 1001 | AB19: =IF(T19<0,A19,0) -> 15 | AC19: =IF(AND(OR('前提と出典'!$C$36+'前提と出典'!$C$38=0,R19>=0),OR('前提と出典'!$C$37+'前提と出典'!$C$38=0,S19>=0)),0,A19) -> 15 | AD19: =IF(W19>=0,A19,1001) -> 1001 | AE19: =IF(W19<0,A19,0) -> 15 | AF19: =IF(AND(OR('前提と出典'!$C$36+'前提と出典'!$C$38=0,U19>=0),OR('前提と出典'!$C$37+'前提と出典'!$C$38=0,V19>=0)),0,A19) -> 15 | AG19: =IF(Z19>=0,A19,1001) -> 1001 | AH19: =IF(Z19<0,A19,0) -> 15 | AI19: =IF(AND(OR('前提と出典'!$C$36+'前提と出典'!$C$38=0,X19>=0),OR('前提と出典'!$C$37+'前提と出典'!$C$38=0,Y19>=0)),0,A19) -> 15
A20: 16 | B20: =A20*('前提と出典'!$C$36+'前提と出典'!$C$38) -> 11.2 | C20: =A20*('前提と出典'!$C$37+'前提と出典'!$C$38) -> 9.6 | D20: =A20*('前提と出典'!$C$36*'契約別単価'!C5+'前提と出典'!$C$37*'契約別単価'!C6+'前提と出典'!$C$38*'契約別単価'!C7) -> 115.12849 | E20: =A20*('前提と出典'!$C$36*'契約別単価'!E5+'前提と出典'!$C$37*'契約別単価'!E6+'前提と出典'!$C$38*'契約別単価'!E7) -> 30959.115 | F20: =A20*('前提と出典'!$C$36*'契約別単価'!F5+'前提と出典'!$C$37*'契約別単価'!F6+'前提と出典'!$C$38*'契約別単価'!F7) -> 12150.328 | G20: =A20*('前提と出典'!$C$36*'契約別単価'!G5+'前提と出典'!$C$37*'契約別単価'!G6+'前提と出典'!$C$38*'契約別単価'!G7) -> 31848.045 | H20: =A20*('前提と出典'!$C$36*'契約別単価'!H5+'前提と出典'!$C$37*'契約別単価'!H6+'前提と出典'!$C$38*'契約別単価'!H7) -> 11052.869 | I20: =A20*('前提と出典'!$C$36*'契約別単価'!I5+'前提と出典'!$C$37*'契約別単価'!I6+'前提と出典'!$C$38*'契約別単価'!I7) -> 675.12849 | J20: =A20*('前提と出典'!$C$36*'契約別単価'!J5+'前提と出典'!$C$37*'契約別単価'!J6+'前提と出典'!$C$38*'契約別単価'!J7) -> 1572.6327 | K20: =A20*('前提と出典'!$C$36*'契約別単価'!K5+'前提と出典'!$C$37*'契約別単価'!K6+'前提と出典'!$C$38*'契約別単価'!K7) -> 6740.8566 | L20: =A20*('前提と出典'!$C$36*'契約別単価'!L5+'前提と出典'!$C$37*'契約別単価'!L6+'前提と出典'!$C$38*'契約別単価'!L7) -> 5488.429 | M20: =IF(('前提と出典'!$C$36+'前提と出典'!$C$38)=0,0,IF(B20<=10,'前提と出典'!B73+'前提と出典'!C73,IF(B20<=100,'前提と出典'!B74+'前提と出典'!C74,IF(B20<=500,'前提と出典'!B75+'前提と出典'!C75,'前提と出典'!B76+'前提と出典'!C76)))) -> 20000 | N20: =IF(('前提と出典'!$C$37+'前提と出典'!$C$38)=0,0,IF(C20<=10,'前提と出典'!D73+'前提と出典'!E73,IF(C20<=100,'前提と出典'!D74+'前提と出典'!E74,IF(C20<=500,'前提と出典'!D75+'前提と出典'!E75,'前提と出典'!D76+'前提と出典'!E76)))) -> 30010.935 | O20: =IF('前提と出典'!$C$36+'前提と出典'!$C$38=0,0,'前提と出典'!$B$4*IF('前提と出典'!$B$20=0,MAX('前提と出典'!$B$6,D20*'前提と出典'!$B$5),'前提と出典'!$B$6+D20*'前提と出典'!$B$5)) -> 22500 | P20: =(E20+G20)*(1-'前提と出典'!$B$7)-I20-K20-M20-O20 -> 10630.116 | Q20: =(F20+H20)*(1-'前提と出典'!$B$7)-J20-L20-N20 -> -14704.115 | R20: =P20-E20*'前提と出典'!$E$4 -> 1342.382 | S20: =Q20-F20*'前提と出典'!$E$4 -> -18349.213 | T20: =R20+S20 -> -17006.831 | U20: =P20-E20*'前提と出典'!$E$5 -> -1753.5294 | V20: =Q20-F20*'前提と出典'!$E$5 -> -19564.246 | W20: =U20+V20 -> -21317.775 | X20: =P20-E20*'前提と出典'!$E$6 -> -4849.4409 | Y20: =Q20-F20*'前提と出典'!$E$6 -> -20779.279 | Z20: =X20+Y20 -> -25628.72 | AA20: =IF(T20>=0,A20,1001) -> 1001 | AB20: =IF(T20<0,A20,0) -> 16 | AC20: =IF(AND(OR('前提と出典'!$C$36+'前提と出典'!$C$38=0,R20>=0),OR('前提と出典'!$C$37+'前提と出典'!$C$38=0,S20>=0)),0,A20) -> 16 | AD20: =IF(W20>=0,A20,1001) -> 1001 | AE20: =IF(W20<0,A20,0) -> 16 | AF20: =IF(AND(OR('前提と出典'!$C$36+'前提と出典'!$C$38=0,U20>=0),OR('前提と出典'!$C$37+'前提と出典'!$C$38=0,V20>=0)),0,A20) -> 16 | AG20: =IF(Z20>=0,A20,1001) -> 1001 | AH20: =IF(Z20<0,A20,0) -> 16 | AI20: =IF(AND(OR('前提と出典'!$C$36+'前提と出典'!$C$38=0,X20>=0),OR('前提と出典'!$C$37+'前提と出典'!$C$38=0,Y20>=0)),0,A20) -> 16
A21: 17 | B21: =A21*('前提と出典'!$C$36+'前提と出典'!$C$38) -> 11.9 | C21: =A21*('前提と出典'!$C$37+'前提と出典'!$C$38) -> 10.2 | D21: =A21*('前提と出典'!$C$36*'契約別単価'!C5+'前提と出典'!$C$37*'契約別単価'!C6+'前提と出典'!$C$38*'契約別単価'!C7) -> 122.32402 | E21: =A21*('前提と出典'!$C$36*'契約別単価'!E5+'前提と出典'!$C$37*'契約別単価'!E6+'前提と出典'!$C$38*'契約別単価'!E7) -> 32894.059 | F21: =A21*('前提と出典'!$C$36*'契約別単価'!F5+'前提と出典'!$C$37*'契約別単価'!F6+'前提と出典'!$C$38*'契約別単価'!F7) -> 12909.723 | G21: =A21*('前提と出典'!$C$36*'契約別単価'!G5+'前提と出典'!$C$37*'契約別単価'!G6+'前提と出典'!$C$38*'契約別単価'!G7) -> 33838.547 | H21: =A21*('前提と出典'!$C$36*'契約別単価'!H5+'前提と出典'!$C$37*'契約別単価'!H6+'前提と出典'!$C$38*'契約別単価'!H7) -> 11743.673 | I21: =A21*('前提と出典'!$C$36*'契約別単価'!I5+'前提と出典'!$C$37*'契約別単価'!I6+'前提と出典'!$C$38*'契約別単価'!I7) -> 717.32402 | J21: =A21*('前提と出典'!$C$36*'契約別単価'!J5+'前提と出典'!$C$37*'契約別単価'!J6+'前提と出典'!$C$38*'契約別単価'!J7) -> 1670.9222 | K21: =A21*('前提と出典'!$C$36*'契約別単価'!K5+'前提と出典'!$C$37*'契約別単価'!K6+'前提と出典'!$C$38*'契約別単価'!K7) -> 7162.1601 | L21: =A21*('前提と出典'!$C$36*'契約別単価'!L5+'前提と出典'!$C$37*'契約別単価'!L6+'前提と出典'!$C$38*'契約別単価'!L7) -> 5831.4558 | M21: =IF(('前提と出典'!$C$36+'前提と出典'!$C$38)=0,0,IF(B21<=10,'前提と出典'!B73+'前提と出典'!C73,IF(B21<=100,'前提と出典'!B74+'前提と出典'!C74,IF(B21<=500,'前提と出典'!B75+'前提と出典'!C75,'前提と出典'!B76+'前提と出典'!C76)))) -> 20000 | N21: =IF(('前提と出典'!$C$37+'前提と出典'!$C$38)=0,0,IF(C21<=10,'前提と出典'!D73+'前提と出典'!E73,IF(C21<=100,'前提と出典'!D74+'前提と出典'!E74,IF(C21<=500,'前提と出典'!D75+'前提と出典'!E75,'前提と出典'!D76+'前提と出典'!E76)))) -> 34510.935 | O21: =IF('前提と出典'!$C$36+'前提と出典'!$C$38=0,0,'前提と出典'!$B$4*IF('前提と出典'!$B$20=0,MAX('前提と出典'!$B$6,D21*'前提と出典'!$B$5),'前提と出典'!$B$6+D21*'前提と出典'!$B$5)) -> 22500 | P21: =(E21+G21)*(1-'前提と出典'!$B$7)-I21-K21-M21-O21 -> 13950.749 | Q21: =(F21+H21)*(1-'前提と出典'!$B$7)-J21-L21-N21 -> -18247.439 | R21: =P21-E21*'前提と出典'!$E$4 -> 4082.5309 | S21: =Q21-F21*'前提と出典'!$E$4 -> -22120.356 | T21: =R21+S21 -> -18037.825 | U21: =P21-E21*'前提と出典'!$E$5 -> 793.12497 | V21: =Q21-F21*'前提と出典'!$E$5 -> -23411.328 | W21: =U21+V21 -> -22618.203 | X21: =P21-E21*'前提と出典'!$E$6 -> -2496.2809 | Y21: =Q21-F21*'前提と出典'!$E$6 -> -24702.3 | Z21: =X21+Y21 -> -27198.581 | AA21: =IF(T21>=0,A21,1001) -> 1001 | AB21: =IF(T21<0,A21,0) -> 17 | AC21: =IF(AND(OR('前提と出典'!$C$36+'前提と出典'!$C$38=0,R21>=0),OR('前提と出典'!$C$37+'前提と出典'!$C$38=0,S21>=0)),0,A21) -> 17 | AD21: =IF(W21>=0,A21,1001) -> 1001 | AE21: =IF(W21<0,A21,0) -> 17 | AF21: =IF(AND(OR('前提と出典'!$C$36+'前提と出典'!$C$38=0,U21>=0),OR('前提と出典'!$C$37+'前提と出典'!$C$38=0,V21>=0)),0,A21) -> 17 | AG21: =IF(Z21>=0,A21,1001) -> 1001 | AH21: =IF(Z21<0,A21,0) -> 17 | AI21: =IF(AND(OR('前提と出典'!$C$36+'前提と出典'!$C$38=0,X21>=0),OR('前提と出典'!$C$37+'前提と出典'!$C$38=0,Y21>=0)),0,A21) -> 17
A22: 18 | B22: =A22*('前提と出典'!$C$36+'前提と出典'!$C$38) -> 12.6 | C22: =A22*('前提と出典'!$C$37+'前提と出典'!$C$38) -> 10.8 | D22: =A22*('前提と出典'!$C$36*'契約別単価'!C5+'前提と出典'!$C$37*'契約別単価'!C6+'前提と出典'!$C$38*'契約別単価'!C7) -> 129.51955 | E22: =A22*('前提と出典'!$C$36*'契約別単価'!E5+'前提と出典'!$C$37*'契約別単価'!E6+'前提と出典'!$C$38*'契約別単価'!E7) -> 34829.004 | F22: =A22*('前提と出典'!$C$36*'契約別単価'!F5+'前提と出典'!$C$37*'契約別単価'!F6+'前提と出典'!$C$38*'契約別単価'!F7) -> 13669.119 | G22: =A22*('前提と出典'!$C$36*'契約別単価'!G5+'前提と出典'!$C$37*'契約別単価'!G6+'前提と出典'!$C$38*'契約別単価'!G7) -> 35829.05 | H22: =A22*('前提と出典'!$C$36*'契約別単価'!H5+'前提と出典'!$C$37*'契約別単価'!H6+'前提と出典'!$C$38*'契約別単価'!H7) -> 12434.477 | I22: =A22*('前提と出典'!$C$36*'契約別単価'!I5+'前提と出典'!$C$37*'契約別単価'!I6+'前提と出典'!$C$38*'契約別単価'!I7) -> 759.51955 | J22: =A22*('前提と出典'!$C$36*'契約別単価'!J5+'前提と出典'!$C$37*'契約別単価'!J6+'前提と出典'!$C$38*'契約別単価'!J7) -> 1769.2118 | K22: =A22*('前提と出典'!$C$36*'契約別単価'!K5+'前提と出典'!$C$37*'契約別単価'!K6+'前提と出典'!$C$38*'契約別単価'!K7) -> 7583.4637 | L22: =A22*('前提と出典'!$C$36*'契約別単価'!L5+'前提と出典'!$C$37*'契約別単価'!L6+'前提と出典'!$C$38*'契約別単価'!L7) -> 6174.4826 | M22: =IF(('前提と出典'!$C$36+'前提と出典'!$C$38)=0,0,IF(B22<=10,'前提と出典'!B73+'前提と出典'!C73,IF(B22<=100,'前提と出典'!B74+'前提と出典'!C74,IF(B22<=500,'前提と出典'!B75+'前提と出典'!C75,'前提と出典'!B76+'前提と出典'!C76)))) -> 20000 | N22: =IF(('前提と出典'!$C$37+'前提と出典'!$C$38)=0,0,IF(C22<=10,'前提と出典'!D73+'前提と出典'!E73,IF(C22<=100,'前提と出典'!D74+'前提と出典'!E74,IF(C22<=500,'前提と出典'!D75+'前提と出典'!E75,'前提と出典'!D76+'前提と出典'!E76)))) -> 34510.935 | O22: =IF('前提と出典'!$C$36+'前提と出典'!$C$38=0,0,'前提と出典'!$B$4*IF('前提と出典'!$B$20=0,MAX('前提と出典'!$B$6,D22*'前提と出典'!$B$5),'前提と出典'!$B$6+D22*'前提と出典'!$B$5)) -> 22500 | P22: =(E22+G22)*(1-'前提と出典'!$B$7)-I22-K22-M22-O22 -> 17271.381 | Q22: =(F22+H22)*(1-'前提と出典'!$B$7)-J22-L22-N22 -> -17290.762 | R22: =P22-E22*'前提と出典'!$E$4 -> 6822.6798 | S22: =Q22-F22*'前提と出典'!$E$4 -> -21391.498 | T22: =R22+S22 -> -14568.818 | U22: =P22-E22*'前提と出典'!$E$5 -> 3339.7794 | V22: =Q22-F22*'前提と出典'!$E$5 -> -22758.41 | W22: =U22+V22 -> -19418.63 | X22: =P22-E22*'前提と出典'!$E$6 -> -143.121 | Y22: =Q22-F22*'前提と出典'!$E$6 -> -24125.322 | Z22: =X22+Y22 -> -24268.443 | AA22: =IF(T22>=0,A22,1001) -> 1001 | AB22: =IF(T22<0,A22,0) -> 18 | AC22: =IF(AND(OR('前提と出典'!$C$36+'前提と出典'!$C$38=0,R22>=0),OR('前提と出典'!$C$37+'前提と出典'!$C$38=0,S22>=0)),0,A22) -> 18 | AD22: =IF(W22>=0,A22,1001) -> 1001 | AE22: =IF(W22<0,A22,0) -> 18 | AF22: =IF(AND(OR('前提と出典'!$C$36+'前提と出典'!$C$38=0,U22>=0),OR('前提と出典'!$C$37+'前提と出典'!$C$38=0,V22>=0)),0,A22) -> 18 | AG22: =IF(Z22>=0,A22,1001) -> 1001 | AH22: =IF(Z22<0,A22,0) -> 18 | AI22: =IF(AND(OR('前提と出典'!$C$36+'前提と出典'!$C$38=0,X22>=0),OR('前提と出典'!$C$37+'前提と出典'!$C$38=0,Y22>=0)),0,A22) -> 18
A23: 19 | B23: =A23*('前提と出典'!$C$36+'前提と出典'!$C$38) -> 13.3 | C23: =A23*('前提と出典'!$C$37+'前提と出典'!$C$38) -> 11.4 | D23: =A23*('前提と出典'!$C$36*'契約別単価'!C5+'前提と出典'!$C$37*'契約別単価'!C6+'前提と出典'!$C$38*'契約別単価'!C7) -> 136.71508 | E23: =A23*('前提と出典'!$C$36*'契約別単価'!E5+'前提と出典'!$C$37*'契約別単価'!E6+'前提と出典'!$C$38*'契約別単価'!E7) -> 36763.948 | F23: =A23*('前提と出典'!$C$36*'契約別単価'!F5+'前提と出典'!$C$37*'契約別単価'!F6+'前提と出典'!$C$38*'契約別単価'!F7) -> 14428.514 | G23: =A23*('前提と出典'!$C$36*'契約別単価'!G5+'前提と出典'!$C$37*'契約別単価'!G6+'前提と出典'!$C$38*'契約別単価'!G7) -> 37819.553 | H23: =A23*('前提と出典'!$C$36*'契約別単価'!H5+'前提と出典'!$C$37*'契約別単価'!H6+'前提と出典'!$C$38*'契約別単価'!H7) -> 13125.282 | I23: =A23*('前提と出典'!$C$36*'契約別単価'!I5+'前提と出典'!$C$37*'契約別単価'!I6+'前提と出典'!$C$38*'契約別単価'!I7) -> 801.71508 | J23: =A23*('前提と出典'!$C$36*'契約別単価'!J5+'前提と出典'!$C$37*'契約別単価'!J6+'前提と出典'!$C$38*'契約別単価'!J7) -> 1867.5013 | K23: =A23*('前提と出典'!$C$36*'契約別単価'!K5+'前提と出典'!$C$37*'契約別単価'!K6+'前提と出典'!$C$38*'契約別単価'!K7) -> 8004.7672 | L23: =A23*('前提と出典'!$C$36*'契約別単価'!L5+'前提と出典'!$C$37*'契約別単価'!L6+'前提と出典'!$C$38*'契約別単価'!L7) -> 6517.5094 | M23: =IF(('前提と出典'!$C$36+'前提と出典'!$C$38)=0,0,IF(B23<=10,'前提と出典'!B73+'前提と出典'!C73,IF(B23<=100,'前提と出典'!B74+'前提と出典'!C74,IF(B23<=500,'前提と出典'!B75+'前提と出典'!C75,'前提と出典'!B76+'前提と出典'!C76)))) -> 20000 | N23: =IF(('前提と出典'!$C$37+'前提と出典'!$C$38)=0,0,IF(C23<=10,'前提と出典'!D73+'前提と出典'!E73,IF(C23<=100,'前提と出典'!D74+'前提と出典'!E74,IF(C23<=500,'前提と出典'!D75+'前提と出典'!E75,'前提と出典'!D76+'前提と出典'!E76)))) -> 34510.935 | O23: =IF('前提と出典'!$C$36+'前提と出典'!$C$38=0,0,'前提と出典'!$B$4*IF('前提と出典'!$B$20=0,MAX('前提と出典'!$B$6,D23*'前提と出典'!$B$5),'前提と出典'!$B$6+D23*'前提と出典'!$B$5)) -> 22500 | P23: =(E23+G23)*(1-'前提と出典'!$B$7)-I23-K23-M23-O23 -> 20592.013 | Q23: =(F23+H23)*(1-'前提と出典'!$B$7)-J23-L23-N23 -> -16334.086 | R23: =P23-E23*'前提と出典'!$E$4 -> 9562.8286 | S23: =Q23-F23*'前提と出典'!$E$4 -> -20662.64 | T23: =R23+S23 -> -11099.812 | U23: =P23-E23*'前提と出典'!$E$5 -> 5886.4338 | V23: =Q23-F23*'前提と出典'!$E$5 -> -22105.492 | W23: =U23+V23 -> -16219.058 | X23: =P23-E23*'前提と出典'!$E$6 -> 2210.0389 | Y23: =Q23-F23*'前提と出典'!$E$6 -> -23548.343 | Z23: =X23+Y23 -> -21338.304 | AA23: =IF(T23>=0,A23,1001) -> 1001 | AB23: =IF(T23<0,A23,0) -> 19 | AC23: =IF(AND(OR('前提と出典'!$C$36+'前提と出典'!$C$38=0,R23>=0),OR('前提と出典'!$C$37+'前提と出典'!$C$38=0,S23>=0)),0,A23) -> 19 | AD23: =IF(W23>=0,A23,1001) -> 1001 | AE23: =IF(W23<0,A23,0) -> 19 | AF23: =IF(AND(OR('前提と出典'!$C$36+'前提と出典'!$C$38=0,U23>=0),OR('前提と出典'!$C$37+'前提と出典'!$C$38=0,V23>=0)),0,A23) -> 19 | AG23: =IF(Z23>=0,A23,1001) -> 1001 | AH23: =IF(Z23<0,A23,0) -> 19 | AI23: =IF(AND(OR('前提と出典'!$C$36+'前提と出典'!$C$38=0,X23>=0),OR('前提と出典'!$C$37+'前提と出典'!$C$38=0,Y23>=0)),0,A23) -> 19
A24: 20 | B24: =A24*('前提と出典'!$C$36+'前提と出典'!$C$38) -> 14 | C24: =A24*('前提と出典'!$C$37+'前提と出典'!$C$38) -> 12 | D24: =A24*('前提と出典'!$C$36*'契約別単価'!C5+'前提と出典'!$C$37*'契約別単価'!C6+'前提と出典'!$C$38*'契約別単価'!C7) -> 143.91061 | E24: =A24*('前提と出典'!$C$36*'契約別単価'!E5+'前提と出典'!$C$37*'契約別単価'!E6+'前提と出典'!$C$38*'契約別単価'!E7) -> 38698.893 | F24: =A24*('前提と出典'!$C$36*'契約別単価'!F5+'前提と出典'!$C$37*'契約別単価'!F6+'前提と出典'!$C$38*'契約別単価'!F7) -> 15187.91 | G24: =A24*('前提と出典'!$C$36*'契約別単価'!G5+'前提と出典'!$C$37*'契約別単価'!G6+'前提と出典'!$C$38*'契約別単価'!G7) -> 39810.056 | H24: =A24*('前提と出典'!$C$36*'契約別単価'!H5+'前提と出典'!$C$37*'契約別単価'!H6+'前提と出典'!$C$38*'契約別単価'!H7) -> 13816.086 | I24: =A24*('前提と出典'!$C$36*'契約別単価'!I5+'前提と出典'!$C$37*'契約別単価'!I6+'前提と出典'!$C$38*'契約別単価'!I7) -> 843.91061 | J24: =A24*('前提と出典'!$C$36*'契約別単価'!J5+'前提と出典'!$C$37*'契約別単価'!J6+'前提と出典'!$C$38*'契約別単価'!J7) -> 1965.7909 | K24: =A24*('前提と出典'!$C$36*'契約別単価'!K5+'前提と出典'!$C$37*'契約別単価'!K6+'前提と出典'!$C$38*'契約別単価'!K7) -> 8426.0708 | L24: =A24*('前提と出典'!$C$36*'契約別単価'!L5+'前提と出典'!$C$37*'契約別単価'!L6+'前提と出典'!$C$38*'契約別単価'!L7) -> 6860.5362 | M24: =IF(('前提と出典'!$C$36+'前提と出典'!$C$38)=0,0,IF(B24<=10,'前提と出典'!B73+'前提と出典'!C73,IF(B24<=100,'前提と出典'!B74+'前提と出典'!C74,IF(B24<=500,'前提と出典'!B75+'前提と出典'!C75,'前提と出典'!B76+'前提と出典'!C76)))) -> 20000 | N24: =IF(('前提と出典'!$C$37+'前提と出典'!$C$38)=0,0,IF(C24<=10,'前提と出典'!D73+'前提と出典'!E73,IF(C24<=100,'前提と出典'!D74+'前提と出典'!E74,IF(C24<=500,'前提と出典'!D75+'前提と出典'!E75,'前提と出典'!D76+'前提と出典'!E76)))) -> 34510.935 | O24: =IF('前提と出典'!$C$36+'前提と出典'!$C$38=0,0,'前提と出典'!$B$4*IF('前提と出典'!$B$20=0,MAX('前提と出典'!$B$6,D24*'前提と出典'!$B$5),'前提と出典'!$B$6+D24*'前提と出典'!$B$5)) -> 22500 | P24: =(E24+G24)*(1-'前提と出典'!$B$7)-I24-K24-M24-O24 -> 23912.645 | Q24: =(F24+H24)*(1-'前提と出典'!$B$7)-J24-L24-N24 -> -15377.41 | R24: =P24-E24*'前提と出典'!$E$4 -> 12302.978 | S24: =Q24-F24*'前提と出典'!$E$4 -> -19933.783 | T24: =R24+S24 -> -7630.8053 | U24: =P24-E24*'前提と出典'!$E$5 -> 8433.0882 | V24: =Q24-F24*'前提と出典'!$E$5 -> -21452.574 | W24: =U24+V24 -> -13019.486 | X24: =P24-E24*'前提と出典'!$E$6 -> 4563.1989 | Y24: =Q24-F24*'前提と出典'!$E$6 -> -22971.365 | Z24: =X24+Y24 -> -18408.166 | AA24: =IF(T24>=0,A24,1001) -> 1001 | AB24: =IF(T24<0,A24,0) -> 20 | AC24: =IF(AND(OR('前提と出典'!$C$36+'前提と出典'!$C$38=0,R24>=0),OR('前提と出典'!$C$37+'前提と出典'!$C$38=0,S24>=0)),0,A24) -> 20 | AD24: =IF(W24>=0,A24,1001) -> 1001 | AE24: =IF(W24<0,A24,0) -> 20 | AF24: =IF(AND(OR('前提と出典'!$C$36+'前提と出典'!$C$38=0,U24>=0),OR('前提と出典'!$C$37+'前提と出典'!$C$38=0,V24>=0)),0,A24) -> 20 | AG24: =IF(Z24>=0,A24,1001) -> 1001 | AH24: =IF(Z24<0,A24,0) -> 20 | AI24: =IF(AND(OR('前提と出典'!$C$36+'前提と出典'!$C$38=0,X24>=0),OR('前提と出典'!$C$37+'前提と出典'!$C$38=0,Y24>=0)),0,A24) -> 20
A25: 21 | B25: =A25*('前提と出典'!$C$36+'前提と出典'!$C$38) -> 14.7 | C25: =A25*('前提と出典'!$C$37+'前提と出典'!$C$38) -> 12.6 | D25: =A25*('前提と出典'!$C$36*'契約別単価'!C5+'前提と出典'!$C$37*'契約別単価'!C6+'前提と出典'!$C$38*'契約別単価'!C7) -> 151.10615 | E25: =A25*('前提と出典'!$C$36*'契約別単価'!E5+'前提と出典'!$C$37*'契約別単価'!E6+'前提と出典'!$C$38*'契約別単価'!E7) -> 40633.838 | F25: =A25*('前提と出典'!$C$36*'契約別単価'!F5+'前提と出典'!$C$37*'契約別単価'!F6+'前提と出典'!$C$38*'契約別単価'!F7) -> 15947.305 | G25: =A25*('前提と出典'!$C$36*'契約別単価'!G5+'前提と出典'!$C$37*'契約別単価'!G6+'前提と出典'!$C$38*'契約別単価'!G7) -> 41800.559 | H25: =A25*('前提と出典'!$C$36*'契約別単価'!H5+'前提と出典'!$C$37*'契約別単価'!H6+'前提と出典'!$C$38*'契約別単価'!H7) -> 14506.89 | I25: =A25*('前提と出典'!$C$36*'契約別単価'!I5+'前提と出典'!$C$37*'契約別単価'!I6+'前提と出典'!$C$38*'契約別単価'!I7) -> 886.10615 | J25: =A25*('前提と出典'!$C$36*'契約別単価'!J5+'前提と出典'!$C$37*'契約別単価'!J6+'前提と出典'!$C$38*'契約別単価'!J7) -> 2064.0804 | K25: =A25*('前提と出典'!$C$36*'契約別単価'!K5+'前提と出典'!$C$37*'契約別単価'!K6+'前提と出典'!$C$38*'契約別単価'!K7) -> 8847.3743 | L25: =A25*('前提と出典'!$C$36*'契約別単価'!L5+'前提と出典'!$C$37*'契約別単価'!L6+'前提と出典'!$C$38*'契約別単価'!L7) -> 7203.563 | M25: =IF(('前提と出典'!$C$36+'前提と出典'!$C$38)=0,0,IF(B25<=10,'前提と出典'!B73+'前提と出典'!C73,IF(B25<=100,'前提と出典'!B74+'前提と出典'!C74,IF(B25<=500,'前提と出典'!B75+'前提と出典'!C75,'前提と出典'!B76+'前提と出典'!C76)))) -> 20000 | N25: =IF(('前提と出典'!$C$37+'前提と出典'!$C$38)=0,0,IF(C25<=10,'前提と出典'!D73+'前提と出典'!E73,IF(C25<=100,'前提と出典'!D74+'前提と出典'!E74,IF(C25<=500,'前提と出典'!D75+'前提と出典'!E75,'前提と出典'!D76+'前提と出典'!E76)))) -> 34510.935 | O25: =IF('前提と出典'!$C$36+'前提と出典'!$C$38=0,0,'前提と出典'!$B$4*IF('前提と出典'!$B$20=0,MAX('前提と出典'!$B$6,D25*'前提と出典'!$B$5),'前提と出典'!$B$6+D25*'前提と出典'!$B$5)) -> 22500 | P25: =(E25+G25)*(1-'前提と出典'!$B$7)-I25-K25-M25-O25 -> 27233.278 | Q25: =(F25+H25)*(1-'前提と出典'!$B$7)-J25-L25-N25 -> -14420.734 | R25: =P25-E25*'前提と出典'!$E$4 -> 15043.126 | S25: =Q25-F25*'前提と出典'!$E$4 -> -19204.925 | T25: =R25+S25 -> -4161.7988 | U25: =P25-E25*'前提と出典'!$E$5 -> 10979.743 | V25: =Q25-F25*'前提と出典'!$E$5 -> -20799.656 | W25: =U25+V25 -> -9819.9131 | X25: =P25-E25*'前提と出典'!$E$6 -> 6916.3588 | Y25: =Q25-F25*'前提と出典'!$E$6 -> -22394.386 | Z25: =X25+Y25 -> -15478.027 | AA25: =IF(T25>=0,A25,1001) -> 1001 | AB25: =IF(T25<0,A25,0) -> 21 | AC25: =IF(AND(OR('前提と出典'!$C$36+'前提と出典'!$C$38=0,R25>=0),OR('前提と出典'!$C$37+'前提と出典'!$C$38=0,S25>=0)),0,A25) -> 21 | AD25: =IF(W25>=0,A25,1001) -> 1001 | AE25: =IF(W25<0,A25,0) -> 21 | AF25: =IF(AND(OR('前提と出典'!$C$36+'前提と出典'!$C$38=0,U25>=0),OR('前提と出典'!$C$37+'前提と出典'!$C$38=0,V25>=0)),0,A25) -> 21 | AG25: =IF(Z25>=0,A25,1001) -> 1001 | AH25: =IF(Z25<0,A25,0) -> 21 | AI25: =IF(AND(OR('前提と出典'!$C$36+'前提と出典'!$C$38=0,X25>=0),OR('前提と出典'!$C$37+'前提と出典'!$C$38=0,Y25>=0)),0,A25) -> 21
A26: 22 | B26: =A26*('前提と出典'!$C$36+'前提と出典'!$C$38) -> 15.4 | C26: =A26*('前提と出典'!$C$37+'前提と出典'!$C$38) -> 13.2 | D26: =A26*('前提と出典'!$C$36*'契約別単価'!C5+'前提と出典'!$C$37*'契約別単価'!C6+'前提と出典'!$C$38*'契約別単価'!C7) -> 158.30168 | E26: =A26*('前提と出典'!$C$36*'契約別単価'!E5+'前提と出典'!$C$37*'契約別単価'!E6+'前提と出典'!$C$38*'契約別単価'!E7) -> 42568.782 | F26: =A26*('前提と出典'!$C$36*'契約別単価'!F5+'前提と出典'!$C$37*'契約別単価'!F6+'前提と出典'!$C$38*'契約別単価'!F7) -> 16706.701 | G26: =A26*('前提と出典'!$C$36*'契約別単価'!G5+'前提と出典'!$C$37*'契約別単価'!G6+'前提と出典'!$C$38*'契約別単価'!G7) -> 43791.061 | H26: =A26*('前提と出典'!$C$36*'契約別単価'!H5+'前提と出典'!$C$37*'契約別単価'!H6+'前提と出典'!$C$38*'契約別単価'!H7) -> 15197.695 | I26: =A26*('前提と出典'!$C$36*'契約別単価'!I5+'前提と出典'!$C$37*'契約別単価'!I6+'前提と出典'!$C$38*'契約別単価'!I7) -> 928.30168 | J26: =A26*('前提と出典'!$C$36*'契約別単価'!J5+'前提と出典'!$C$37*'契約別単価'!J6+'前提と出典'!$C$38*'契約別単価'!J7) -> 2162.37 | K26: =A26*('前提と出典'!$C$36*'契約別単価'!K5+'前提と出典'!$C$37*'契約別単価'!K6+'前提と出典'!$C$38*'契約別単価'!K7) -> 9268.6778 | L26: =A26*('前提と出典'!$C$36*'契約別単価'!L5+'前提と出典'!$C$37*'契約別単価'!L6+'前提と出典'!$C$38*'契約別単価'!L7) -> 7546.5898 | M26: =IF(('前提と出典'!$C$36+'前提と出典'!$C$38)=0,0,IF(B26<=10,'前提と出典'!B73+'前提と出典'!C73,IF(B26<=100,'前提と出典'!B74+'前提と出典'!C74,IF(B26<=500,'前提と出典'!B75+'前提と出典'!C75,'前提と出典'!B76+'前提と出典'!C76)))) -> 20000 | N26: =IF(('前提と出典'!$C$37+'前提と出典'!$C$38)=0,0,IF(C26<=10,'前提と出典'!D73+'前提と出典'!E73,IF(C26<=100,'前提と出典'!D74+'前提と出典'!E74,IF(C26<=500,'前提と出典'!D75+'前提と出典'!E75,'前提と出典'!D76+'前提と出典'!E76)))) -> 34510.935 | O26: =IF('前提と出典'!$C$36+'前提と出典'!$C$38=0,0,'前提と出典'!$B$4*IF('前提と出典'!$B$20=0,MAX('前提と出典'!$B$6,D26*'前提と出典'!$B$5),'前提と出典'!$B$6+D26*'前提と出典'!$B$5)) -> 22500 | P26: =(E26+G26)*(1-'前提と出典'!$B$7)-I26-K26-M26-O26 -> 30553.91 | Q26: =(F26+H26)*(1-'前提と出典'!$B$7)-J26-L26-N26 -> -13464.057 | R26: =P26-E26*'前提と出典'!$E$4 -> 17783.275 | S26: =Q26-F26*'前提と出典'!$E$4 -> -18476.068 | T26: =R26+S26 -> -692.79236 | U26: =P26-E26*'前提と出典'!$E$5 -> 13526.397 | V26: =Q26-F26*'前提と出典'!$E$5 -> -20146.738 | W26: =U26+V26 -> -6620.3407 | X26: =P26-E26*'前提と出典'!$E$6 -> 9269.5188 | Y26: =Q26-F26*'前提と出典'!$E$6 -> -21817.408 | Z26: =X26+Y26 -> -12547.889 | AA26: =IF(T26>=0,A26,1001) -> 1001 | AB26: =IF(T26<0,A26,0) -> 22 | AC26: =IF(AND(OR('前提と出典'!$C$36+'前提と出典'!$C$38=0,R26>=0),OR('前提と出典'!$C$37+'前提と出典'!$C$38=0,S26>=0)),0,A26) -> 22 | AD26: =IF(W26>=0,A26,1001) -> 1001 | AE26: =IF(W26<0,A26,0) -> 22 | AF26: =IF(AND(OR('前提と出典'!$C$36+'前提と出典'!$C$38=0,U26>=0),OR('前提と出典'!$C$37+'前提と出典'!$C$38=0,V26>=0)),0,A26) -> 22 | AG26: =IF(Z26>=0,A26,1001) -> 1001 | AH26: =IF(Z26<0,A26,0) -> 22 | AI26: =IF(AND(OR('前提と出典'!$C$36+'前提と出典'!$C$38=0,X26>=0),OR('前提と出典'!$C$37+'前提と出典'!$C$38=0,Y26>=0)),0,A26) -> 22
A27: 23 | B27: =A27*('前提と出典'!$C$36+'前提と出典'!$C$38) -> 16.1 | C27: =A27*('前提と出典'!$C$37+'前提と出典'!$C$38) -> 13.8 | D27: =A27*('前提と出典'!$C$36*'契約別単価'!C5+'前提と出典'!$C$37*'契約別単価'!C6+'前提と出典'!$C$38*'契約別単価'!C7) -> 165.49721 | E27: =A27*('前提と出典'!$C$36*'契約別単価'!E5+'前提と出典'!$C$37*'契約別単価'!E6+'前提と出典'!$C$38*'契約別単価'!E7) -> 44503.727 | F27: =A27*('前提と出典'!$C$36*'契約別単価'!F5+'前提と出典'!$C$37*'契約別単価'!F6+'前提と出典'!$C$38*'契約別単価'!F7) -> 17466.096 | G27: =A27*('前提と出典'!$C$36*'契約別単価'!G5+'前提と出典'!$C$37*'契約別単価'!G6+'前提と出典'!$C$38*'契約別単価'!G7) -> 45781.564 | H27: =A27*('前提と出典'!$C$36*'契約別単価'!H5+'前提と出典'!$C$37*'契約別単価'!H6+'前提と出典'!$C$38*'契約別単価'!H7) -> 15888.499 | I27: =A27*('前提と出典'!$C$36*'契約別単価'!I5+'前提と出典'!$C$37*'契約別単価'!I6+'前提と出典'!$C$38*'契約別単価'!I7) -> 970.49721 | J27: =A27*('前提と出典'!$C$36*'契約別単価'!J5+'前提と出典'!$C$37*'契約別単価'!J6+'前提と出典'!$C$38*'契約別単価'!J7) -> 2260.6595 | K27: =A27*('前提と出典'!$C$36*'契約別単価'!K5+'前提と出典'!$C$37*'契約別単価'!K6+'前提と出典'!$C$38*'契約別単価'!K7) -> 9689.9814 | L27: =A27*('前提と出典'!$C$36*'契約別単価'!L5+'前提と出典'!$C$37*'契約別単価'!L6+'前提と出典'!$C$38*'契約別単価'!L7) -> 7889.6166 | M27: =IF(('前提と出典'!$C$36+'前提と出典'!$C$38)=0,0,IF(B27<=10,'前提と出典'!B73+'前提と出典'!C73,IF(B27<=100,'前提と出典'!B74+'前提と出典'!C74,IF(B27<=500,'前提と出典'!B75+'前提と出典'!C75,'前提と出典'!B76+'前提と出典'!C76)))) -> 20000 | N27: =IF(('前提と出典'!$C$37+'前提と出典'!$C$38)=0,0,IF(C27<=10,'前提と出典'!D73+'前提と出典'!E73,IF(C27<=100,'前提と出典'!D74+'前提と出典'!E74,IF(C27<=500,'前提と出典'!D75+'前提と出典'!E75,'前提と出典'!D76+'前提と出典'!E76)))) -> 34510.935 | O27: =IF('前提と出典'!$C$36+'前提と出典'!$C$38=0,0,'前提と出典'!$B$4*IF('前提と出典'!$B$20=0,MAX('前提と出典'!$B$6,D27*'前提と出典'!$B$5),'前提と出典'!$B$6+D27*'前提と出典'!$B$5)) -> 22838.615 | P27: =(E27+G27)*(1-'前提と出典'!$B$7)-I27-K27-M27-O27 -> 33535.928 | Q27: =(F27+H27)*(1-'前提と出典'!$B$7)-J27-L27-N27 -> -12507.381 | R27: =P27-E27*'前提と出典'!$E$4 -> 20184.81 | S27: =Q27-F27*'前提と出典'!$E$4 -> -17747.21 | T27: =R27+S27 -> 2437.5996 | U27: =P27-E27*'前提と出典'!$E$5 -> 15734.437 | V27: =Q27-F27*'前提と出典'!$E$5 -> -19493.82 | W27: =U27+V27 -> -3759.3827 | X27: =P27-E27*'前提と出典'!$E$6 -> 11284.064 | Y27: =Q27-F27*'前提と出典'!$E$6 -> -21240.429 | Z27: =X27+Y27 -> -9956.365 | AA27: =IF(T27>=0,A27,1001) -> 23 | AB27: =IF(T27<0,A27,0) -> 0 | AC27: =IF(AND(OR('前提と出典'!$C$36+'前提と出典'!$C$38=0,R27>=0),OR('前提と出典'!$C$37+'前提と出典'!$C$38=0,S27>=0)),0,A27) -> 23 | AD27: =IF(W27>=0,A27,1001) -> 1001 | AE27: =IF(W27<0,A27,0) -> 23 | AF27: =IF(AND(OR('前提と出典'!$C$36+'前提と出典'!$C$38=0,U27>=0),OR('前提と出典'!$C$37+'前提と出典'!$C$38=0,V27>=0)),0,A27) -> 23 | AG27: =IF(Z27>=0,A27,1001) -> 1001 | AH27: =IF(Z27<0,A27,0) -> 23 | AI27: =IF(AND(OR('前提と出典'!$C$36+'前提と出典'!$C$38=0,X27>=0),OR('前提と出典'!$C$37+'前提と出典'!$C$38=0,Y27>=0)),0,A27) -> 23
A28: 24 | B28: =A28*('前提と出典'!$C$36+'前提と出典'!$C$38) -> 16.8 | C28: =A28*('前提と出典'!$C$37+'前提と出典'!$C$38) -> 14.4 | D28: =A28*('前提と出典'!$C$36*'契約別単価'!C5+'前提と出典'!$C$37*'契約別単価'!C6+'前提と出典'!$C$38*'契約別単価'!C7) -> 172.69274 | E28: =A28*('前提と出典'!$C$36*'契約別単価'!E5+'前提と出典'!$C$37*'契約別単価'!E6+'前提と出典'!$C$38*'契約別単価'!E7) -> 46438.672 | F28: =A28*('前提と出典'!$C$36*'契約別単価'!F5+'前提と出典'!$C$37*'契約別単価'!F6+'前提と出典'!$C$38*'契約別単価'!F7) -> 18225.492 | G28: =A28*('前提と出典'!$C$36*'契約別単価'!G5+'前提と出典'!$C$37*'契約別単価'!G6+'前提と出典'!$C$38*'契約別単価'!G7) -> 47772.067 | H28: =A28*('前提と出典'!$C$36*'契約別単価'!H5+'前提と出典'!$C$37*'契約別単価'!H6+'前提と出典'!$C$38*'契約別単価'!H7) -> 16579.303 | I28: =A28*('前提と出典'!$C$36*'契約別単価'!I5+'前提と出典'!$C$37*'契約別単価'!I6+'前提と出典'!$C$38*'契約別単価'!I7) -> 1012.6927 | J28: =A28*('前提と出典'!$C$36*'契約別単価'!J5+'前提と出典'!$C$37*'契約別単価'!J6+'前提と出典'!$C$38*'契約別単価'!J7) -> 2358.949 | K28: =A28*('前提と出典'!$C$36*'契約別単価'!K5+'前提と出典'!$C$37*'契約別単価'!K6+'前提と出典'!$C$38*'契約別単価'!K7) -> 10111.285 | L28: =A28*('前提と出典'!$C$36*'契約別単価'!L5+'前提と出典'!$C$37*'契約別単価'!L6+'前提と出典'!$C$38*'契約別単価'!L7) -> 8232.6434 | M28: =IF(('前提と出典'!$C$36+'前提と出典'!$C$38)=0,0,IF(B28<=10,'前提と出典'!B73+'前提と出典'!C73,IF(B28<=100,'前提と出典'!B74+'前提と出典'!C74,IF(B28<=500,'前提と出典'!B75+'前提と出典'!C75,'前提と出典'!B76+'前提と出典'!C76)))) -> 20000 | N28: =IF(('前提と出典'!$C$37+'前提と出典'!$C$38)=0,0,IF(C28<=10,'前提と出典'!D73+'前提と出典'!E73,IF(C28<=100,'前提と出典'!D74+'前提と出典'!E74,IF(C28<=500,'前提と出典'!D75+'前提と出典'!E75,'前提と出典'!D76+'前提と出典'!E76)))) -> 34510.935 | O28: =IF('前提と出典'!$C$36+'前提と出典'!$C$38=0,0,'前提と出典'!$B$4*IF('前提と出典'!$B$20=0,MAX('前提と出典'!$B$6,D28*'前提と出典'!$B$5),'前提と出典'!$B$6+D28*'前提と出典'!$B$5)) -> 23831.598 | P28: =(E28+G28)*(1-'前提と出典'!$B$7)-I28-K28-M28-O28 -> 35863.577 | Q28: =(F28+H28)*(1-'前提と出典'!$B$7)-J28-L28-N28 -> -11550.705 | R28: =P28-E28*'前提と出典'!$E$4 -> 21931.975 | S28: =Q28-F28*'前提と出典'!$E$4 -> -17018.352 | T28: =R28+S28 -> 4913.6228 | U28: =P28-E28*'前提と出典'!$E$5 -> 17288.108 | V28: =Q28-F28*'前提と出典'!$E$5 -> -18840.902 | W28: =U28+V28 -> -1552.7935 | X28: =P28-E28*'前提と出典'!$E$6 -> 12644.241 | Y28: =Q28-F28*'前提と出典'!$E$6 -> -20663.451 | Z28: =X28+Y28 -> -8019.2098 | AA28: =IF(T28>=0,A28,1001) -> 24 | AB28: =IF(T28<0,A28,0) -> 0 | AC28: =IF(AND(OR('前提と出典'!$C$36+'前提と出典'!$C$38=0,R28>=0),OR('前提と出典'!$C$37+'前提と出典'!$C$38=0,S28>=0)),0,A28) -> 24 | AD28: =IF(W28>=0,A28,1001) -> 1001 | AE28: =IF(W28<0,A28,0) -> 24 | AF28: =IF(AND(OR('前提と出典'!$C$36+'前提と出典'!$C$38=0,U28>=0),OR('前提と出典'!$C$37+'前提と出典'!$C$38=0,V28>=0)),0,A28) -> 24 | AG28: =IF(Z28>=0,A28,1001) -> 1001 | AH28: =IF(Z28<0,A28,0) -> 24 | AI28: =IF(AND(OR('前提と出典'!$C$36+'前提と出典'!$C$38=0,X28>=0),OR('前提と出典'!$C$37+'前提と出典'!$C$38=0,Y28>=0)),0,A28) -> 24
A29: 25 | B29: =A29*('前提と出典'!$C$36+'前提と出典'!$C$38) -> 17.5 | C29: =A29*('前提と出典'!$C$37+'前提と出典'!$C$38) -> 15 | D29: =A29*('前提と出典'!$C$36*'契約別単価'!C5+'前提と出典'!$C$37*'契約別単価'!C6+'前提と出典'!$C$38*'契約別単価'!C7) -> 179.88827 | E29: =A29*('前提と出典'!$C$36*'契約別単価'!E5+'前提と出典'!$C$37*'契約別単価'!E6+'前提と出典'!$C$38*'契約別単価'!E7) -> 48373.616 | F29: =A29*('前提と出典'!$C$36*'契約別単価'!F5+'前提と出典'!$C$37*'契約別単価'!F6+'前提と出典'!$C$38*'契約別単価'!F7) -> 18984.887 | G29: =A29*('前提と出典'!$C$36*'契約別単価'!G5+'前提と出典'!$C$37*'契約別単価'!G6+'前提と出典'!$C$38*'契約別単価'!G7) -> 49762.57 | H29: =A29*('前提と出典'!$C$36*'契約別単価'!H5+'前提と出典'!$C$37*'契約別単価'!H6+'前提と出典'!$C$38*'契約別単価'!H7) -> 17270.108 | I29: =A29*('前提と出典'!$C$36*'契約別単価'!I5+'前提と出典'!$C$37*'契約別単価'!I6+'前提と出典'!$C$38*'契約別単価'!I7) -> 1054.8883 | J29: =A29*('前提と出典'!$C$36*'契約別単価'!J5+'前提と出典'!$C$37*'契約別単価'!J6+'前提と出典'!$C$38*'契約別単価'!J7) -> 2457.2386 | K29: =A29*('前提と出典'!$C$36*'契約別単価'!K5+'前提と出典'!$C$37*'契約別単価'!K6+'前提と出典'!$C$38*'契約別単価'!K7) -> 10532.588 | L29: =A29*('前提と出典'!$C$36*'契約別単価'!L5+'前提と出典'!$C$37*'契約別単価'!L6+'前提と出典'!$C$38*'契約別単価'!L7) -> 8575.6703 | M29: =IF(('前提と出典'!$C$36+'前提と出典'!$C$38)=0,0,IF(B29<=10,'前提と出典'!B73+'前提と出典'!C73,IF(B29<=100,'前提と出典'!B74+'前提と出典'!C74,IF(B29<=500,'前提と出典'!B75+'前提と出典'!C75,'前提と出典'!B76+'前提と出典'!C76)))) -> 20000 | N29: =IF(('前提と出典'!$C$37+'前提と出典'!$C$38)=0,0,IF(C29<=10,'前提と出典'!D73+'前提と出典'!E73,IF(C29<=100,'前提と出典'!D74+'前提と出典'!E74,IF(C29<=500,'前提と出典'!D75+'前提と出典'!E75,'前提と出典'!D76+'前提と出典'!E76)))) -> 34510.935 | O29: =IF('前提と出典'!$C$36+'前提と出典'!$C$38=0,0,'前提と出典'!$B$4*IF('前提と出典'!$B$20=0,MAX('前提と出典'!$B$6,D29*'前提と出典'!$B$5),'前提と出典'!$B$6+D29*'前提と出典'!$B$5)) -> 24824.581 | P29: =(E29+G29)*(1-'前提と出典'!$B$7)-I29-K29-M29-O29 -> 38191.226 | Q29: =(F29+H29)*(1-'前提と出典'!$B$7)-J29-L29-N29 -> -10594.029 | R29: =P29-E29*'前提と出典'!$E$4 -> 23679.141 | S29: =Q29-F29*'前提と出典'!$E$4 -> -16289.495 | T29: =R29+S29 -> 7389.646 | U29: =P29-E29*'前提と出典'!$E$5 -> 18841.779 | V29: =Q29-F29*'前提と出典'!$E$5 -> -18187.984 | W29: =U29+V29 -> 653.79569 | X29: =P29-E29*'前提と出典'!$E$6 -> 14004.418 | Y29: =Q29-F29*'前提と出典'!$E$6 -> -20086.472 | Z29: =X29+Y29 -> -6082.0546 | AA29: =IF(T29>=0,A29,1001) -> 25 | AB29: =IF(T29<0,A29,0) -> 0 | AC29: =IF(AND(OR('前提と出典'!$C$36+'前提と出典'!$C$38=0,R29>=0),OR('前提と出典'!$C$37+'前提と出典'!$C$38=0,S29>=0)),0,A29) -> 25 | AD29: =IF(W29>=0,A29,1001) -> 25 | AE29: =IF(W29<0,A29,0) -> 0 | AF29: =IF(AND(OR('前提と出典'!$C$36+'前提と出典'!$C$38=0,U29>=0),OR('前提と出典'!$C$37+'前提と出典'!$C$38=0,V29>=0)),0,A29) -> 25 | AG29: =IF(Z29>=0,A29,1001) -> 1001 | AH29: =IF(Z29<0,A29,0) -> 25 | AI29: =IF(AND(OR('前提と出典'!$C$36+'前提と出典'!$C$38=0,X29>=0),OR('前提と出典'!$C$37+'前提と出典'!$C$38=0,Y29>=0)),0,A29) -> 25
A30: 26 | B30: =A30*('前提と出典'!$C$36+'前提と出典'!$C$38) -> 18.2 | C30: =A30*('前提と出典'!$C$37+'前提と出典'!$C$38) -> 15.6 | D30: =A30*('前提と出典'!$C$36*'契約別単価'!C5+'前提と出典'!$C$37*'契約別単価'!C6+'前提と出典'!$C$38*'契約別単価'!C7) -> 187.0838 | E30: =A30*('前提と出典'!$C$36*'契約別単価'!E5+'前提と出典'!$C$37*'契約別単価'!E6+'前提と出典'!$C$38*'契約別単価'!E7) -> 50308.561 | F30: =A30*('前提と出典'!$C$36*'契約別単価'!F5+'前提と出典'!$C$37*'契約別単価'!F6+'前提と出典'!$C$38*'契約別単価'!F7) -> 19744.282 | G30: =A30*('前提と出典'!$C$36*'契約別単価'!G5+'前提と出典'!$C$37*'契約別単価'!G6+'前提と出典'!$C$38*'契約別単価'!G7) -> 51753.073 | H30: =A30*('前提と出典'!$C$36*'契約別単価'!H5+'前提と出典'!$C$37*'契約別単価'!H6+'前提と出典'!$C$38*'契約別単価'!H7) -> 17960.912 | I30: =A30*('前提と出典'!$C$36*'契約別単価'!I5+'前提と出典'!$C$37*'契約別単価'!I6+'前提と出典'!$C$38*'契約別単価'!I7) -> 1097.0838 | J30: =A30*('前提と出典'!$C$36*'契約別単価'!J5+'前提と出典'!$C$37*'契約別単価'!J6+'前提と出典'!$C$38*'契約別単価'!J7) -> 2555.5281 | K30: =A30*('前提と出典'!$C$36*'契約別単価'!K5+'前提と出典'!$C$37*'契約別単価'!K6+'前提と出典'!$C$38*'契約別単価'!K7) -> 10953.892 | L30: =A30*('前提と出典'!$C$36*'契約別単価'!L5+'前提と出典'!$C$37*'契約別単価'!L6+'前提と出典'!$C$38*'契約別単価'!L7) -> 8918.6971 | M30: =IF(('前提と出典'!$C$36+'前提と出典'!$C$38)=0,0,IF(B30<=10,'前提と出典'!B73+'前提と出典'!C73,IF(B30<=100,'前提と出典'!B74+'前提と出典'!C74,IF(B30<=500,'前提と出典'!B75+'前提と出典'!C75,'前提と出典'!B76+'前提と出典'!C76)))) -> 20000 | N30: =IF(('前提と出典'!$C$37+'前提と出典'!$C$38)=0,0,IF(C30<=10,'前提と出典'!D73+'前提と出典'!E73,IF(C30<=100,'前提と出典'!D74+'前提と出典'!E74,IF(C30<=500,'前提と出典'!D75+'前提と出典'!E75,'前提と出典'!D76+'前提と出典'!E76)))) -> 34510.935 | O30: =IF('前提と出典'!$C$36+'前提と出典'!$C$38=0,0,'前提と出典'!$B$4*IF('前提と出典'!$B$20=0,MAX('前提と出典'!$B$6,D30*'前提と出典'!$B$5),'前提と出典'!$B$6+D30*'前提と出典'!$B$5)) -> 25817.564 | P30: =(E30+G30)*(1-'前提と出典'!$B$7)-I30-K30-M30-O30 -> 40518.875 | Q30: =(F30+H30)*(1-'前提と出典'!$B$7)-J30-L30-N30 -> -9637.3525 | R30: =P30-E30*'前提と出典'!$E$4 -> 25426.307 | S30: =Q30-F30*'前提と出典'!$E$4 -> -15560.637 | T30: =R30+S30 -> 9865.6693 | U30: =P30-E30*'前提と出典'!$E$5 -> 20395.45 | V30: =Q30-F30*'前提と出典'!$E$5 -> -17535.066 | W30: =U30+V30 -> 2860.3849 | X30: =P30-E30*'前提と出典'!$E$6 -> 15364.594 | Y30: =Q30-F30*'前提と出典'!$E$6 -> -19509.494 | Z30: =X30+Y30 -> -4144.8994 | AA30: =IF(T30>=0,A30,1001) -> 26 | AB30: =IF(T30<0,A30,0) -> 0 | AC30: =IF(AND(OR('前提と出典'!$C$36+'前提と出典'!$C$38=0,R30>=0),OR('前提と出典'!$C$37+'前提と出典'!$C$38=0,S30>=0)),0,A30) -> 26 | AD30: =IF(W30>=0,A30,1001) -> 26 | AE30: =IF(W30<0,A30,0) -> 0 | AF30: =IF(AND(OR('前提と出典'!$C$36+'前提と出典'!$C$38=0,U30>=0),OR('前提と出典'!$C$37+'前提と出典'!$C$38=0,V30>=0)),0,A30) -> 26 | AG30: =IF(Z30>=0,A30,1001) -> 1001 | AH30: =IF(Z30<0,A30,0) -> 26 | AI30: =IF(AND(OR('前提と出典'!$C$36+'前提と出典'!$C$38=0,X30>=0),OR('前提と出典'!$C$37+'前提と出典'!$C$38=0,Y30>=0)),0,A30) -> 26
A31: 27 | B31: =A31*('前提と出典'!$C$36+'前提と出典'!$C$38) -> 18.9 | C31: =A31*('前提と出典'!$C$37+'前提と出典'!$C$38) -> 16.2 | D31: =A31*('前提と出典'!$C$36*'契約別単価'!C5+'前提と出典'!$C$37*'契約別単価'!C6+'前提と出典'!$C$38*'契約別単価'!C7) -> 194.27933 | E31: =A31*('前提と出典'!$C$36*'契約別単価'!E5+'前提と出典'!$C$37*'契約別単価'!E6+'前提と出典'!$C$38*'契約別単価'!E7) -> 52243.506 | F31: =A31*('前提と出典'!$C$36*'契約別単価'!F5+'前提と出典'!$C$37*'契約別単価'!F6+'前提と出典'!$C$38*'契約別単価'!F7) -> 20503.678 | G31: =A31*('前提と出典'!$C$36*'契約別単価'!G5+'前提と出典'!$C$37*'契約別単価'!G6+'前提と出典'!$C$38*'契約別単価'!G7) -> 53743.575 | H31: =A31*('前提と出典'!$C$36*'契約別単価'!H5+'前提と出典'!$C$37*'契約別単価'!H6+'前提と出典'!$C$38*'契約別単価'!H7) -> 18651.716 | I31: =A31*('前提と出典'!$C$36*'契約別単価'!I5+'前提と出典'!$C$37*'契約別単価'!I6+'前提と出典'!$C$38*'契約別単価'!I7) -> 1139.2793 | J31: =A31*('前提と出典'!$C$36*'契約別単価'!J5+'前提と出典'!$C$37*'契約別単価'!J6+'前提と出典'!$C$38*'契約別単価'!J7) -> 2653.8177 | K31: =A31*('前提と出典'!$C$36*'契約別単価'!K5+'前提と出典'!$C$37*'契約別単価'!K6+'前提と出典'!$C$38*'契約別単価'!K7) -> 11375.196 | L31: =A31*('前提と出典'!$C$36*'契約別単価'!L5+'前提と出典'!$C$37*'契約別単価'!L6+'前提と出典'!$C$38*'契約別単価'!L7) -> 9261.7239 | M31: =IF(('前提と出典'!$C$36+'前提と出典'!$C$38)=0,0,IF(B31<=10,'前提と出典'!B73+'前提と出典'!C73,IF(B31<=100,'前提と出典'!B74+'前提と出典'!C74,IF(B31<=500,'前提と出典'!B75+'前提と出典'!C75,'前提と出典'!B76+'前提と出典'!C76)))) -> 20000 | N31: =IF(('前提と出典'!$C$37+'前提と出典'!$C$38)=0,0,IF(C31<=10,'前提と出典'!D73+'前提と出典'!E73,IF(C31<=100,'前提と出典'!D74+'前提と出典'!E74,IF(C31<=500,'前提と出典'!D75+'前提と出典'!E75,'前提と出典'!D76+'前提と出典'!E76)))) -> 34510.935 | O31: =IF('前提と出典'!$C$36+'前提と出典'!$C$38=0,0,'前提と出典'!$B$4*IF('前提と出典'!$B$20=0,MAX('前提と出典'!$B$6,D31*'前提と出典'!$B$5),'前提と出典'!$B$6+D31*'前提と出典'!$B$5)) -> 26810.547 | P31: =(E31+G31)*(1-'前提と出典'!$B$7)-I31-K31-M31-O31 -> 42846.524 | Q31: =(F31+H31)*(1-'前提と出典'!$B$7)-J31-L31-N31 -> -8680.6763 | R31: =P31-E31*'前提と出典'!$E$4 -> 27173.472 | S31: =Q31-F31*'前提と出典'!$E$4 -> -14831.78 | T31: =R31+S31 -> 12341.692 | U31: =P31-E31*'前提と出典'!$E$5 -> 21949.122 | V31: =Q31-F31*'前提と出典'!$E$5 -> -16882.147 | W31: =U31+V31 -> 5066.9741 | X31: =P31-E31*'前提と出典'!$E$6 -> 16724.771 | Y31: =Q31-F31*'前提と出典'!$E$6 -> -18932.515 | Z31: =X31+Y31 -> -2207.7442 | AA31: =IF(T31>=0,A31,1001) -> 27 | AB31: =IF(T31<0,A31,0) -> 0 | AC31: =IF(AND(OR('前提と出典'!$C$36+'前提と出典'!$C$38=0,R31>=0),OR('前提と出典'!$C$37+'前提と出典'!$C$38=0,S31>=0)),0,A31) -> 27 | AD31: =IF(W31>=0,A31,1001) -> 27 | AE31: =IF(W31<0,A31,0) -> 0 | AF31: =IF(AND(OR('前提と出典'!$C$36+'前提と出典'!$C$38=0,U31>=0),OR('前提と出典'!$C$37+'前提と出典'!$C$38=0,V31>=0)),0,A31) -> 27 | AG31: =IF(Z31>=0,A31,1001) -> 1001 | AH31: =IF(Z31<0,A31,0) -> 27 | AI31: =IF(AND(OR('前提と出典'!$C$36+'前提と出典'!$C$38=0,X31>=0),OR('前提と出典'!$C$37+'前提と出典'!$C$38=0,Y31>=0)),0,A31) -> 27
A32: 28 | B32: =A32*('前提と出典'!$C$36+'前提と出典'!$C$38) -> 19.6 | C32: =A32*('前提と出典'!$C$37+'前提と出典'!$C$38) -> 16.8 | D32: =A32*('前提と出典'!$C$36*'契約別単価'!C5+'前提と出典'!$C$37*'契約別単価'!C6+'前提と出典'!$C$38*'契約別単価'!C7) -> 201.47486 | E32: =A32*('前提と出典'!$C$36*'契約別単価'!E5+'前提と出典'!$C$37*'契約別単価'!E6+'前提と出典'!$C$38*'契約別単価'!E7) -> 54178.45 | F32: =A32*('前提と出典'!$C$36*'契約別単価'!F5+'前提と出典'!$C$37*'契約別単価'!F6+'前提と出典'!$C$38*'契約別単価'!F7) -> 21263.073 | G32: =A32*('前提と出典'!$C$36*'契約別単価'!G5+'前提と出典'!$C$37*'契約別単価'!G6+'前提と出典'!$C$38*'契約別単価'!G7) -> 55734.078 | H32: =A32*('前提と出典'!$C$36*'契約別単価'!H5+'前提と出典'!$C$37*'契約別単価'!H6+'前提と出典'!$C$38*'契約別単価'!H7) -> 19342.52 | I32: =A32*('前提と出典'!$C$36*'契約別単価'!I5+'前提と出典'!$C$37*'契約別単価'!I6+'前提と出典'!$C$38*'契約別単価'!I7) -> 1181.4749 | J32: =A32*('前提と出典'!$C$36*'契約別単価'!J5+'前提と出典'!$C$37*'契約別単価'!J6+'前提と出典'!$C$38*'契約別単価'!J7) -> 2752.1072 | K32: =A32*('前提と出典'!$C$36*'契約別単価'!K5+'前提と出典'!$C$37*'契約別単価'!K6+'前提と出典'!$C$38*'契約別単価'!K7) -> 11796.499 | L32: =A32*('前提と出典'!$C$36*'契約別単価'!L5+'前提と出典'!$C$37*'契約別単価'!L6+'前提と出典'!$C$38*'契約別単価'!L7) -> 9604.7507 | M32: =IF(('前提と出典'!$C$36+'前提と出典'!$C$38)=0,0,IF(B32<=10,'前提と出典'!B73+'前提と出典'!C73,IF(B32<=100,'前提と出典'!B74+'前提と出典'!C74,IF(B32<=500,'前提と出典'!B75+'前提と出典'!C75,'前提と出典'!B76+'前提と出典'!C76)))) -> 20000 | N32: =IF(('前提と出典'!$C$37+'前提と出典'!$C$38)=0,0,IF(C32<=10,'前提と出典'!D73+'前提と出典'!E73,IF(C32<=100,'前提と出典'!D74+'前提と出典'!E74,IF(C32<=500,'前提と出典'!D75+'前提と出典'!E75,'前提と出典'!D76+'前提と出典'!E76)))) -> 34510.935 | O32: =IF('前提と出典'!$C$36+'前提と出典'!$C$38=0,0,'前提と出典'!$B$4*IF('前提と出典'!$B$20=0,MAX('前提と出典'!$B$6,D32*'前提と出典'!$B$5),'前提と出典'!$B$6+D32*'前提と出典'!$B$5)) -> 27803.531 | P32: =(E32+G32)*(1-'前提と出典'!$B$7)-I32-K32-M32-O32 -> 45174.173 | Q32: =(F32+H32)*(1-'前提と出典'!$B$7)-J32-L32-N32 -> -7724.0001 | R32: =P32-E32*'前提と出典'!$E$4 -> 28920.638 | S32: =Q32-F32*'前提と出典'!$E$4 -> -14102.922 | T32: =R32+S32 -> 14817.716 | U32: =P32-E32*'前提と出典'!$E$5 -> 23502.793 | V32: =Q32-F32*'前提と出典'!$E$5 -> -16229.229 | W32: =U32+V32 -> 7273.5633 | X32: =P32-E32*'前提と出典'!$E$6 -> 18084.948 | Y32: =Q32-F32*'前提と出典'!$E$6 -> -18355.537 | Z32: =X32+Y32 -> -270.58905 | AA32: =IF(T32>=0,A32,1001) -> 28 | AB32: =IF(T32<0,A32,0) -> 0 | AC32: =IF(AND(OR('前提と出典'!$C$36+'前提と出典'!$C$38=0,R32>=0),OR('前提と出典'!$C$37+'前提と出典'!$C$38=0,S32>=0)),0,A32) -> 28 | AD32: =IF(W32>=0,A32,1001) -> 28 | AE32: =IF(W32<0,A32,0) -> 0 | AF32: =IF(AND(OR('前提と出典'!$C$36+'前提と出典'!$C$38=0,U32>=0),OR('前提と出典'!$C$37+'前提と出典'!$C$38=0,V32>=0)),0,A32) -> 28 | AG32: =IF(Z32>=0,A32,1001) -> 1001 | AH32: =IF(Z32<0,A32,0) -> 28 | AI32: =IF(AND(OR('前提と出典'!$C$36+'前提と出典'!$C$38=0,X32>=0),OR('前提と出典'!$C$37+'前提と出典'!$C$38=0,Y32>=0)),0,A32) -> 28
A33: 29 | B33: =A33*('前提と出典'!$C$36+'前提と出典'!$C$38) -> 20.3 | C33: =A33*('前提と出典'!$C$37+'前提と出典'!$C$38) -> 17.4 | D33: =A33*('前提と出典'!$C$36*'契約別単価'!C5+'前提と出典'!$C$37*'契約別単価'!C6+'前提と出典'!$C$38*'契約別単価'!C7) -> 208.67039 | E33: =A33*('前提と出典'!$C$36*'契約別単価'!E5+'前提と出典'!$C$37*'契約別単価'!E6+'前提と出典'!$C$38*'契約別単価'!E7) -> 56113.395 | F33: =A33*('前提と出典'!$C$36*'契約別単価'!F5+'前提と出典'!$C$37*'契約別単価'!F6+'前提と出典'!$C$38*'契約別単価'!F7) -> 22022.469 | G33: =A33*('前提と出典'!$C$36*'契約別単価'!G5+'前提と出典'!$C$37*'契約別単価'!G6+'前提と出典'!$C$38*'契約別単価'!G7) -> 57724.581 | H33: =A33*('前提と出典'!$C$36*'契約別単価'!H5+'前提と出典'!$C$37*'契約別単価'!H6+'前提と出典'!$C$38*'契約別単価'!H7) -> 20033.325 | I33: =A33*('前提と出典'!$C$36*'契約別単価'!I5+'前提と出典'!$C$37*'契約別単価'!I6+'前提と出典'!$C$38*'契約別単価'!I7) -> 1223.6704 | J33: =A33*('前提と出典'!$C$36*'契約別単価'!J5+'前提と出典'!$C$37*'契約別単価'!J6+'前提と出典'!$C$38*'契約別単価'!J7) -> 2850.3968 | K33: =A33*('前提と出典'!$C$36*'契約別単価'!K5+'前提と出典'!$C$37*'契約別単価'!K6+'前提と出典'!$C$38*'契約別単価'!K7) -> 12217.803 | L33: =A33*('前提と出典'!$C$36*'契約別単価'!L5+'前提と出典'!$C$37*'契約別単価'!L6+'前提と出典'!$C$38*'契約別単価'!L7) -> 9947.7775 | M33: =IF(('前提と出典'!$C$36+'前提と出典'!$C$38)=0,0,IF(B33<=10,'前提と出典'!B73+'前提と出典'!C73,IF(B33<=100,'前提と出典'!B74+'前提と出典'!C74,IF(B33<=500,'前提と出典'!B75+'前提と出典'!C75,'前提と出典'!B76+'前提と出典'!C76)))) -> 20000 | N33: =IF(('前提と出典'!$C$37+'前提と出典'!$C$38)=0,0,IF(C33<=10,'前提と出典'!D73+'前提と出典'!E73,IF(C33<=100,'前提と出典'!D74+'前提と出典'!E74,IF(C33<=500,'前提と出典'!D75+'前提と出典'!E75,'前提と出典'!D76+'前提と出典'!E76)))) -> 34510.935 | O33: =IF('前提と出典'!$C$36+'前提と出典'!$C$38=0,0,'前提と出典'!$B$4*IF('前提と出典'!$B$20=0,MAX('前提と出典'!$B$6,D33*'前提と出典'!$B$5),'前提と出典'!$B$6+D33*'前提と出典'!$B$5)) -> 28796.514 | P33: =(E33+G33)*(1-'前提と出典'!$B$7)-I33-K33-M33-O33 -> 47501.822 | Q33: =(F33+H33)*(1-'前提と出典'!$B$7)-J33-L33-N33 -> -6767.3238 | R33: =P33-E33*'前提と出典'!$E$4 -> 30667.803 | S33: =Q33-F33*'前提と出典'!$E$4 -> -13374.064 | T33: =R33+S33 -> 17293.739 | U33: =P33-E33*'前提と出典'!$E$5 -> 25056.464 | V33: =Q33-F33*'前提と出典'!$E$5 -> -15576.311 | W33: =U33+V33 -> 9480.1525 | X33: =P33-E33*'前提と出典'!$E$6 -> 19445.124 | Y33: =Q33-F33*'前提と出典'!$E$6 -> -17778.558 | Z33: =X33+Y33 -> 1666.5662 | AA33: =IF(T33>=0,A33,1001) -> 29 | AB33: =IF(T33<0,A33,0) -> 0 | AC33: =IF(AND(OR('前提と出典'!$C$36+'前提と出典'!$C$38=0,R33>=0),OR('前提と出典'!$C$37+'前提と出典'!$C$38=0,S33>=0)),0,A33) -> 29 | AD33: =IF(W33>=0,A33,1001) -> 29 | AE33: =IF(W33<0,A33,0) -> 0 | AF33: =IF(AND(OR('前提と出典'!$C$36+'前提と出典'!$C$38=0,U33>=0),OR('前提と出典'!$C$37+'前提と出典'!$C$38=0,V33>=0)),0,A33) -> 29 | AG33: =IF(Z33>=0,A33,1001) -> 29 | AH33: =IF(Z33<0,A33,0) -> 0 | AI33: =IF(AND(OR('前提と出典'!$C$36+'前提と出典'!$C$38=0,X33>=0),OR('前提と出典'!$C$37+'前提と出典'!$C$38=0,Y33>=0)),0,A33) -> 29
A34: 30 | B34: =A34*('前提と出典'!$C$36+'前提と出典'!$C$38) -> 21 | C34: =A34*('前提と出典'!$C$37+'前提と出典'!$C$38) -> 18 | D34: =A34*('前提と出典'!$C$36*'契約別単価'!C5+'前提と出典'!$C$37*'契約別単価'!C6+'前提と出典'!$C$38*'契約別単価'!C7) -> 215.86592 | E34: =A34*('前提と出典'!$C$36*'契約別単価'!E5+'前提と出典'!$C$37*'契約別単価'!E6+'前提と出典'!$C$38*'契約別単価'!E7) -> 58048.34 | F34: =A34*('前提と出典'!$C$36*'契約別単価'!F5+'前提と出典'!$C$37*'契約別単価'!F6+'前提と出典'!$C$38*'契約別単価'!F7) -> 22781.864 | G34: =A34*('前提と出典'!$C$36*'契約別単価'!G5+'前提と出典'!$C$37*'契約別単価'!G6+'前提と出典'!$C$38*'契約別単価'!G7) -> 59715.084 | H34: =A34*('前提と出典'!$C$36*'契約別単価'!H5+'前提と出典'!$C$37*'契約別単価'!H6+'前提と出典'!$C$38*'契約別単価'!H7) -> 20724.129 | I34: =A34*('前提と出典'!$C$36*'契約別単価'!I5+'前提と出典'!$C$37*'契約別単価'!I6+'前提と出典'!$C$38*'契約別単価'!I7) -> 1265.8659 | J34: =A34*('前提と出典'!$C$36*'契約別単価'!J5+'前提と出典'!$C$37*'契約別単価'!J6+'前提と出典'!$C$38*'契約別単価'!J7) -> 2948.6863 | K34: =A34*('前提と出典'!$C$36*'契約別単価'!K5+'前提と出典'!$C$37*'契約別単価'!K6+'前提と出典'!$C$38*'契約別単価'!K7) -> 12639.106 | L34: =A34*('前提と出典'!$C$36*'契約別単価'!L5+'前提と出典'!$C$37*'契約別単価'!L6+'前提と出典'!$C$38*'契約別単価'!L7) -> 10290.804 | M34: =IF(('前提と出典'!$C$36+'前提と出典'!$C$38)=0,0,IF(B34<=10,'前提と出典'!B73+'前提と出典'!C73,IF(B34<=100,'前提と出典'!B74+'前提と出典'!C74,IF(B34<=500,'前提と出典'!B75+'前提と出典'!C75,'前提と出典'!B76+'前提と出典'!C76)))) -> 20000 | N34: =IF(('前提と出典'!$C$37+'前提と出典'!$C$38)=0,0,IF(C34<=10,'前提と出典'!D73+'前提と出典'!E73,IF(C34<=100,'前提と出典'!D74+'前提と出典'!E74,IF(C34<=500,'前提と出典'!D75+'前提と出典'!E75,'前提と出典'!D76+'前提と出典'!E76)))) -> 34510.935 | O34: =IF('前提と出典'!$C$36+'前提と出典'!$C$38=0,0,'前提と出典'!$B$4*IF('前提と出典'!$B$20=0,MAX('前提と出典'!$B$6,D34*'前提と出典'!$B$5),'前提と出典'!$B$6+D34*'前提と出典'!$B$5)) -> 29789.497 | P34: =(E34+G34)*(1-'前提と出典'!$B$7)-I34-K34-M34-O34 -> 49829.471 | Q34: =(F34+H34)*(1-'前提と出典'!$B$7)-J34-L34-N34 -> -5810.6476 | R34: =P34-E34*'前提と出典'!$E$4 -> 32414.969 | S34: =Q34-F34*'前提と出典'!$E$4 -> -12645.207 | T34: =R34+S34 -> 19769.762 | U34: =P34-E34*'前提と出典'!$E$5 -> 26610.135 | V34: =Q34-F34*'前提と出典'!$E$5 -> -14923.393 | W34: =U34+V34 -> 11686.742 | X34: =P34-E34*'前提と出典'!$E$6 -> 20805.301 | Y34: =Q34-F34*'前提と出典'!$E$6 -> -17201.58 | Z34: =X34+Y34 -> 3603.7213 | AA34: =IF(T34>=0,A34,1001) -> 30 | AB34: =IF(T34<0,A34,0) -> 0 | AC34: =IF(AND(OR('前提と出典'!$C$36+'前提と出典'!$C$38=0,R34>=0),OR('前提と出典'!$C$37+'前提と出典'!$C$38=0,S34>=0)),0,A34) -> 30 | AD34: =IF(W34>=0,A34,1001) -> 30 | AE34: =IF(W34<0,A34,0) -> 0 | AF34: =IF(AND(OR('前提と出典'!$C$36+'前提と出典'!$C$38=0,U34>=0),OR('前提と出典'!$C$37+'前提と出典'!$C$38=0,V34>=0)),0,A34) -> 30 | AG34: =IF(Z34>=0,A34,1001) -> 30 | AH34: =IF(Z34<0,A34,0) -> 0 | AI34: =IF(AND(OR('前提と出典'!$C$36+'前提と出典'!$C$38=0,X34>=0),OR('前提と出典'!$C$37+'前提と出典'!$C$38=0,Y34>=0)),0,A34) -> 30
A35: 31 | B35: =A35*('前提と出典'!$C$36+'前提と出典'!$C$38) -> 21.7 | C35: =A35*('前提と出典'!$C$37+'前提と出典'!$C$38) -> 18.6 | D35: =A35*('前提と出典'!$C$36*'契約別単価'!C5+'前提と出典'!$C$37*'契約別単価'!C6+'前提と出典'!$C$38*'契約別単価'!C7) -> 223.06145 | E35: =A35*('前提と出典'!$C$36*'契約別単価'!E5+'前提と出典'!$C$37*'契約別単価'!E6+'前提と出典'!$C$38*'契約別単価'!E7) -> 59983.284 | F35: =A35*('前提と出典'!$C$36*'契約別単価'!F5+'前提と出典'!$C$37*'契約別単価'!F6+'前提と出典'!$C$38*'契約別単価'!F7) -> 23541.26 | G35: =A35*('前提と出典'!$C$36*'契約別単価'!G5+'前提と出典'!$C$37*'契約別単価'!G6+'前提と出典'!$C$38*'契約別単価'!G7) -> 61705.587 | H35: =A35*('前提と出典'!$C$36*'契約別単価'!H5+'前提と出典'!$C$37*'契約別単価'!H6+'前提と出典'!$C$38*'契約別単価'!H7) -> 21414.933 | I35: =A35*('前提と出典'!$C$36*'契約別単価'!I5+'前提と出典'!$C$37*'契約別単価'!I6+'前提と出典'!$C$38*'契約別単価'!I7) -> 1308.0615 | J35: =A35*('前提と出典'!$C$36*'契約別単価'!J5+'前提と出典'!$C$37*'契約別単価'!J6+'前提と出典'!$C$38*'契約別単価'!J7) -> 3046.9759 | K35: =A35*('前提と出典'!$C$36*'契約別単価'!K5+'前提と出典'!$C$37*'契約別単価'!K6+'前提と出典'!$C$38*'契約別単価'!K7) -> 13060.41 | L35: =A35*('前提と出典'!$C$36*'契約別単価'!L5+'前提と出典'!$C$37*'契約別単価'!L6+'前提と出典'!$C$38*'契約別単価'!L7) -> 10633.831 | M35: =IF(('前提と出典'!$C$36+'前提と出典'!$C$38)=0,0,IF(B35<=10,'前提と出典'!B73+'前提と出典'!C73,IF(B35<=100,'前提と出典'!B74+'前提と出典'!C74,IF(B35<=500,'前提と出典'!B75+'前提と出典'!C75,'前提と出典'!B76+'前提と出典'!C76)))) -> 20000 | N35: =IF(('前提と出典'!$C$37+'前提と出典'!$C$38)=0,0,IF(C35<=10,'前提と出典'!D73+'前提と出典'!E73,IF(C35<=100,'前提と出典'!D74+'前提と出典'!E74,IF(C35<=500,'前提と出典'!D75+'前提と出典'!E75,'前提と出典'!D76+'前提と出典'!E76)))) -> 34510.935 | O35: =IF('前提と出典'!$C$36+'前提と出典'!$C$38=0,0,'前提と出典'!$B$4*IF('前提と出典'!$B$20=0,MAX('前提と出典'!$B$6,D35*'前提と出典'!$B$5),'前提と出典'!$B$6+D35*'前提と出典'!$B$5)) -> 30782.48 | P35: =(E35+G35)*(1-'前提と出典'!$B$7)-I35-K35-M35-O35 -> 52157.12 | Q35: =(F35+H35)*(1-'前提と出典'!$B$7)-J35-L35-N35 -> -4853.9714 | R35: =P35-E35*'前提と出典'!$E$4 -> 34162.135 | S35: =Q35-F35*'前提と出典'!$E$4 -> -11916.349 | T35: =R35+S35 -> 22245.785 | U35: =P35-E35*'前提と出典'!$E$5 -> 28163.806 | V35: =Q35-F35*'前提と出典'!$E$5 -> -14270.475 | W35: =U35+V35 -> 13893.331 | X35: =P35-E35*'前提と出典'!$E$6 -> 22165.478 | Y35: =Q35-F35*'前提と出典'!$E$6 -> -16624.601 | Z35: =X35+Y35 -> 5540.8765 | AA35: =IF(T35>=0,A35,1001) -> 31 | AB35: =IF(T35<0,A35,0) -> 0 | AC35: =IF(AND(OR('前提と出典'!$C$36+'前提と出典'!$C$38=0,R35>=0),OR('前提と出典'!$C$37+'前提と出典'!$C$38=0,S35>=0)),0,A35) -> 31 | AD35: =IF(W35>=0,A35,1001) -> 31 | AE35: =IF(W35<0,A35,0) -> 0 | AF35: =IF(AND(OR('前提と出典'!$C$36+'前提と出典'!$C$38=0,U35>=0),OR('前提と出典'!$C$37+'前提と出典'!$C$38=0,V35>=0)),0,A35) -> 31 | AG35: =IF(Z35>=0,A35,1001) -> 31 | AH35: =IF(Z35<0,A35,0) -> 0 | AI35: =IF(AND(OR('前提と出典'!$C$36+'前提と出典'!$C$38=0,X35>=0),OR('前提と出典'!$C$37+'前提と出典'!$C$38=0,Y35>=0)),0,A35) -> 31
A36: 32 | B36: =A36*('前提と出典'!$C$36+'前提と出典'!$C$38) -> 22.4 | C36: =A36*('前提と出典'!$C$37+'前提と出典'!$C$38) -> 19.2 | D36: =A36*('前提と出典'!$C$36*'契約別単価'!C5+'前提と出典'!$C$37*'契約別単価'!C6+'前提と出典'!$C$38*'契約別単価'!C7) -> 230.25698 | E36: =A36*('前提と出典'!$C$36*'契約別単価'!E5+'前提と出典'!$C$37*'契約別単価'!E6+'前提と出典'!$C$38*'契約別単価'!E7) -> 61918.229 | F36: =A36*('前提と出典'!$C$36*'契約別単価'!F5+'前提と出典'!$C$37*'契約別単価'!F6+'前提と出典'!$C$38*'契約別単価'!F7) -> 24300.655 | G36: =A36*('前提と出典'!$C$36*'契約別単価'!G5+'前提と出典'!$C$37*'契約別単価'!G6+'前提と出典'!$C$38*'契約別単価'!G7) -> 63696.089 | H36: =A36*('前提と出典'!$C$36*'契約別単価'!H5+'前提と出典'!$C$37*'契約別単価'!H6+'前提と出典'!$C$38*'契約別単価'!H7) -> 22105.738 | I36: =A36*('前提と出典'!$C$36*'契約別単価'!I5+'前提と出典'!$C$37*'契約別単価'!I6+'前提と出典'!$C$38*'契約別単価'!I7) -> 1350.257 | J36: =A36*('前提と出典'!$C$36*'契約別単価'!J5+'前提と出典'!$C$37*'契約別単価'!J6+'前提と出典'!$C$38*'契約別単価'!J7) -> 3145.2654 | K36: =A36*('前提と出典'!$C$36*'契約別単価'!K5+'前提と出典'!$C$37*'契約別単価'!K6+'前提と出典'!$C$38*'契約別単価'!K7) -> 13481.713 | L36: =A36*('前提と出典'!$C$36*'契約別単価'!L5+'前提と出典'!$C$37*'契約別単価'!L6+'前提と出典'!$C$38*'契約別単価'!L7) -> 10976.858 | M36: =IF(('前提と出典'!$C$36+'前提と出典'!$C$38)=0,0,IF(B36<=10,'前提と出典'!B73+'前提と出典'!C73,IF(B36<=100,'前提と出典'!B74+'前提と出典'!C74,IF(B36<=500,'前提と出典'!B75+'前提と出典'!C75,'前提と出典'!B76+'前提と出典'!C76)))) -> 20000 | N36: =IF(('前提と出典'!$C$37+'前提と出典'!$C$38)=0,0,IF(C36<=10,'前提と出典'!D73+'前提と出典'!E73,IF(C36<=100,'前提と出典'!D74+'前提と出典'!E74,IF(C36<=500,'前提と出典'!D75+'前提と出典'!E75,'前提と出典'!D76+'前提と出典'!E76)))) -> 34510.935 | O36: =IF('前提と出典'!$C$36+'前提と出典'!$C$38=0,0,'前提と出典'!$B$4*IF('前提と出典'!$B$20=0,MAX('前提と出典'!$B$6,D36*'前提と出典'!$B$5),'前提と出典'!$B$6+D36*'前提と出典'!$B$5)) -> 31775.464 | P36: =(E36+G36)*(1-'前提と出典'!$B$7)-I36-K36-M36-O36 -> 54484.769 | Q36: =(F36+H36)*(1-'前提と出典'!$B$7)-J36-L36-N36 -> -3897.2951 | R36: =P36-E36*'前提と出典'!$E$4 -> 35909.3 | S36: =Q36-F36*'前提と出典'!$E$4 -> -11187.492 | T36: =R36+S36 -> 24721.809 | U36: =P36-E36*'前提と出典'!$E$5 -> 29717.477 | V36: =Q36-F36*'前提と出典'!$E$5 -> -13617.557 | W36: =U36+V36 -> 16099.92 | X36: =P36-E36*'前提と出典'!$E$6 -> 23525.655 | Y36: =Q36-F36*'前提と出典'!$E$6 -> -16047.623 | Z36: =X36+Y36 -> 7478.0317 | AA36: =IF(T36>=0,A36,1001) -> 32 | AB36: =IF(T36<0,A36,0) -> 0 | AC36: =IF(AND(OR('前提と出典'!$C$36+'前提と出典'!$C$38=0,R36>=0),OR('前提と出典'!$C$37+'前提と出典'!$C$38=0,S36>=0)),0,A36) -> 32 | AD36: =IF(W36>=0,A36,1001) -> 32 | AE36: =IF(W36<0,A36,0) -> 0 | AF36: =IF(AND(OR('前提と出典'!$C$36+'前提と出典'!$C$38=0,U36>=0),OR('前提と出典'!$C$37+'前提と出典'!$C$38=0,V36>=0)),0,A36) -> 32 | AG36: =IF(Z36>=0,A36,1001) -> 32 | AH36: =IF(Z36<0,A36,0) -> 0 | AI36: =IF(AND(OR('前提と出典'!$C$36+'前提と出典'!$C$38=0,X36>=0),OR('前提と出典'!$C$37+'前提と出典'!$C$38=0,Y36>=0)),0,A36) -> 32
A37: 33 | B37: =A37*('前提と出典'!$C$36+'前提と出典'!$C$38) -> 23.1 | C37: =A37*('前提と出典'!$C$37+'前提と出典'!$C$38) -> 19.8 | D37: =A37*('前提と出典'!$C$36*'契約別単価'!C5+'前提と出典'!$C$37*'契約別単価'!C6+'前提と出典'!$C$38*'契約別単価'!C7) -> 237.45251 | E37: =A37*('前提と出典'!$C$36*'契約別単価'!E5+'前提と出典'!$C$37*'契約別単価'!E6+'前提と出典'!$C$38*'契約別単価'!E7) -> 63853.174 | F37: =A37*('前提と出典'!$C$36*'契約別単価'!F5+'前提と出典'!$C$37*'契約別単価'!F6+'前提と出典'!$C$38*'契約別単価'!F7) -> 25060.051 | G37: =A37*('前提と出典'!$C$36*'契約別単価'!G5+'前提と出典'!$C$37*'契約別単価'!G6+'前提と出典'!$C$38*'契約別単価'!G7) -> 65686.592 | H37: =A37*('前提と出典'!$C$36*'契約別単価'!H5+'前提と出典'!$C$37*'契約別単価'!H6+'前提と出典'!$C$38*'契約別単価'!H7) -> 22796.542 | I37: =A37*('前提と出典'!$C$36*'契約別単価'!I5+'前提と出典'!$C$37*'契約別単価'!I6+'前提と出典'!$C$38*'契約別単価'!I7) -> 1392.4525 | J37: =A37*('前提と出典'!$C$36*'契約別単価'!J5+'前提と出典'!$C$37*'契約別単価'!J6+'前提と出典'!$C$38*'契約別単価'!J7) -> 3243.5549 | K37: =A37*('前提と出典'!$C$36*'契約別単価'!K5+'前提と出典'!$C$37*'契約別単価'!K6+'前提と出典'!$C$38*'契約別単価'!K7) -> 13903.017 | L37: =A37*('前提と出典'!$C$36*'契約別単価'!L5+'前提と出典'!$C$37*'契約別単価'!L6+'前提と出典'!$C$38*'契約別単価'!L7) -> 11319.885 | M37: =IF(('前提と出典'!$C$36+'前提と出典'!$C$38)=0,0,IF(B37<=10,'前提と出典'!B73+'前提と出典'!C73,IF(B37<=100,'前提と出典'!B74+'前提と出典'!C74,IF(B37<=500,'前提と出典'!B75+'前提と出典'!C75,'前提と出典'!B76+'前提と出典'!C76)))) -> 20000 | N37: =IF(('前提と出典'!$C$37+'前提と出典'!$C$38)=0,0,IF(C37<=10,'前提と出典'!D73+'前提と出典'!E73,IF(C37<=100,'前提と出典'!D74+'前提と出典'!E74,IF(C37<=500,'前提と出典'!D75+'前提と出典'!E75,'前提と出典'!D76+'前提と出典'!E76)))) -> 34510.935 | O37: =IF('前提と出典'!$C$36+'前提と出典'!$C$38=0,0,'前提と出典'!$B$4*IF('前提と出典'!$B$20=0,MAX('前提と出典'!$B$6,D37*'前提と出典'!$B$5),'前提と出典'!$B$6+D37*'前提と出典'!$B$5)) -> 32768.447 | P37: =(E37+G37)*(1-'前提と出典'!$B$7)-I37-K37-M37-O37 -> 56812.418 | Q37: =(F37+H37)*(1-'前提と出典'!$B$7)-J37-L37-N37 -> -2940.6189 | R37: =P37-E37*'前提と出典'!$E$4 -> 37656.466 | S37: =Q37-F37*'前提と出典'!$E$4 -> -10458.634 | T37: =R37+S37 -> 27197.832 | U37: =P37-E37*'前提と出典'!$E$5 -> 31271.149 | V37: =Q37-F37*'前提と出典'!$E$5 -> -12964.639 | W37: =U37+V37 -> 18306.509 | X37: =P37-E37*'前提と出典'!$E$6 -> 24885.831 | Y37: =Q37-F37*'前提と出典'!$E$6 -> -15470.644 | Z37: =X37+Y37 -> 9415.1869 | AA37: =IF(T37>=0,A37,1001) -> 33 | AB37: =IF(T37<0,A37,0) -> 0 | AC37: =IF(AND(OR('前提と出典'!$C$36+'前提と出典'!$C$38=0,R37>=0),OR('前提と出典'!$C$37+'前提と出典'!$C$38=0,S37>=0)),0,A37) -> 33 | AD37: =IF(W37>=0,A37,1001) -> 33 | AE37: =IF(W37<0,A37,0) -> 0 | AF37: =IF(AND(OR('前提と出典'!$C$36+'前提と出典'!$C$38=0,U37>=0),OR('前提と出典'!$C$37+'前提と出典'!$C$38=0,V37>=0)),0,A37) -> 33 | AG37: =IF(Z37>=0,A37,1001) -> 33 | AH37: =IF(Z37<0,A37,0) -> 0 | AI37: =IF(AND(OR('前提と出典'!$C$36+'前提と出典'!$C$38=0,X37>=0),OR('前提と出典'!$C$37+'前提と出典'!$C$38=0,Y37>=0)),0,A37) -> 33
A38: 34 | B38: =A38*('前提と出典'!$C$36+'前提と出典'!$C$38) -> 23.8 | C38: =A38*('前提と出典'!$C$37+'前提と出典'!$C$38) -> 20.4 | D38: =A38*('前提と出典'!$C$36*'契約別単価'!C5+'前提と出典'!$C$37*'契約別単価'!C6+'前提と出典'!$C$38*'契約別単価'!C7) -> 244.64804 | E38: =A38*('前提と出典'!$C$36*'契約別単価'!E5+'前提と出典'!$C$37*'契約別単価'!E6+'前提と出典'!$C$38*'契約別単価'!E7) -> 65788.118 | F38: =A38*('前提と出典'!$C$36*'契約別単価'!F5+'前提と出典'!$C$37*'契約別単価'!F6+'前提と出典'!$C$38*'契約別単価'!F7) -> 25819.446 | G38: =A38*('前提と出典'!$C$36*'契約別単価'!G5+'前提と出典'!$C$37*'契約別単価'!G6+'前提と出典'!$C$38*'契約別単価'!G7) -> 67677.095 | H38: =A38*('前提と出典'!$C$36*'契約別単価'!H5+'前提と出典'!$C$37*'契約別単価'!H6+'前提と出典'!$C$38*'契約別単価'!H7) -> 23487.346 | I38: =A38*('前提と出典'!$C$36*'契約別単価'!I5+'前提と出典'!$C$37*'契約別単価'!I6+'前提と出典'!$C$38*'契約別単価'!I7) -> 1434.648 | J38: =A38*('前提と出典'!$C$36*'契約別単価'!J5+'前提と出典'!$C$37*'契約別単価'!J6+'前提と出典'!$C$38*'契約別単価'!J7) -> 3341.8445 | K38: =A38*('前提と出典'!$C$36*'契約別単価'!K5+'前提と出典'!$C$37*'契約別単価'!K6+'前提と出典'!$C$38*'契約別単価'!K7) -> 14324.32 | L38: =A38*('前提と出典'!$C$36*'契約別単価'!L5+'前提と出典'!$C$37*'契約別単価'!L6+'前提と出典'!$C$38*'契約別単価'!L7) -> 11662.912 | M38: =IF(('前提と出典'!$C$36+'前提と出典'!$C$38)=0,0,IF(B38<=10,'前提と出典'!B73+'前提と出典'!C73,IF(B38<=100,'前提と出典'!B74+'前提と出典'!C74,IF(B38<=500,'前提と出典'!B75+'前提と出典'!C75,'前提と出典'!B76+'前提と出典'!C76)))) -> 20000 | N38: =IF(('前提と出典'!$C$37+'前提と出典'!$C$38)=0,0,IF(C38<=10,'前提と出典'!D73+'前提と出典'!E73,IF(C38<=100,'前提と出典'!D74+'前提と出典'!E74,IF(C38<=500,'前提と出典'!D75+'前提と出典'!E75,'前提と出典'!D76+'前提と出典'!E76)))) -> 34510.935 | O38: =IF('前提と出典'!$C$36+'前提と出典'!$C$38=0,0,'前提と出典'!$B$4*IF('前提と出典'!$B$20=0,MAX('前提と出典'!$B$6,D38*'前提と出典'!$B$5),'前提と出典'!$B$6+D38*'前提と出典'!$B$5)) -> 33761.43 | P38: =(E38+G38)*(1-'前提と出典'!$B$7)-I38-K38-M38-O38 -> 59140.067 | Q38: =(F38+H38)*(1-'前提と出典'!$B$7)-J38-L38-N38 -> -1983.9426 | R38: =P38-E38*'前提と出典'!$E$4 -> 39403.632 | S38: =Q38-F38*'前提と出典'!$E$4 -> -9729.7765 | T38: =R38+S38 -> 29673.855 | U38: =P38-E38*'前提と出典'!$E$5 -> 32824.82 | V38: =Q38-F38*'前提と出典'!$E$5 -> -12311.721 | W38: =U38+V38 -> 20513.099 | X38: =P38-E38*'前提と出典'!$E$6 -> 26246.008 | Y38: =Q38-F38*'前提と出典'!$E$6 -> -14893.666 | Z38: =X38+Y38 -> 11352.342 | AA38: =IF(T38>=0,A38,1001) -> 34 | AB38: =IF(T38<0,A38,0) -> 0 | AC38: =IF(AND(OR('前提と出典'!$C$36+'前提と出典'!$C$38=0,R38>=0),OR('前提と出典'!$C$37+'前提と出典'!$C$38=0,S38>=0)),0,A38) -> 34 | AD38: =IF(W38>=0,A38,1001) -> 34 | AE38: =IF(W38<0,A38,0) -> 0 | AF38: =IF(AND(OR('前提と出典'!$C$36+'前提と出典'!$C$38=0,U38>=0),OR('前提と出典'!$C$37+'前提と出典'!$C$38=0,V38>=0)),0,A38) -> 34 | AG38: =IF(Z38>=0,A38,1001) -> 34 | AH38: =IF(Z38<0,A38,0) -> 0 | AI38: =IF(AND(OR('前提と出典'!$C$36+'前提と出典'!$C$38=0,X38>=0),OR('前提と出典'!$C$37+'前提と出典'!$C$38=0,Y38>=0)),0,A38) -> 34
A39: 35 | B39: =A39*('前提と出典'!$C$36+'前提と出典'!$C$38) -> 24.5 | C39: =A39*('前提と出典'!$C$37+'前提と出典'!$C$38) -> 21 | D39: =A39*('前提と出典'!$C$36*'契約別単価'!C5+'前提と出典'!$C$37*'契約別単価'!C6+'前提と出典'!$C$38*'契約別単価'!C7) -> 251.84358 | E39: =A39*('前提と出典'!$C$36*'契約別単価'!E5+'前提と出典'!$C$37*'契約別単価'!E6+'前提と出典'!$C$38*'契約別単価'!E7) -> 67723.063 | F39: =A39*('前提と出典'!$C$36*'契約別単価'!F5+'前提と出典'!$C$37*'契約別単価'!F6+'前提と出典'!$C$38*'契約別単価'!F7) -> 26578.842 | G39: =A39*('前提と出典'!$C$36*'契約別単価'!G5+'前提と出典'!$C$37*'契約別単価'!G6+'前提と出典'!$C$38*'契約別単価'!G7) -> 69667.598 | H39: =A39*('前提と出典'!$C$36*'契約別単価'!H5+'前提と出典'!$C$37*'契約別単価'!H6+'前提と出典'!$C$38*'契約別単価'!H7) -> 24178.151 | I39: =A39*('前提と出典'!$C$36*'契約別単価'!I5+'前提と出典'!$C$37*'契約別単価'!I6+'前提と出典'!$C$38*'契約別単価'!I7) -> 1476.8436 | J39: =A39*('前提と出典'!$C$36*'契約別単価'!J5+'前提と出典'!$C$37*'契約別単価'!J6+'前提と出典'!$C$38*'契約別単価'!J7) -> 3440.134 | K39: =A39*('前提と出典'!$C$36*'契約別単価'!K5+'前提と出典'!$C$37*'契約別単価'!K6+'前提と出典'!$C$38*'契約別単価'!K7) -> 14745.624 | L39: =A39*('前提と出典'!$C$36*'契約別単価'!L5+'前提と出典'!$C$37*'契約別単価'!L6+'前提と出典'!$C$38*'契約別単価'!L7) -> 12005.938 | M39: =IF(('前提と出典'!$C$36+'前提と出典'!$C$38)=0,0,IF(B39<=10,'前提と出典'!B73+'前提と出典'!C73,IF(B39<=100,'前提と出典'!B74+'前提と出典'!C74,IF(B39<=500,'前提と出典'!B75+'前提と出典'!C75,'前提と出典'!B76+'前提と出典'!C76)))) -> 20000 | N39: =IF(('前提と出典'!$C$37+'前提と出典'!$C$38)=0,0,IF(C39<=10,'前提と出典'!D73+'前提と出典'!E73,IF(C39<=100,'前提と出典'!D74+'前提と出典'!E74,IF(C39<=500,'前提と出典'!D75+'前提と出典'!E75,'前提と出典'!D76+'前提と出典'!E76)))) -> 34510.935 | O39: =IF('前提と出典'!$C$36+'前提と出典'!$C$38=0,0,'前提と出典'!$B$4*IF('前提と出典'!$B$20=0,MAX('前提と出典'!$B$6,D39*'前提と出典'!$B$5),'前提と出典'!$B$6+D39*'前提と出典'!$B$5)) -> 34754.413 | P39: =(E39+G39)*(1-'前提と出典'!$B$7)-I39-K39-M39-O39 -> 61467.716 | Q39: =(F39+H39)*(1-'前提と出典'!$B$7)-J39-L39-N39 -> -1027.2664 | R39: =P39-E39*'前提と出典'!$E$4 -> 41150.797 | S39: =Q39-F39*'前提と出典'!$E$4 -> -9000.9189 | T39: =R39+S39 -> 32149.878 | U39: =P39-E39*'前提と出典'!$E$5 -> 34378.491 | V39: =Q39-F39*'前提と出典'!$E$5 -> -11658.803 | W39: =U39+V39 -> 22719.688 | X39: =P39-E39*'前提と出典'!$E$6 -> 27606.185 | Y39: =Q39-F39*'前提と出典'!$E$6 -> -14316.687 | Z39: =X39+Y39 -> 13289.497 | AA39: =IF(T39>=0,A39,1001) -> 35 | AB39: =IF(T39<0,A39,0) -> 0 | AC39: =IF(AND(OR('前提と出典'!$C$36+'前提と出典'!$C$38=0,R39>=0),OR('前提と出典'!$C$37+'前提と出典'!$C$38=0,S39>=0)),0,A39) -> 35 | AD39: =IF(W39>=0,A39,1001) -> 35 | AE39: =IF(W39<0,A39,0) -> 0 | AF39: =IF(AND(OR('前提と出典'!$C$36+'前提と出典'!$C$38=0,U39>=0),OR('前提と出典'!$C$37+'前提と出典'!$C$38=0,V39>=0)),0,A39) -> 35 | AG39: =IF(Z39>=0,A39,1001) -> 35 | AH39: =IF(Z39<0,A39,0) -> 0 | AI39: =IF(AND(OR('前提と出典'!$C$36+'前提と出典'!$C$38=0,X39>=0),OR('前提と出典'!$C$37+'前提と出典'!$C$38=0,Y39>=0)),0,A39) -> 35
A40: 36 | B40: =A40*('前提と出典'!$C$36+'前提と出典'!$C$38) -> 25.2 | C40: =A40*('前提と出典'!$C$37+'前提と出典'!$C$38) -> 21.6 | D40: =A40*('前提と出典'!$C$36*'契約別単価'!C5+'前提と出典'!$C$37*'契約別単価'!C6+'前提と出典'!$C$38*'契約別単価'!C7) -> 259.03911 | E40: =A40*('前提と出典'!$C$36*'契約別単価'!E5+'前提と出典'!$C$37*'契約別単価'!E6+'前提と出典'!$C$38*'契約別単価'!E7) -> 69658.008 | F40: =A40*('前提と出典'!$C$36*'契約別単価'!F5+'前提と出典'!$C$37*'契約別単価'!F6+'前提と出典'!$C$38*'契約別単価'!F7) -> 27338.237 | G40: =A40*('前提と出典'!$C$36*'契約別単価'!G5+'前提と出典'!$C$37*'契約別単価'!G6+'前提と出典'!$C$38*'契約別単価'!G7) -> 71658.101 | H40: =A40*('前提と出典'!$C$36*'契約別単価'!H5+'前提と出典'!$C$37*'契約別単価'!H6+'前提と出典'!$C$38*'契約別単価'!H7) -> 24868.955 | I40: =A40*('前提と出典'!$C$36*'契約別単価'!I5+'前提と出典'!$C$37*'契約別単価'!I6+'前提と出典'!$C$38*'契約別単価'!I7) -> 1519.0391 | J40: =A40*('前提と出典'!$C$36*'契約別単価'!J5+'前提と出典'!$C$37*'契約別単価'!J6+'前提と出典'!$C$38*'契約別単価'!J7) -> 3538.4236 | K40: =A40*('前提と出典'!$C$36*'契約別単価'!K5+'前提と出典'!$C$37*'契約別単価'!K6+'前提と出典'!$C$38*'契約別単価'!K7) -> 15166.927 | L40: =A40*('前提と出典'!$C$36*'契約別単価'!L5+'前提と出典'!$C$37*'契約別単価'!L6+'前提と出典'!$C$38*'契約別単価'!L7) -> 12348.965 | M40: =IF(('前提と出典'!$C$36+'前提と出典'!$C$38)=0,0,IF(B40<=10,'前提と出典'!B73+'前提と出典'!C73,IF(B40<=100,'前提と出典'!B74+'前提と出典'!C74,IF(B40<=500,'前提と出典'!B75+'前提と出典'!C75,'前提と出典'!B76+'前提と出典'!C76)))) -> 20000 | N40: =IF(('前提と出典'!$C$37+'前提と出典'!$C$38)=0,0,IF(C40<=10,'前提と出典'!D73+'前提と出典'!E73,IF(C40<=100,'前提と出典'!D74+'前提と出典'!E74,IF(C40<=500,'前提と出典'!D75+'前提と出典'!E75,'前提と出典'!D76+'前提と出典'!E76)))) -> 34510.935 | O40: =IF('前提と出典'!$C$36+'前提と出典'!$C$38=0,0,'前提と出典'!$B$4*IF('前提と出典'!$B$20=0,MAX('前提と出典'!$B$6,D40*'前提と出典'!$B$5),'前提と出典'!$B$6+D40*'前提と出典'!$B$5)) -> 35747.397 | P40: =(E40+G40)*(1-'前提と出典'!$B$7)-I40-K40-M40-O40 -> 63795.365 | Q40: =(F40+H40)*(1-'前提と出典'!$B$7)-J40-L40-N40 -> -70.590177 | R40: =P40-E40*'前提と出典'!$E$4 -> 42897.963 | S40: =Q40-F40*'前提と出典'!$E$4 -> -8272.0614 | T40: =R40+S40 -> 34625.902 | U40: =P40-E40*'前提と出典'!$E$5 -> 35932.162 | V40: =Q40-F40*'前提と出典'!$E$5 -> -11005.885 | W40: =U40+V40 -> 24926.277 | X40: =P40-E40*'前提と出典'!$E$6 -> 28966.361 | Y40: =Q40-F40*'前提と出典'!$E$6 -> -13739.709 | Z40: =X40+Y40 -> 15226.653 | AA40: =IF(T40>=0,A40,1001) -> 36 | AB40: =IF(T40<0,A40,0) -> 0 | AC40: =IF(AND(OR('前提と出典'!$C$36+'前提と出典'!$C$38=0,R40>=0),OR('前提と出典'!$C$37+'前提と出典'!$C$38=0,S40>=0)),0,A40) -> 36 | AD40: =IF(W40>=0,A40,1001) -> 36 | AE40: =IF(W40<0,A40,0) -> 0 | AF40: =IF(AND(OR('前提と出典'!$C$36+'前提と出典'!$C$38=0,U40>=0),OR('前提と出典'!$C$37+'前提と出典'!$C$38=0,V40>=0)),0,A40) -> 36 | AG40: =IF(Z40>=0,A40,1001) -> 36 | AH40: =IF(Z40<0,A40,0) -> 0 | AI40: =IF(AND(OR('前提と出典'!$C$36+'前提と出典'!$C$38=0,X40>=0),OR('前提と出典'!$C$37+'前提と出典'!$C$38=0,Y40>=0)),0,A40) -> 36
A41: 37 | B41: =A41*('前提と出典'!$C$36+'前提と出典'!$C$38) -> 25.9 | C41: =A41*('前提と出典'!$C$37+'前提と出典'!$C$38) -> 22.2 | D41: =A41*('前提と出典'!$C$36*'契約別単価'!C5+'前提と出典'!$C$37*'契約別単価'!C6+'前提と出典'!$C$38*'契約別単価'!C7) -> 266.23464 | E41: =A41*('前提と出典'!$C$36*'契約別単価'!E5+'前提と出典'!$C$37*'契約別単価'!E6+'前提と出典'!$C$38*'契約別単価'!E7) -> 71592.952 | F41: =A41*('前提と出典'!$C$36*'契約別単価'!F5+'前提と出典'!$C$37*'契約別単価'!F6+'前提と出典'!$C$38*'契約別単価'!F7) -> 28097.633 | G41: =A41*('前提と出典'!$C$36*'契約別単価'!G5+'前提と出典'!$C$37*'契約別単価'!G6+'前提と出典'!$C$38*'契約別単価'!G7) -> 73648.603 | H41: =A41*('前提と出典'!$C$36*'契約別単価'!H5+'前提と出典'!$C$37*'契約別単価'!H6+'前提と出典'!$C$38*'契約別単価'!H7) -> 25559.759 | I41: =A41*('前提と出典'!$C$36*'契約別単価'!I5+'前提と出典'!$C$37*'契約別単価'!I6+'前提と出典'!$C$38*'契約別単価'!I7) -> 1561.2346 | J41: =A41*('前提と出典'!$C$36*'契約別単価'!J5+'前提と出典'!$C$37*'契約別単価'!J6+'前提と出典'!$C$38*'契約別単価'!J7) -> 3636.7131 | K41: =A41*('前提と出典'!$C$36*'契約別単価'!K5+'前提と出典'!$C$37*'契約別単価'!K6+'前提と出典'!$C$38*'契約別単価'!K7) -> 15588.231 | L41: =A41*('前提と出典'!$C$36*'契約別単価'!L5+'前提と出典'!$C$37*'契約別単価'!L6+'前提と出典'!$C$38*'契約別単価'!L7) -> 12691.992 | M41: =IF(('前提と出典'!$C$36+'前提と出典'!$C$38)=0,0,IF(B41<=10,'前提と出典'!B73+'前提と出典'!C73,IF(B41<=100,'前提と出典'!B74+'前提と出典'!C74,IF(B41<=500,'前提と出典'!B75+'前提と出典'!C75,'前提と出典'!B76+'前提と出典'!C76)))) -> 20000 | N41: =IF(('前提と出典'!$C$37+'前提と出典'!$C$38)=0,0,IF(C41<=10,'前提と出典'!D73+'前提と出典'!E73,IF(C41<=100,'前提と出典'!D74+'前提と出典'!E74,IF(C41<=500,'前提と出典'!D75+'前提と出典'!E75,'前提と出典'!D76+'前提と出典'!E76)))) -> 34510.935 | O41: =IF('前提と出典'!$C$36+'前提と出典'!$C$38=0,0,'前提と出典'!$B$4*IF('前提と出典'!$B$20=0,MAX('前提と出典'!$B$6,D41*'前提と出典'!$B$5),'前提と出典'!$B$6+D41*'前提と出典'!$B$5)) -> 36740.38 | P41: =(E41+G41)*(1-'前提と出典'!$B$7)-I41-K41-M41-O41 -> 66123.014 | Q41: =(F41+H41)*(1-'前提と出典'!$B$7)-J41-L41-N41 -> 886.08606 | R41: =P41-E41*'前提と出典'!$E$4 -> 44645.129 | S41: =Q41-F41*'前提と出典'!$E$4 -> -7543.2038 | T41: =R41+S41 -> 37101.925 | U41: =P41-E41*'前提と出典'!$E$5 -> 37485.833 | V41: =Q41-F41*'前提と出典'!$E$5 -> -10352.967 | W41: =U41+V41 -> 27132.866 | X41: =P41-E41*'前提と出典'!$E$6 -> 30326.538 | Y41: =Q41-F41*'前提と出典'!$E$6 -> -13162.73 | Z41: =X41+Y41 -> 17163.808 | AA41: =IF(T41>=0,A41,1001) -> 37 | AB41: =IF(T41<0,A41,0) -> 0 | AC41: =IF(AND(OR('前提と出典'!$C$36+'前提と出典'!$C$38=0,R41>=0),OR('前提と出典'!$C$37+'前提と出典'!$C$38=0,S41>=0)),0,A41) -> 37 | AD41: =IF(W41>=0,A41,1001) -> 37 | AE41: =IF(W41<0,A41,0) -> 0 | AF41: =IF(AND(OR('前提と出典'!$C$36+'前提と出典'!$C$38=0,U41>=0),OR('前提と出典'!$C$37+'前提と出典'!$C$38=0,V41>=0)),0,A41) -> 37 | AG41: =IF(Z41>=0,A41,1001) -> 37 | AH41: =IF(Z41<0,A41,0) -> 0 | AI41: =IF(AND(OR('前提と出典'!$C$36+'前提と出典'!$C$38=0,X41>=0),OR('前提と出典'!$C$37+'前提と出典'!$C$38=0,Y41>=0)),0,A41) -> 37
A42: 38 | B42: =A42*('前提と出典'!$C$36+'前提と出典'!$C$38) -> 26.6 | C42: =A42*('前提と出典'!$C$37+'前提と出典'!$C$38) -> 22.8 | D42: =A42*('前提と出典'!$C$36*'契約別単価'!C5+'前提と出典'!$C$37*'契約別単価'!C6+'前提と出典'!$C$38*'契約別単価'!C7) -> 273.43017 | E42: =A42*('前提と出典'!$C$36*'契約別単価'!E5+'前提と出典'!$C$37*'契約別単価'!E6+'前提と出典'!$C$38*'契約別単価'!E7) -> 73527.897 | F42: =A42*('前提と出典'!$C$36*'契約別単価'!F5+'前提と出典'!$C$37*'契約別単価'!F6+'前提と出典'!$C$38*'契約別単価'!F7) -> 28857.028 | G42: =A42*('前提と出典'!$C$36*'契約別単価'!G5+'前提と出典'!$C$37*'契約別単価'!G6+'前提と出典'!$C$38*'契約別単価'!G7) -> 75639.106 | H42: =A42*('前提と出典'!$C$36*'契約別単価'!H5+'前提と出典'!$C$37*'契約別単価'!H6+'前提と出典'!$C$38*'契約別単価'!H7) -> 26250.563 | I42: =A42*('前提と出典'!$C$36*'契約別単価'!I5+'前提と出典'!$C$37*'契約別単価'!I6+'前提と出典'!$C$38*'契約別単価'!I7) -> 1603.4302 | J42: =A42*('前提と出典'!$C$36*'契約別単価'!J5+'前提と出典'!$C$37*'契約別単価'!J6+'前提と出典'!$C$38*'契約別単価'!J7) -> 3735.0027 | K42: =A42*('前提と出典'!$C$36*'契約別単価'!K5+'前提と出典'!$C$37*'契約別単価'!K6+'前提と出典'!$C$38*'契約別単価'!K7) -> 16009.534 | L42: =A42*('前提と出典'!$C$36*'契約別単価'!L5+'前提と出典'!$C$37*'契約別単価'!L6+'前提と出典'!$C$38*'契約別単価'!L7) -> 13035.019 | M42: =IF(('前提と出典'!$C$36+'前提と出典'!$C$38)=0,0,IF(B42<=10,'前提と出典'!B73+'前提と出典'!C73,IF(B42<=100,'前提と出典'!B74+'前提と出典'!C74,IF(B42<=500,'前提と出典'!B75+'前提と出典'!C75,'前提と出典'!B76+'前提と出典'!C76)))) -> 20000 | N42: =IF(('前提と出典'!$C$37+'前提と出典'!$C$38)=0,0,IF(C42<=10,'前提と出典'!D73+'前提と出典'!E73,IF(C42<=100,'前提と出典'!D74+'前提と出典'!E74,IF(C42<=500,'前提と出典'!D75+'前提と出典'!E75,'前提と出典'!D76+'前提と出典'!E76)))) -> 34510.935 | O42: =IF('前提と出典'!$C$36+'前提と出典'!$C$38=0,0,'前提と出典'!$B$4*IF('前提と出典'!$B$20=0,MAX('前提と出典'!$B$6,D42*'前提と出典'!$B$5),'前提と出典'!$B$6+D42*'前提と出典'!$B$5)) -> 37733.363 | P42: =(E42+G42)*(1-'前提と出典'!$B$7)-I42-K42-M42-O42 -> 68450.663 | Q42: =(F42+H42)*(1-'前提と出典'!$B$7)-J42-L42-N42 -> 1842.7623 | R42: =P42-E42*'前提と出典'!$E$4 -> 46392.294 | S42: =Q42-F42*'前提と出典'!$E$4 -> -6814.3462 | T42: =R42+S42 -> 39577.948 | U42: =P42-E42*'前提と出典'!$E$5 -> 39039.504 | V42: =Q42-F42*'前提と出典'!$E$5 -> -9700.049 | W42: =U42+V42 -> 29339.455 | X42: =P42-E42*'前提と出典'!$E$6 -> 31686.715 | Y42: =Q42-F42*'前提と出典'!$E$6 -> -12585.752 | Z42: =X42+Y42 -> 19100.963 | AA42: =IF(T42>=0,A42,1001) -> 38 | AB42: =IF(T42<0,A42,0) -> 0 | AC42: =IF(AND(OR('前提と出典'!$C$36+'前提と出典'!$C$38=0,R42>=0),OR('前提と出典'!$C$37+'前提と出典'!$C$38=0,S42>=0)),0,A42) -> 38 | AD42: =IF(W42>=0,A42,1001) -> 38 | AE42: =IF(W42<0,A42,0) -> 0 | AF42: =IF(AND(OR('前提と出典'!$C$36+'前提と出典'!$C$38=0,U42>=0),OR('前提と出典'!$C$37+'前提と出典'!$C$38=0,V42>=0)),0,A42) -> 38 | AG42: =IF(Z42>=0,A42,1001) -> 38 | AH42: =IF(Z42<0,A42,0) -> 0 | AI42: =IF(AND(OR('前提と出典'!$C$36+'前提と出典'!$C$38=0,X42>=0),OR('前提と出典'!$C$37+'前提と出典'!$C$38=0,Y42>=0)),0,A42) -> 38
A43: 39 | B43: =A43*('前提と出典'!$C$36+'前提と出典'!$C$38) -> 27.3 | C43: =A43*('前提と出典'!$C$37+'前提と出典'!$C$38) -> 23.4 | D43: =A43*('前提と出典'!$C$36*'契約別単価'!C5+'前提と出典'!$C$37*'契約別単価'!C6+'前提と出典'!$C$38*'契約別単価'!C7) -> 280.6257 | E43: =A43*('前提と出典'!$C$36*'契約別単価'!E5+'前提と出典'!$C$37*'契約別単価'!E6+'前提と出典'!$C$38*'契約別単価'!E7) -> 75462.842 | F43: =A43*('前提と出典'!$C$36*'契約別単価'!F5+'前提と出典'!$C$37*'契約別単価'!F6+'前提と出典'!$C$38*'契約別単価'!F7) -> 29616.424 | G43: =A43*('前提と出典'!$C$36*'契約別単価'!G5+'前提と出典'!$C$37*'契約別単価'!G6+'前提と出典'!$C$38*'契約別単価'!G7) -> 77629.609 | H43: =A43*('前提と出典'!$C$36*'契約別単価'!H5+'前提と出典'!$C$37*'契約別単価'!H6+'前提と出典'!$C$38*'契約別単価'!H7) -> 26941.368 | I43: =A43*('前提と出典'!$C$36*'契約別単価'!I5+'前提と出典'!$C$37*'契約別単価'!I6+'前提と出典'!$C$38*'契約別単価'!I7) -> 1645.6257 | J43: =A43*('前提と出典'!$C$36*'契約別単価'!J5+'前提と出典'!$C$37*'契約別単価'!J6+'前提と出典'!$C$38*'契約別単価'!J7) -> 3833.2922 | K43: =A43*('前提と出典'!$C$36*'契約別単価'!K5+'前提と出典'!$C$37*'契約別単価'!K6+'前提と出典'!$C$38*'契約別単価'!K7) -> 16430.838 | L43: =A43*('前提と出典'!$C$36*'契約別単価'!L5+'前提と出典'!$C$37*'契約別単価'!L6+'前提と出典'!$C$38*'契約別単価'!L7) -> 13378.046 | M43: =IF(('前提と出典'!$C$36+'前提と出典'!$C$38)=0,0,IF(B43<=10,'前提と出典'!B73+'前提と出典'!C73,IF(B43<=100,'前提と出典'!B74+'前提と出典'!C74,IF(B43<=500,'前提と出典'!B75+'前提と出典'!C75,'前提と出典'!B76+'前提と出典'!C76)))) -> 20000 | N43: =IF(('前提と出典'!$C$37+'前提と出典'!$C$38)=0,0,IF(C43<=10,'前提と出典'!D73+'前提と出典'!E73,IF(C43<=100,'前提と出典'!D74+'前提と出典'!E74,IF(C43<=500,'前提と出典'!D75+'前提と出典'!E75,'前提と出典'!D76+'前提と出典'!E76)))) -> 34510.935 | O43: =IF('前提と出典'!$C$36+'前提と出典'!$C$38=0,0,'前提と出典'!$B$4*IF('前提と出典'!$B$20=0,MAX('前提と出典'!$B$6,D43*'前提と出典'!$B$5),'前提と出典'!$B$6+D43*'前提と出典'!$B$5)) -> 38726.346 | P43: =(E43+G43)*(1-'前提と出典'!$B$7)-I43-K43-M43-O43 -> 70778.312 | Q43: =(F43+H43)*(1-'前提と出典'!$B$7)-J43-L43-N43 -> 2799.4385 | R43: =P43-E43*'前提と出典'!$E$4 -> 48139.46 | S43: =Q43-F43*'前提と出典'!$E$4 -> -6085.4886 | T43: =R43+S43 -> 42053.971 | U43: =P43-E43*'前提と出典'!$E$5 -> 40593.176 | V43: =Q43-F43*'前提と出典'!$E$5 -> -9047.131 | W43: =U43+V43 -> 31546.045 | X43: =P43-E43*'前提と出典'!$E$6 -> 33046.891 | Y43: =Q43-F43*'前提と出典'!$E$6 -> -12008.773 | Z43: =X43+Y43 -> 21038.118 | AA43: =IF(T43>=0,A43,1001) -> 39 | AB43: =IF(T43<0,A43,0) -> 0 | AC43: =IF(AND(OR('前提と出典'!$C$36+'前提と出典'!$C$38=0,R43>=0),OR('前提と出典'!$C$37+'前提と出典'!$C$38=0,S43>=0)),0,A43) -> 39 | AD43: =IF(W43>=0,A43,1001) -> 39 | AE43: =IF(W43<0,A43,0) -> 0 | AF43: =IF(AND(OR('前提と出典'!$C$36+'前提と出典'!$C$38=0,U43>=0),OR('前提と出典'!$C$37+'前提と出典'!$C$38=0,V43>=0)),0,A43) -> 39 | AG43: =IF(Z43>=0,A43,1001) -> 39 | AH43: =IF(Z43<0,A43,0) -> 0 | AI43: =IF(AND(OR('前提と出典'!$C$36+'前提と出典'!$C$38=0,X43>=0),OR('前提と出典'!$C$37+'前提と出典'!$C$38=0,Y43>=0)),0,A43) -> 39
A44: 40 | B44: =A44*('前提と出典'!$C$36+'前提と出典'!$C$38) -> 28 | C44: =A44*('前提と出典'!$C$37+'前提と出典'!$C$38) -> 24 | D44: =A44*('前提と出典'!$C$36*'契約別単価'!C5+'前提と出典'!$C$37*'契約別単価'!C6+'前提と出典'!$C$38*'契約別単価'!C7) -> 287.82123 | E44: =A44*('前提と出典'!$C$36*'契約別単価'!E5+'前提と出典'!$C$37*'契約別単価'!E6+'前提と出典'!$C$38*'契約別単価'!E7) -> 77397.786 | F44: =A44*('前提と出典'!$C$36*'契約別単価'!F5+'前提と出典'!$C$37*'契約別単価'!F6+'前提と出典'!$C$38*'契約別単価'!F7) -> 30375.819 | G44: =A44*('前提と出典'!$C$36*'契約別単価'!G5+'前提と出典'!$C$37*'契約別単価'!G6+'前提と出典'!$C$38*'契約別単価'!G7) -> 79620.112 | H44: =A44*('前提と出典'!$C$36*'契約別単価'!H5+'前提と出典'!$C$37*'契約別単価'!H6+'前提と出典'!$C$38*'契約別単価'!H7) -> 27632.172 | I44: =A44*('前提と出典'!$C$36*'契約別単価'!I5+'前提と出典'!$C$37*'契約別単価'!I6+'前提と出典'!$C$38*'契約別単価'!I7) -> 1687.8212 | J44: =A44*('前提と出典'!$C$36*'契約別単価'!J5+'前提と出典'!$C$37*'契約別単価'!J6+'前提と出典'!$C$38*'契約別単価'!J7) -> 3931.5817 | K44: =A44*('前提と出典'!$C$36*'契約別単価'!K5+'前提と出典'!$C$37*'契約別単価'!K6+'前提と出典'!$C$38*'契約別単価'!K7) -> 16852.142 | L44: =A44*('前提と出典'!$C$36*'契約別単価'!L5+'前提と出典'!$C$37*'契約別単価'!L6+'前提と出典'!$C$38*'契約別単価'!L7) -> 13721.072 | M44: =IF(('前提と出典'!$C$36+'前提と出典'!$C$38)=0,0,IF(B44<=10,'前提と出典'!B73+'前提と出典'!C73,IF(B44<=100,'前提と出典'!B74+'前提と出典'!C74,IF(B44<=500,'前提と出典'!B75+'前提と出典'!C75,'前提と出典'!B76+'前提と出典'!C76)))) -> 20000 | N44: =IF(('前提と出典'!$C$37+'前提と出典'!$C$38)=0,0,IF(C44<=10,'前提と出典'!D73+'前提と出典'!E73,IF(C44<=100,'前提と出典'!D74+'前提と出典'!E74,IF(C44<=500,'前提と出典'!D75+'前提と出典'!E75,'前提と出典'!D76+'前提と出典'!E76)))) -> 34510.935 | O44: =IF('前提と出典'!$C$36+'前提と出典'!$C$38=0,0,'前提と出典'!$B$4*IF('前提と出典'!$B$20=0,MAX('前提と出典'!$B$6,D44*'前提と出典'!$B$5),'前提と出典'!$B$6+D44*'前提と出典'!$B$5)) -> 39719.33 | P44: =(E44+G44)*(1-'前提と出典'!$B$7)-I44-K44-M44-O44 -> 73105.961 | Q44: =(F44+H44)*(1-'前提と出典'!$B$7)-J44-L44-N44 -> 3756.1148 | R44: =P44-E44*'前提と出典'!$E$4 -> 49886.625 | S44: =Q44-F44*'前提と出典'!$E$4 -> -5356.631 | T44: =R44+S44 -> 44529.994 | U44: =P44-E44*'前提と出典'!$E$5 -> 42146.847 | V44: =Q44-F44*'前提と出典'!$E$5 -> -8394.2129 | W44: =U44+V44 -> 33752.634 | X44: =P44-E44*'前提と出典'!$E$6 -> 34407.068 | Y44: =Q44-F44*'前提と出典'!$E$6 -> -11431.795 | Z44: =X44+Y44 -> 22975.273 | AA44: =IF(T44>=0,A44,1001) -> 40 | AB44: =IF(T44<0,A44,0) -> 0 | AC44: =IF(AND(OR('前提と出典'!$C$36+'前提と出典'!$C$38=0,R44>=0),OR('前提と出典'!$C$37+'前提と出典'!$C$38=0,S44>=0)),0,A44) -> 40 | AD44: =IF(W44>=0,A44,1001) -> 40 | AE44: =IF(W44<0,A44,0) -> 0 | AF44: =IF(AND(OR('前提と出典'!$C$36+'前提と出典'!$C$38=0,U44>=0),OR('前提と出典'!$C$37+'前提と出典'!$C$38=0,V44>=0)),0,A44) -> 40 | AG44: =IF(Z44>=0,A44,1001) -> 40 | AH44: =IF(Z44<0,A44,0) -> 0 | AI44: =IF(AND(OR('前提と出典'!$C$36+'前提と出典'!$C$38=0,X44>=0),OR('前提と出典'!$C$37+'前提と出典'!$C$38=0,Y44>=0)),0,A44) -> 40
A45: 41 | B45: =A45*('前提と出典'!$C$36+'前提と出典'!$C$38) -> 28.7 | C45: =A45*('前提と出典'!$C$37+'前提と出典'!$C$38) -> 24.6 | D45: =A45*('前提と出典'!$C$36*'契約別単価'!C5+'前提と出典'!$C$37*'契約別単価'!C6+'前提と出典'!$C$38*'契約別単価'!C7) -> 295.01676 | E45: =A45*('前提と出典'!$C$36*'契約別単価'!E5+'前提と出典'!$C$37*'契約別単価'!E6+'前提と出典'!$C$38*'契約別単価'!E7) -> 79332.731 | F45: =A45*('前提と出典'!$C$36*'契約別単価'!F5+'前提と出典'!$C$37*'契約別単価'!F6+'前提と出典'!$C$38*'契約別単価'!F7) -> 31135.215 | G45: =A45*('前提と出典'!$C$36*'契約別単価'!G5+'前提と出典'!$C$37*'契約別単価'!G6+'前提と出典'!$C$38*'契約別単価'!G7) -> 81610.615 | H45: =A45*('前提と出典'!$C$36*'契約別単価'!H5+'前提と出典'!$C$37*'契約別単価'!H6+'前提と出典'!$C$38*'契約別単価'!H7) -> 28322.976 | I45: =A45*('前提と出典'!$C$36*'契約別単価'!I5+'前提と出典'!$C$37*'契約別単価'!I6+'前提と出典'!$C$38*'契約別単価'!I7) -> 1730.0168 | J45: =A45*('前提と出典'!$C$36*'契約別単価'!J5+'前提と出典'!$C$37*'契約別単価'!J6+'前提と出典'!$C$38*'契約別単価'!J7) -> 4029.8713 | K45: =A45*('前提と出典'!$C$36*'契約別単価'!K5+'前提と出典'!$C$37*'契約別単価'!K6+'前提と出典'!$C$38*'契約別単価'!K7) -> 17273.445 | L45: =A45*('前提と出典'!$C$36*'契約別単価'!L5+'前提と出典'!$C$37*'契約別単価'!L6+'前提と出典'!$C$38*'契約別単価'!L7) -> 14064.099 | M45: =IF(('前提と出典'!$C$36+'前提と出典'!$C$38)=0,0,IF(B45<=10,'前提と出典'!B73+'前提と出典'!C73,IF(B45<=100,'前提と出典'!B74+'前提と出典'!C74,IF(B45<=500,'前提と出典'!B75+'前提と出典'!C75,'前提と出典'!B76+'前提と出典'!C76)))) -> 20000 | N45: =IF(('前提と出典'!$C$37+'前提と出典'!$C$38)=0,0,IF(C45<=10,'前提と出典'!D73+'前提と出典'!E73,IF(C45<=100,'前提と出典'!D74+'前提と出典'!E74,IF(C45<=500,'前提と出典'!D75+'前提と出典'!E75,'前提と出典'!D76+'前提と出典'!E76)))) -> 34510.935 | O45: =IF('前提と出典'!$C$36+'前提と出典'!$C$38=0,0,'前提と出典'!$B$4*IF('前提と出典'!$B$20=0,MAX('前提と出典'!$B$6,D45*'前提と出典'!$B$5),'前提と出典'!$B$6+D45*'前提と出典'!$B$5)) -> 40712.313 | P45: =(E45+G45)*(1-'前提と出典'!$B$7)-I45-K45-M45-O45 -> 75433.61 | Q45: =(F45+H45)*(1-'前提と出典'!$B$7)-J45-L45-N45 -> 4712.791 | R45: =P45-E45*'前提と出典'!$E$4 -> 51633.791 | S45: =Q45-F45*'前提と出典'!$E$4 -> -4627.7734 | T45: =R45+S45 -> 47006.018 | U45: =P45-E45*'前提と出典'!$E$5 -> 43700.518 | V45: =Q45-F45*'前提と出典'!$E$5 -> -7741.2949 | W45: =U45+V45 -> 35959.223 | X45: =P45-E45*'前提と出典'!$E$6 -> 35767.245 | Y45: =Q45-F45*'前提と出典'!$E$6 -> -10854.816 | Z45: =X45+Y45 -> 24912.429 | AA45: =IF(T45>=0,A45,1001) -> 41 | AB45: =IF(T45<0,A45,0) -> 0 | AC45: =IF(AND(OR('前提と出典'!$C$36+'前提と出典'!$C$38=0,R45>=0),OR('前提と出典'!$C$37+'前提と出典'!$C$38=0,S45>=0)),0,A45) -> 41 | AD45: =IF(W45>=0,A45,1001) -> 41 | AE45: =IF(W45<0,A45,0) -> 0 | AF45: =IF(AND(OR('前提と出典'!$C$36+'前提と出典'!$C$38=0,U45>=0),OR('前提と出典'!$C$37+'前提と出典'!$C$38=0,V45>=0)),0,A45) -> 41 | AG45: =IF(Z45>=0,A45,1001) -> 41 | AH45: =IF(Z45<0,A45,0) -> 0 | AI45: =IF(AND(OR('前提と出典'!$C$36+'前提と出典'!$C$38=0,X45>=0),OR('前提と出典'!$C$37+'前提と出典'!$C$38=0,Y45>=0)),0,A45) -> 41
A46: 42 | B46: =A46*('前提と出典'!$C$36+'前提と出典'!$C$38) -> 29.4 | C46: =A46*('前提と出典'!$C$37+'前提と出典'!$C$38) -> 25.2 | D46: =A46*('前提と出典'!$C$36*'契約別単価'!C5+'前提と出典'!$C$37*'契約別単価'!C6+'前提と出典'!$C$38*'契約別単価'!C7) -> 302.21229 | E46: =A46*('前提と出典'!$C$36*'契約別単価'!E5+'前提と出典'!$C$37*'契約別単価'!E6+'前提と出典'!$C$38*'契約別単価'!E7) -> 81267.676 | F46: =A46*('前提と出典'!$C$36*'契約別単価'!F5+'前提と出典'!$C$37*'契約別単価'!F6+'前提と出典'!$C$38*'契約別単価'!F7) -> 31894.61 | G46: =A46*('前提と出典'!$C$36*'契約別単価'!G5+'前提と出典'!$C$37*'契約別単価'!G6+'前提と出典'!$C$38*'契約別単価'!G7) -> 83601.117 | H46: =A46*('前提と出典'!$C$36*'契約別単価'!H5+'前提と出典'!$C$37*'契約別単価'!H6+'前提と出典'!$C$38*'契約別単価'!H7) -> 29013.781 | I46: =A46*('前提と出典'!$C$36*'契約別単価'!I5+'前提と出典'!$C$37*'契約別単価'!I6+'前提と出典'!$C$38*'契約別単価'!I7) -> 1772.2123 | J46: =A46*('前提と出典'!$C$36*'契約別単価'!J5+'前提と出典'!$C$37*'契約別単価'!J6+'前提と出典'!$C$38*'契約別単価'!J7) -> 4128.1608 | K46: =A46*('前提と出典'!$C$36*'契約別単価'!K5+'前提と出典'!$C$37*'契約別単価'!K6+'前提と出典'!$C$38*'契約別単価'!K7) -> 17694.749 | L46: =A46*('前提と出典'!$C$36*'契約別単価'!L5+'前提と出典'!$C$37*'契約別単価'!L6+'前提と出典'!$C$38*'契約別単価'!L7) -> 14407.126 | M46: =IF(('前提と出典'!$C$36+'前提と出典'!$C$38)=0,0,IF(B46<=10,'前提と出典'!B73+'前提と出典'!C73,IF(B46<=100,'前提と出典'!B74+'前提と出典'!C74,IF(B46<=500,'前提と出典'!B75+'前提と出典'!C75,'前提と出典'!B76+'前提と出典'!C76)))) -> 20000 | N46: =IF(('前提と出典'!$C$37+'前提と出典'!$C$38)=0,0,IF(C46<=10,'前提と出典'!D73+'前提と出典'!E73,IF(C46<=100,'前提と出典'!D74+'前提と出典'!E74,IF(C46<=500,'前提と出典'!D75+'前提と出典'!E75,'前提と出典'!D76+'前提と出典'!E76)))) -> 34510.935 | O46: =IF('前提と出典'!$C$36+'前提と出典'!$C$38=0,0,'前提と出典'!$B$4*IF('前提と出典'!$B$20=0,MAX('前提と出典'!$B$6,D46*'前提と出典'!$B$5),'前提と出典'!$B$6+D46*'前提と出典'!$B$5)) -> 41705.296 | P46: =(E46+G46)*(1-'前提と出典'!$B$7)-I46-K46-M46-O46 -> 77761.259 | Q46: =(F46+H46)*(1-'前提と出典'!$B$7)-J46-L46-N46 -> 5669.4672 | R46: =P46-E46*'前提と出典'!$E$4 -> 53380.957 | S46: =Q46-F46*'前提と出典'!$E$4 -> -3898.9158 | T46: =R46+S46 -> 49482.041 | U46: =P46-E46*'前提と出典'!$E$5 -> 45254.189 | V46: =Q46-F46*'前提と出典'!$E$5 -> -7088.3768 | W46: =U46+V46 -> 38165.812 | X46: =P46-E46*'前提と出典'!$E$6 -> 37127.422 | Y46: =Q46-F46*'前提と出典'!$E$6 -> -10277.838 | Z46: =X46+Y46 -> 26849.584 | AA46: =IF(T46>=0,A46,1001) -> 42 | AB46: =IF(T46<0,A46,0) -> 0 | AC46: =IF(AND(OR('前提と出典'!$C$36+'前提と出典'!$C$38=0,R46>=0),OR('前提と出典'!$C$37+'前提と出典'!$C$38=0,S46>=0)),0,A46) -> 42 | AD46: =IF(W46>=0,A46,1001) -> 42 | AE46: =IF(W46<0,A46,0) -> 0 | AF46: =IF(AND(OR('前提と出典'!$C$36+'前提と出典'!$C$38=0,U46>=0),OR('前提と出典'!$C$37+'前提と出典'!$C$38=0,V46>=0)),0,A46) -> 42 | AG46: =IF(Z46>=0,A46,1001) -> 42 | AH46: =IF(Z46<0,A46,0) -> 0 | AI46: =IF(AND(OR('前提と出典'!$C$36+'前提と出典'!$C$38=0,X46>=0),OR('前提と出典'!$C$37+'前提と出典'!$C$38=0,Y46>=0)),0,A46) -> 42
A47: 43 | B47: =A47*('前提と出典'!$C$36+'前提と出典'!$C$38) -> 30.1 | C47: =A47*('前提と出典'!$C$37+'前提と出典'!$C$38) -> 25.8 | D47: =A47*('前提と出典'!$C$36*'契約別単価'!C5+'前提と出典'!$C$37*'契約別単価'!C6+'前提と出典'!$C$38*'契約別単価'!C7) -> 309.40782 | E47: =A47*('前提と出典'!$C$36*'契約別単価'!E5+'前提と出典'!$C$37*'契約別単価'!E6+'前提と出典'!$C$38*'契約別単価'!E7) -> 83202.62 | F47: =A47*('前提と出典'!$C$36*'契約別単価'!F5+'前提と出典'!$C$37*'契約別単価'!F6+'前提と出典'!$C$38*'契約別単価'!F7) -> 32654.006 | G47: =A47*('前提と出典'!$C$36*'契約別単価'!G5+'前提と出典'!$C$37*'契約別単価'!G6+'前提と出典'!$C$38*'契約別単価'!G7) -> 85591.62 | H47: =A47*('前提と出典'!$C$36*'契約別単価'!H5+'前提と出典'!$C$37*'契約別単価'!H6+'前提と出典'!$C$38*'契約別単価'!H7) -> 29704.585 | I47: =A47*('前提と出典'!$C$36*'契約別単価'!I5+'前提と出典'!$C$37*'契約別単価'!I6+'前提と出典'!$C$38*'契約別単価'!I7) -> 1814.4078 | J47: =A47*('前提と出典'!$C$36*'契約別単価'!J5+'前提と出典'!$C$37*'契約別単価'!J6+'前提と出典'!$C$38*'契約別単価'!J7) -> 4226.4504 | K47: =A47*('前提と出典'!$C$36*'契約別単価'!K5+'前提と出典'!$C$37*'契約別単価'!K6+'前提と出典'!$C$38*'契約別単価'!K7) -> 18116.052 | L47: =A47*('前提と出典'!$C$36*'契約別単価'!L5+'前提と出典'!$C$37*'契約別単価'!L6+'前提と出典'!$C$38*'契約別単価'!L7) -> 14750.153 | M47: =IF(('前提と出典'!$C$36+'前提と出典'!$C$38)=0,0,IF(B47<=10,'前提と出典'!B73+'前提と出典'!C73,IF(B47<=100,'前提と出典'!B74+'前提と出典'!C74,IF(B47<=500,'前提と出典'!B75+'前提と出典'!C75,'前提と出典'!B76+'前提と出典'!C76)))) -> 20000 | N47: =IF(('前提と出典'!$C$37+'前提と出典'!$C$38)=0,0,IF(C47<=10,'前提と出典'!D73+'前提と出典'!E73,IF(C47<=100,'前提と出典'!D74+'前提と出典'!E74,IF(C47<=500,'前提と出典'!D75+'前提と出典'!E75,'前提と出典'!D76+'前提と出典'!E76)))) -> 34510.935 | O47: =IF('前提と出典'!$C$36+'前提と出典'!$C$38=0,0,'前提と出典'!$B$4*IF('前提と出典'!$B$20=0,MAX('前提と出典'!$B$6,D47*'前提と出典'!$B$5),'前提と出典'!$B$6+D47*'前提と出典'!$B$5)) -> 42698.279 | P47: =(E47+G47)*(1-'前提と出典'!$B$7)-I47-K47-M47-O47 -> 80088.908 | Q47: =(F47+H47)*(1-'前提と出典'!$B$7)-J47-L47-N47 -> 6626.1435 | R47: =P47-E47*'前提と出典'!$E$4 -> 55128.122 | S47: =Q47-F47*'前提と出典'!$E$4 -> -3170.0582 | T47: =R47+S47 -> 51958.064 | U47: =P47-E47*'前提と出典'!$E$5 -> 46807.86 | V47: =Q47-F47*'前提と出典'!$E$5 -> -6435.4588 | W47: =U47+V47 -> 40372.402 | X47: =P47-E47*'前提と出典'!$E$6 -> 38487.598 | Y47: =Q47-F47*'前提と出典'!$E$6 -> -9700.8593 | Z47: =X47+Y47 -> 28786.739 | AA47: =IF(T47>=0,A47,1001) -> 43 | AB47: =IF(T47<0,A47,0) -> 0 | AC47: =IF(AND(OR('前提と出典'!$C$36+'前提と出典'!$C$38=0,R47>=0),OR('前提と出典'!$C$37+'前提と出典'!$C$38=0,S47>=0)),0,A47) -> 43 | AD47: =IF(W47>=0,A47,1001) -> 43 | AE47: =IF(W47<0,A47,0) -> 0 | AF47: =IF(AND(OR('前提と出典'!$C$36+'前提と出典'!$C$38=0,U47>=0),OR('前提と出典'!$C$37+'前提と出典'!$C$38=0,V47>=0)),0,A47) -> 43 | AG47: =IF(Z47>=0,A47,1001) -> 43 | AH47: =IF(Z47<0,A47,0) -> 0 | AI47: =IF(AND(OR('前提と出典'!$C$36+'前提と出典'!$C$38=0,X47>=0),OR('前提と出典'!$C$37+'前提と出典'!$C$38=0,Y47>=0)),0,A47) -> 43
A48: 44 | B48: =A48*('前提と出典'!$C$36+'前提と出典'!$C$38) -> 30.8 | C48: =A48*('前提と出典'!$C$37+'前提と出典'!$C$38) -> 26.4 | D48: =A48*('前提と出典'!$C$36*'契約別単価'!C5+'前提と出典'!$C$37*'契約別単価'!C6+'前提と出典'!$C$38*'契約別単価'!C7) -> 316.60335 | E48: =A48*('前提と出典'!$C$36*'契約別単価'!E5+'前提と出典'!$C$37*'契約別単価'!E6+'前提と出典'!$C$38*'契約別単価'!E7) -> 85137.565 | F48: =A48*('前提と出典'!$C$36*'契約別単価'!F5+'前提と出典'!$C$37*'契約別単価'!F6+'前提と出典'!$C$38*'契約別単価'!F7) -> 33413.401 | G48: =A48*('前提と出典'!$C$36*'契約別単価'!G5+'前提と出典'!$C$37*'契約別単価'!G6+'前提と出典'!$C$38*'契約別単価'!G7) -> 87582.123 | H48: =A48*('前提と出典'!$C$36*'契約別単価'!H5+'前提と出典'!$C$37*'契約別単価'!H6+'前提と出典'!$C$38*'契約別単価'!H7) -> 30395.389 | I48: =A48*('前提と出典'!$C$36*'契約別単価'!I5+'前提と出典'!$C$37*'契約別単価'!I6+'前提と出典'!$C$38*'契約別単価'!I7) -> 1856.6034 | J48: =A48*('前提と出典'!$C$36*'契約別単価'!J5+'前提と出典'!$C$37*'契約別単価'!J6+'前提と出典'!$C$38*'契約別単価'!J7) -> 4324.7399 | K48: =A48*('前提と出典'!$C$36*'契約別単価'!K5+'前提と出典'!$C$37*'契約別単価'!K6+'前提と出典'!$C$38*'契約別単価'!K7) -> 18537.356 | L48: =A48*('前提と出典'!$C$36*'契約別単価'!L5+'前提と出典'!$C$37*'契約別単価'!L6+'前提と出典'!$C$38*'契約別単価'!L7) -> 15093.18 | M48: =IF(('前提と出典'!$C$36+'前提と出典'!$C$38)=0,0,IF(B48<=10,'前提と出典'!B73+'前提と出典'!C73,IF(B48<=100,'前提と出典'!B74+'前提と出典'!C74,IF(B48<=500,'前提と出典'!B75+'前提と出典'!C75,'前提と出典'!B76+'前提と出典'!C76)))) -> 20000 | N48: =IF(('前提と出典'!$C$37+'前提と出典'!$C$38)=0,0,IF(C48<=10,'前提と出典'!D73+'前提と出典'!E73,IF(C48<=100,'前提と出典'!D74+'前提と出典'!E74,IF(C48<=500,'前提と出典'!D75+'前提と出典'!E75,'前提と出典'!D76+'前提と出典'!E76)))) -> 34510.935 | O48: =IF('前提と出典'!$C$36+'前提と出典'!$C$38=0,0,'前提と出典'!$B$4*IF('前提と出典'!$B$20=0,MAX('前提と出典'!$B$6,D48*'前提と出典'!$B$5),'前提と出典'!$B$6+D48*'前提と出典'!$B$5)) -> 43691.263 | P48: =(E48+G48)*(1-'前提と出典'!$B$7)-I48-K48-M48-O48 -> 82416.557 | Q48: =(F48+H48)*(1-'前提と出典'!$B$7)-J48-L48-N48 -> 7582.8197 | R48: =P48-E48*'前提と出典'!$E$4 -> 56875.288 | S48: =Q48-F48*'前提と出典'!$E$4 -> -2441.2006 | T48: =R48+S48 -> 54434.087 | U48: =P48-E48*'前提と出典'!$E$5 -> 48361.531 | V48: =Q48-F48*'前提と出典'!$E$5 -> -5782.5407 | W48: =U48+V48 -> 42578.991 | X48: =P48-E48*'前提と出典'!$E$6 -> 39847.775 | Y48: =Q48-F48*'前提と出典'!$E$6 -> -9123.8809 | Z48: =X48+Y48 -> 30723.894 | AA48: =IF(T48>=0,A48,1001) -> 44 | AB48: =IF(T48<0,A48,0) -> 0 | AC48: =IF(AND(OR('前提と出典'!$C$36+'前提と出典'!$C$38=0,R48>=0),OR('前提と出典'!$C$37+'前提と出典'!$C$38=0,S48>=0)),0,A48) -> 44 | AD48: =IF(W48>=0,A48,1001) -> 44 | AE48: =IF(W48<0,A48,0) -> 0 | AF48: =IF(AND(OR('前提と出典'!$C$36+'前提と出典'!$C$38=0,U48>=0),OR('前提と出典'!$C$37+'前提と出典'!$C$38=0,V48>=0)),0,A48) -> 44 | AG48: =IF(Z48>=0,A48,1001) -> 44 | AH48: =IF(Z48<0,A48,0) -> 0 | AI48: =IF(AND(OR('前提と出典'!$C$36+'前提と出典'!$C$38=0,X48>=0),OR('前提と出典'!$C$37+'前提と出典'!$C$38=0,Y48>=0)),0,A48) -> 44
